Workbook

Sheet VERDICT
B2: ACOLHE — one tender, one answer
B3: =INPUTS!$C$8&" · "&TEXT(INPUTS!$C$5,"#,##0")&" kits · bid "&TEXT(INPUTS!$C$7,"0%")&" of R$"&TEXT(INPUTS!$C$6,"#,##0.00")&" · "&INPUTS!$C$9&" · supplier discount "&TEXT(INPUTS!$C$13,"0%")&" · paid day "&TEXT(INPUTS!$C$10,"0")
B5: VERDICT | C5: =IF(DEAL!$C$12="","NO BID — a cost leg is unknown, so there is no number to judge",IF(DEAL!$C$25<0,"NO — this lot loses money at your bid",IF(DEAL!$C$25<INPUTS!$C$29,"THIN — net "&TEXT(DEAL!$C$25,"0.0%")&" against a "&TEXT(INPUTS!$C$29,"0%")&" target. "&TEXT($C$43,"0")&" of 9 checks not passed.",IF($C$43>0,"PENCILS — but "&TEXT($C$43,"0")&" check(s) not passed. Read them before you bid.","PENCILS — all 9 checks pass"))))
B7: WHAT YOU MAKE
B8: On this one lot, after tax and fees | C8: =DEAL!$C$24 | D8: per kit | E8: =DEAL!$C$26 | G8: Take-home is after the fixed costs on INPUTS.
B9: Per hour of your own time | C9: =DEAL!$C$49 | D9: hours on this lot | E9: =DEAL!$C$48
B10: A YEAR OF LOTS LIKE THIS, take-home | C10: =DEAL!$C$53 | D10: lots a year assumed | E10: =DEAL!$C$50 | G10: Lots per year is an assumption (INPUTS!C32).
B11: …which is, per month | C11: =DEAL!$C$54 | D11: per month in US$ | E11: =DEAL!$C$55
B12: …for this many hours a month | C12: =DEAL!$C$56
B14: IS THAT REAL?
B15: Net margin on this lot | C15: =DEAL!$C$25 | D15: your target | E15: =INPUTS!$C$29
B16: Cash you must front for one lot | C16: =DEAL!$C$29 | D16: days it is out | E16: =DEAL!$C$30
B17: Annualised return on that cash | C17: =DEAL!$C$31
B18: Lots a year your CAPITAL can carry | C18: =DEAL!$C$62 | D18: lots you planned | E18: =DEAL!$C$50 | G18: The real ceiling on income: cash, not tenders.
B19: Revenue that plan implies (RBT12) | C19: =DEAL!$C$64 | D19: Simples rate it puts you in | E19: =DEAL!$C$65
B21: WHERE EVERY REAL OF BID PRICE GOES (per kit)
C22: R$ per kit | D22: % of bid
B23: Bid price per kit | C23: =DEAL!$C$15 | D23: =IF(OR($C$23="",$C$23=0,C23=""),"",C23/$C$23)
B24: Goods, after supplier discount | C24: =DEAL!$C$7 | D24: =IF(OR($C$23="",$C$23=0,C24=""),"",C24/$C$23) | G24: Goods + freight over ~94% and nothing saves it.
B25: Freight | C25: =DEAL!$C$10 | D25: =IF(OR($C$23="",$C$23=0,C25=""),"",C25/$C$23)
B26: Assembly | C26: =DEAL!$C$9 | D26: =IF(OR($C$23="",$C$23=0,C26=""),"",C26/$C$23)
B27: Allowance for unpriced lines + packaging | C27: =DEAL!$C$8+DEAL!$C$11 | D27: =IF(OR($C$23="",$C$23=0,C27=""),"",C27/$C$23)
B28: Simples + IRRF + platform fee | C28: =IF(INPUTS!$C$5=0,"",(DEAL!$C$21+DEAL!$C$22+DEAL!$C$23)/INPUTS!$C$5) | D28: =IF(OR($C$23="",$C$23=0,C28=""),"",C28/$C$23)
B29: LEFT OVER = net profit per kit | C29: =DEAL!$C$26 | D29: =IF(OR($C$23="",$C$23=0,C29=""),"",C29/$C$23)
B31: THE CHECKS — every one must pass
B32: Check | C32: Status | D32: What it would take
B33: 1. Cost is fully known | C33: =IF(DEAL!$C$12="","BLOCKED","PASS") | D33: =IF(DEAL!$C$12="","Assembly or freight is blank. Quote it — a blank is not a zero.","Total cost R$"&TEXT(DEAL!$C$12,"#,##0.00")&" per kit")
B34: 2. The lot makes money | C34: =IF(DEAL!$C$25="","—",IF(DEAL!$C$25<0,"FAIL","PASS")) | D34: =IF(DEAL!$C$25="","Cost unknown",IF(DEAL!$C$25<0,"You would have to bid at least "&TEXT(DEAL!$C$37,"0.0%")&" of estimate just to break even","Break-even bid is "&TEXT(DEAL!$C$37,"0.0%")&" of estimate; you are bidding "&TEXT(INPUTS!$C$7,"0.0%")))
B35: 3. It hits your target margin | C35: =IF(DEAL!$C$25="","—",IF(DEAL!$C$25>=INPUTS!$C$29,"PASS","THIN")) | D35: =IF(DEAL!$C$25="","Cost unknown",IF(DEAL!$C$25>=INPUTS!$C$29,"Clears target with room","Needs "&TEXT(DEAL!$C$40,"0.0%")&" off list from the supplier, OR freight under R$"&TEXT(DEAL!$C$43,"#,##0.00")&" per kit, OR a bid at "&TEXT(DEAL!$C$36,"0.0%")&" of estimate"))
B36: 4. You can fund one lot | C36: =IF(INPUTS!$C$28="","UNKNOWN",IF(DEAL!$C$29="","—",IF(DEAL!$C$29<=INPUTS!$C$28,"PASS","SHORT"))) | D36: =IF(INPUTS!$C$28="","Capital not set — put your real number in INPUTS!C28",IF(DEAL!$C$29="","Cost unknown",IF(DEAL!$C$29<=INPUTS!$C$28,"Needs R$"&TEXT(DEAL!$C$29,"#,##0")&" of the R$"&TEXT(INPUTS!$C$28,"#,##0")&" you have","Short by R$"&TEXT(DEAL!$C$29-INPUTS!$C$28,"#,##0")&" for "&TEXT(INPUTS!$C$10,"0")&" days")))
B37: 5. Your capital can carry the year you planned | C37: =IF(OR(DEAL!$C$62="",DEAL!$C$62=0),"UNKNOWN",IF(DEAL!$C$62>=DEAL!$C$50,"PASS","CAPPED")) | D37: =IF(OR(DEAL!$C$62="",DEAL!$C$62=0),"Set capital on INPUTS!C28 to answer this",IF(DEAL!$C$62>=DEAL!$C$50,"Capital supports "&TEXT(DEAL!$C$62,"#,##0.0")&" lots a year; you planned "&TEXT(DEAL!$C$50,"#,##0"),"Capital supports only "&TEXT(DEAL!$C$62,"#,##0.0")&" lots a year, not "&TEXT(DEAL!$C$50,"#,##0")&". Income is capped by cash, not by tenders. Supplier terms fix this for free; a loan costs money"))
B38: 6. You can pack it yourself | C38: =IF(INPUTS!$C$5<=INPUTS!$C$20,"PASS","NEEDS CO-PACKER") | D38: =IF(INPUTS!$C$5<=INPUTS!$C$20,TEXT(INPUTS!$C$5,"#,##0")&" kits is inside the "&TEXT(INPUTS!$C$20,"#,##0")&"-kit self-pack ceiling","Lot of "&TEXT(INPUTS!$C$5,"#,##0")&" exceeds the "&TEXT(INPUTS!$C$20,"#,##0")&"-kit ceiling. No SP co-packer publishes a price — get one before you bid")
B39: 7. The BOM is fully priced | C39: =IF(BOM!$E$23=0,"PASS","OPEN") | D39: =IF(BOM!$E$23=0,"All 17 lines priced",TEXT(BOM!$E$23,"0")&" line(s) unpriced. You are carrying R$"&TEXT(INPUTS!$C$17,"#,##0.00")&" of allowance against them — a guess, not a quote")
B40: 8. Freight is measured for this UF and mode | C40: =IF(INPUTS!$C$14<>"","PASS",IF(FREIGHT!$B$8="","NOT MEASURED","PASS")) | D40: =IF(INPUTS!$C$14<>"","Using your quoted override of R$"&TEXT(INPUTS!$C$14,"#,##0.00"),IF(FREIGHT!$B$8="","No measured rate for "&INPUTS!$C$8&" by "&INPUTS!$C$9&". Quote it, or change the mode","R$"&TEXT(FREIGHT!$B$8,"#,##0.00")&" per kit, measured to the CAPITAL CEP only — interior will differ"))
B41: 9. The tax bracket matches the year you planned | C41: =IF(ABS(DEAL!$C$65-DEAL!$C$20)<0.0001,"PASS","UNDERSTATED") | D41: =IF(ABS(DEAL!$C$65-DEAL!$C$20)<0.0001,"RBT12 on INPUTS matches the "&TEXT(DEAL!$C$64,"#,##0")&" of revenue your plan implies","You are taxed at "&TEXT(DEAL!$C$20,"0.00%")&" but "&TEXT(DEAL!$C$50,"#,##0")&" lots implies R$"&TEXT(DEAL!$C$64,"#,##0")&" of revenue, which is the "&TEXT(DEAL!$C$65,"0.00%")&" bracket. Raise INPUTS!C23")
B43: Checks not passed | C43: =SUMPRODUCT(--($C$33:$C$41<>"PASS")) | D43: out of 9
B45: WHAT WOULD HAVE TO BE TRUE
B46: Supplier discount off list needed to hit target | C46: =DEAL!$C$40 | D46: The single biggest lever in the model. 45% is the UNVERIFIED account-tier figure.
B47: Supplier discount needed merely to break even | C47: =DEAL!$C$42 | D47: Negative means list price alone already breaks even.
B48: Max freight per kit at target margin | C48: =DEAL!$C$43 | D48: Negative means no freight price on earth saves this bid.
B49: Max freight per kit to break even | C49: =DEAL!$C$44
B50: Bid as % of estimate needed for target margin | C50: =DEAL!$C$36 | D50: Above ~97% the lot cannot be won: per-item lines clear at 97–100%.
B51: Bid as % of estimate to break even | C51: =DEAL!$C$37
B53: STILL PRICED AT ZERO — read before you trust any of the above
B54: Unpriced BOM lines | C54: =BOM!$E$23 | D54: The kit bag. Allowance carried: | E54: =INPUTS!$C$17
B55: Co-packer cost per kit | C55: =IF(INPUTS!$C$19="","NOT QUOTED",INPUTS!$C$19) | D55: Only bites above the self-pack ceiling.
B56: Packaging / box / label | C56: =INPUTS!$C$18 | D56: A 60×40×40 box is not free.
B57: Annual fixed costs assumed | C57: =INPUTS!$C$33 | D57: Contador, e-CNPJ, site, server. Estimated, not quoted.
B59: Blue on yellow = you type it, and only on INPUTS. Green = pulled from another sheet. Black = formula. Do not type over black cells.

Sheet INPUTS
B2: INPUTS — the only sheet you type on
B3: Every yellow cell is a number you choose or measure. Nothing anywhere else in this workbook is typed. One tender per copy of this file.
B4: THE TENDER
B5: Kits in the lot (quantidade) | C5: 61 | D5: For an SRP, the quantity you actually expect to be called off — not the ceiling.
B6: Buyer's estimated price per kit (valor estimado) | C6: 359.05 | D6: From the edital. R$359,05 was the Itaquaquecetuba 2025 estimate for a 17-item kit.
B7: My bid as % of the estimate | C7: 0.9 | D7: Per-item lines clear at 97–100% of estimate; lote unico at 36–63%.
B8: Buyer UF | C8: CE | D8: Two letters. Drives freight and transit from the FREIGHT sheet.
B9: Delivery mode: LTL or PARCEL | C9: LTL | D9: LTL only when the edital delivers the WHOLE lot to ONE address in one go. 'Parcelado' or per-ordem addresses = PARCEL.
B10: Days from empenho to cash in the bank | C10: 45 | D10: Measured on 7 editais: 34 best, 40–55 typical, 69 worst (docs/ORDER_TO_CASH.md).
B12: THE TWO LEVERS THAT DECIDE THIS DEAL
B13: Supplier discount off list (account tier) | C13: 0 | D13: 0% until an account is opened. ~45% is the UNVERIFIED account-tier figure — do not use it until it is quoted in writing.
B14: Freight per kit OVERRIDE (blank = use the table) | D14: A real quoted figure typed here replaces the FREIGHT table for this deal.
B16: COSTS NOT YET IN THE BOM
B17: Allowance for unpriced BOM lines | C17: 0 | D17: BOM has 1 unpriced line (the kit bag). Leaving this at 0 means bidding as if the bag is free.
B18: Packaging / box / label per kit | C18: 0 | D18: Not yet costed.
B19: Co-packer cost per kit (only if lot > ceiling) | D19: NO QUOTE EXISTS — 24 SP providers surveyed, none publishes a price. Blank = unknown, and the verdict blocks rather than assuming zero.
B20: Self-pack ceiling (kits you can pack per order) | C20: 240 | D20: config/capital.yaml: 8 h per won order at 2 min/kit.
B22: TAX, FEES, CAPITAL
B23: Revenue last 12 months (RBT12) | C23: 180000 | D23: Anexo I efetivo: ≤180k 4,00% · 360k 5,65% · 720k 7,58% · 1,8M ~9,1% · 3,6M ~11,9%. Tem de bater com a receita do ano que você planeia — é o que a verificação 9 compara.
B24: IRRF withheld by the buyer | C24: 0 | D24: 0% if the IN RFB 1.234 Anexo IV declaration is filed with every contract. 1,2% if it is not — and there is no refund path.
B25: Platform fee as % of lot value | C25: 0.015 | D25: BLL: 1,5% of the lote adjudicado, only on a win. Compras.gov.br: 0%.
B26: Platform fee cap (R$) | C26: 600 | D26: BLL caps at R$600 when the lote exceeds R$40.000. Use a huge number for no cap.
B27: Platform fixed fee per process (R$) | C27: 0 | D27: BNC R$118,80 / PCP R$129 per process, charged even when you lose. BLL and Compras.gov.br: 0.
B28: Capital available (R$) | C28: 15600 | D28: From the written plan. Confirm it — every capacity number in the model moves with this one cell. Blank it out and checks 4 and 5 say UNKNOWN instead of guessing.
B29: Target NET margin | C29: 0.15 | D29: What 'pencils' means to you. Change it and everything the verdict demands moves with it.
B31: TURNING ONE DEAL INTO A YEAR — this is what you actually take home
B32: Lots like this you expect to win in a year | C32: 8 | D32: The written plan's figure. It is an assumption: Brazil publishes winners, never losers, so no one can measure a win rate until they have bid. Check 5 tests it against your capital.
B33: Annual fixed costs (R$) | C33: 6000 | D33: Contador ~R$300/mo = 3.600, e-CNPJ ~250, domain + site ~300, server ~360, contingency. Estimated, not quoted.
B34: Your hours per won order | C34: 8 | D34: Constraint C9 in the plan: 8 h per won order, sourcing to shipping.
B35: BRL per USD | C35: 5.2 | D35: The rate implied by the written plan's US$ figures. Check the spot rate before quoting it to anyone.

Sheet DEAL
B2: DEAL — the arithmetic. Nothing on this sheet is typed.
B4: COST PER KIT
B5: Goods at list price (BOM total) | C5: =BOM!$E$22 | D5: Sum of the priced BOM lines.
B6: less supplier discount | C6: =-C5*INPUTS!$C$13
B7: Goods after discount | C7: =C5+C6
B8: Allowance for unpriced BOM lines | C8: =INPUTS!$C$17
B9: Assembly | C9: =IF(INPUTS!$C$5<=INPUTS!$C$20,0,IF(INPUTS!$C$19="","",INPUTS!$C$19)) | D9: 0 when you pack it yourself; the co-packer figure otherwise; blank = unknown.
B10: Freight per kit used | C10: =IF(INPUTS!$C$14<>"",INPUTS!$C$14,IF(FREIGHT!$B$8="","",FREIGHT!$B$8)) | D10: Your override if set, otherwise the measured table for this UF and mode.
B11: Packaging / box / label | C11: =INPUTS!$C$18
B12: TOTAL COST PER KIT | C12: =IF(OR(C9="",C10=""),"",C7+C8+C9+C10+C11) | D12: Blank means a cost leg is unknown — that is a NO BID, not a zero.
B14: THE LOT
B15: Bid price per kit | C15: =INPUTS!$C$6*INPUTS!$C$7
B16: Revenue (lot) | C16: =C15*INPUTS!$C$5
B17: Cost of goods + freight + assembly (lot) | C17: =IF(C12="","",C12*INPUTS!$C$5)
B18: Gross profit (lot) | C18: =IF(C17="","",C16-C17)
B19: Gross margin % | C19: =IF(C18="","",IF(C16=0,0,C18/C16))
B20: Simples Nacional effective rate | C20: =IF(INPUTS!$C$23<=0,0.04,IF(INPUTS!$C$23<=180000,0.04,IF(INPUTS!$C$23<=360000,(INPUTS!$C$23*0.073-5940)/INPUTS!$C$23,IF(INPUTS!$C$23<=720000,(INPUTS!$C$23*0.095-13860)/INPUTS!$C$23,IF(INPUTS!$C$23<=1800000,(INPUTS!$C$23*0.107-22500)/INPUTS!$C$23,IF(INPUTS!$C$23<=3600000,(INPUTS!$C$23*0.143-87300)/INPUTS!$C$23,(INPUTS!$C$23*0.19-378000)/INPUTS!$C$23)))))) | D20: LC 123 Anexo I, alíquota EFETIVA = (RBT12 x nominal - dedução)/RBT12. Cobre as seis faixas até R$4,8M.
B21: Simples tax | C21: =C16*C20
B22: IRRF withheld | C22: =C16*INPUTS!$C$24
B23: Platform fee | C23: =MIN(C16*INPUTS!$C$25,INPUTS!$C$26)+INPUTS!$C$27
B24: NET PROFIT (lot) | C24: =IF(C18="","",C18-C21-C22-C23)
B25: NET MARGIN % | C25: =IF(C24="","",IF(C16=0,0,C24/C16))
B26: Net profit per kit | C26: =IF(C24="","",C24/INPUTS!$C$5)
B28: CASH
B29: Cash you must front before the buyer pays | C29: =IF(C17="","",C17+INPUTS!$C$27) | D29: Goods, freight, assembly and any fixed fee all leave before the empenho pays out.
B30: Days that cash is out | C30: =INPUTS!$C$10 | D30: Conservative: assumes cash leaves on day 0. In practice the supplier is paid nearer day 11, so the true return is higher.
B31: Annualised return on that cash | C31: =IF(OR(C24="",C29=""),"",IF(C29=0,0,C24/C29*365/C30))
B33: WHAT WOULD HAVE TO BE TRUE
B34: Break-even price per kit | C34: =IF(C12="","",(C12+INPUTS!$C$27/INPUTS!$C$5)/(1-C20-INPUTS!$C$24-INPUTS!$C$25)) | D34: Ignores the platform fee cap, so it runs slightly conservative.
B35: Price per kit at your target margin | C35: =IF(C12="","",(C12+INPUTS!$C$27/INPUTS!$C$5)/(1-C20-INPUTS!$C$24-INPUTS!$C$25-INPUTS!$C$29))
B36: …as % of the buyer's estimate | C36: =IF(C35="","",C35/INPUTS!$C$6) | D36: Above ~97% the lot cannot be won at target.
B37: Minimum bid as % of estimate to break even | C37: =IF(C34="","",C34/INPUTS!$C$6)
B38: Max TOTAL cost per kit at your bid, at target | C38: =C15*(1-C20-INPUTS!$C$24-INPUTS!$C$25-INPUTS!$C$29)-INPUTS!$C$27/INPUTS!$C$5
B39: Max GOODS cost per kit at target | C39: =IF(OR(C9="",C10=""),"",C38-C8-C9-C10-C11)
B40: Supplier discount needed to hit target | C40: =IF(OR(C39="",C5=0),"",1-C39/C5) | D40: The number to take into a wholesaler meeting.
B41: Max TOTAL cost per kit at break-even | C41: =C15*(1-C20-INPUTS!$C$24-INPUTS!$C$25)-INPUTS!$C$27/INPUTS!$C$5
B42: Supplier discount needed to break even | C42: =IF(OR(C9="",C10="",C5=0),"",1-(C41-C8-C9-C10-C11)/C5)
B43: Max freight per kit at target (rest of cost fixed) | C43: =IF(C9="","",C38-C7-C8-C9-C11) | D43: Negative = no freight price saves this bid.
B44: Max freight per kit at break-even | C44: =IF(C9="","",C41-C7-C8-C9-C11)
B46: WHAT YOU MAKE — one lot scaled into a year
B47: Net profit per lot | C47: =IF(C24="","",C24)
B48: Your hours per won order | C48: =INPUTS!$C$34
B49: Pay per hour of your own time | C49: =IF(OR(C47="",C48=0),"",C47/C48) | D49: Compare this against what an hour of your time is worth elsewhere.
B50: Lots like this you plan to win in a year | C50: =INPUTS!$C$32 | D50: Set to what the capital actually allows (see check 5), not to a hope.
B51: Net profit from those lots | C51: =IF(C47="","",C47*C50)
B52: less annual fixed costs | C52: =-INPUTS!$C$33
B53: TAKE-HOME, per year | C53: =IF(C51="","",C51+C52)
B54: TAKE-HOME, per month | C54: =IF(C53="","",C53/12)
B55: …in US$ per month | C55: =IF(OR(C54="",INPUTS!$C$35=0),"",C54/INPUTS!$C$35)
B56: Hours a month that takes | C56: =C48*C50/12
B58: CAN YOUR CAPITAL ACTUALLY RUN THAT MANY LOTS?
B59: Cash tied up per lot | C59: =IF(C29="","",C29)
B60: Lots you can carry at once | C60: =IF(OR(INPUTS!$C$28="",C59="",C59=0),"",INPUTS!$C$28/C59) | D60: Capital divided by the cash one lot consumes.
B61: Days each lot ties that cash up | C61: =INPUTS!$C$10
B62: Lots a year your capital allows | C62: =IF(OR(C60="",C61=0),"",C60*365/C61) | D62: This, not the number of tenders published, is the ceiling on income.
B63: Gap against the year you planned | C63: =IF(C62="","",C62-C50) | D63: Negative means supplier terms or a credit line is the only way to the planned number.
B64: Revenue your planned year implies | C64: =C16*C50 | D64: Feeds check 9.
B65: Simples rate that revenue implies | C65: =IF(C64<=0,0.04,IF(C64<=180000,0.04,IF(C64<=360000,(C64*0.073-5940)/C64,IF(C64<=720000,(C64*0.095-13860)/C64,IF(C64<=1800000,(C64*0.107-22500)/C64,IF(C64<=3600000,(C64*0.143-87300)/C64,(C64*0.19-378000)/C64))))))
B66: Simples rate you are actually modelling | C66: =C20 | D66: If these two differ, the net margin above is too flattering.

Sheet GATES
B2: GATES — net margin under the two things you do not control
B3: Your target net margin | C3: =INPUTS!$C$29 | D3: Green = clears your target. Amber = makes money but misses it. Red = loses money.
B5: GRID A — supplier discount × freight per kit (at your current bid level)
B6: discount off list ↓ freight per kit → | C6: ="YOUR "&INPUTS!$C$8&" "&INPUTS!$C$9 | D6: ="LTL SP→CE" | E6: ="PAC to BA" | F6: ="PAC to CE/PE/PA" | G6: ="PAC to MA/SE/RN" | H6: ="Zero freight (reference)"
C7: =DEAL!$C$10 | D7: 53.99 | E7: 132.9 | F7: 152.6 | G7: 188.4 | H7: 0
B8: 0 | C8: =IF(OR(DEAL!$C$9="",C$7=""),"",1-((BOM!$E$22*(1-$B8)+INPUTS!$C$17+DEAL!$C$9+C$7+INPUTS!$C$18)+INPUTS!$C$27/INPUTS!$C$5)/DEAL!$C$15-DEAL!$C$20-INPUTS!$C$24-INPUTS!$C$25) | D8: =IF(OR(DEAL!$C$9="",D$7=""),"",1-((BOM!$E$22*(1-$B8)+INPUTS!$C$17+DEAL!$C$9+D$7+INPUTS!$C$18)+INPUTS!$C$27/INPUTS!$C$5)/DEAL!$C$15-DEAL!$C$20-INPUTS!$C$24-INPUTS!$C$25) | E8: =IF(OR(DEAL!$C$9="",E$7=""),"",1-((BOM!$E$22*(1-$B8)+INPUTS!$C$17+DEAL!$C$9+E$7+INPUTS!$C$18)+INPUTS!$C$27/INPUTS!$C$5)/DEAL!$C$15-DEAL!$C$20-INPUTS!$C$24-INPUTS!$C$25) | F8: =IF(OR(DEAL!$C$9="",F$7=""),"",1-((BOM!$E$22*(1-$B8)+INPUTS!$C$17+DEAL!$C$9+F$7+INPUTS!$C$18)+INPUTS!$C$27/INPUTS!$C$5)/DEAL!$C$15-DEAL!$C$20-INPUTS!$C$24-INPUTS!$C$25) | G8: =IF(OR(DEAL!$C$9="",G$7=""),"",1-((BOM!$E$22*(1-$B8)+INPUTS!$C$17+DEAL!$C$9+G$7+INPUTS!$C$18)+INPUTS!$C$27/INPUTS!$C$5)/DEAL!$C$15-DEAL!$C$20-INPUTS!$C$24-INPUTS!$C$25) | H8: =IF(OR(DEAL!$C$9="",H$7=""),"",1-((BOM!$E$22*(1-$B8)+INPUTS!$C$17+DEAL!$C$9+H$7+INPUTS!$C$18)+INPUTS!$C$27/INPUTS!$C$5)/DEAL!$C$15-DEAL!$C$20-INPUTS!$C$24-INPUTS!$C$25)
B9: 0.05 | C9: =IF(OR(DEAL!$C$9="",C$7=""),"",1-((BOM!$E$22*(1-$B9)+INPUTS!$C$17+DEAL!$C$9+C$7+INPUTS!$C$18)+INPUTS!$C$27/INPUTS!$C$5)/DEAL!$C$15-DEAL!$C$20-INPUTS!$C$24-INPUTS!$C$25) | D9: =IF(OR(DEAL!$C$9="",D$7=""),"",1-((BOM!$E$22*(1-$B9)+INPUTS!$C$17+DEAL!$C$9+D$7+INPUTS!$C$18)+INPUTS!$C$27/INPUTS!$C$5)/DEAL!$C$15-DEAL!$C$20-INPUTS!$C$24-INPUTS!$C$25) | E9: =IF(OR(DEAL!$C$9="",E$7=""),"",1-((BOM!$E$22*(1-$B9)+INPUTS!$C$17+DEAL!$C$9+E$7+INPUTS!$C$18)+INPUTS!$C$27/INPUTS!$C$5)/DEAL!$C$15-DEAL!$C$20-INPUTS!$C$24-INPUTS!$C$25) | F9: =IF(OR(DEAL!$C$9="",F$7=""),"",1-((BOM!$E$22*(1-$B9)+INPUTS!$C$17+DEAL!$C$9+F$7+INPUTS!$C$18)+INPUTS!$C$27/INPUTS!$C$5)/DEAL!$C$15-DEAL!$C$20-INPUTS!$C$24-INPUTS!$C$25) | G9: =IF(OR(DEAL!$C$9="",G$7=""),"",1-((BOM!$E$22*(1-$B9)+INPUTS!$C$17+DEAL!$C$9+G$7+INPUTS!$C$18)+INPUTS!$C$27/INPUTS!$C$5)/DEAL!$C$15-DEAL!$C$20-INPUTS!$C$24-INPUTS!$C$25) | H9: =IF(OR(DEAL!$C$9="",H$7=""),"",1-((BOM!$E$22*(1-$B9)+INPUTS!$C$17+DEAL!$C$9+H$7+INPUTS!$C$18)+INPUTS!$C$27/INPUTS!$C$5)/DEAL!$C$15-DEAL!$C$20-INPUTS!$C$24-INPUTS!$C$25)
B10: 0.1 | C10: =IF(OR(DEAL!$C$9="",C$7=""),"",1-((BOM!$E$22*(1-$B10)+INPUTS!$C$17+DEAL!$C$9+C$7+INPUTS!$C$18)+INPUTS!$C$27/INPUTS!$C$5)/DEAL!$C$15-DEAL!$C$20-INPUTS!$C$24-INPUTS!$C$25) | D10: =IF(OR(DEAL!$C$9="",D$7=""),"",1-((BOM!$E$22*(1-$B10)+INPUTS!$C$17+DEAL!$C$9+D$7+INPUTS!$C$18)+INPUTS!$C$27/INPUTS!$C$5)/DEAL!$C$15-DEAL!$C$20-INPUTS!$C$24-INPUTS!$C$25) | E10: =IF(OR(DEAL!$C$9="",E$7=""),"",1-((BOM!$E$22*(1-$B10)+INPUTS!$C$17+DEAL!$C$9+E$7+INPUTS!$C$18)+INPUTS!$C$27/INPUTS!$C$5)/DEAL!$C$15-DEAL!$C$20-INPUTS!$C$24-INPUTS!$C$25) | F10: =IF(OR(DEAL!$C$9="",F$7=""),"",1-((BOM!$E$22*(1-$B10)+INPUTS!$C$17+DEAL!$C$9+F$7+INPUTS!$C$18)+INPUTS!$C$27/INPUTS!$C$5)/DEAL!$C$15-DEAL!$C$20-INPUTS!$C$24-INPUTS!$C$25) | G10: =IF(OR(DEAL!$C$9="",G$7=""),"",1-((BOM!$E$22*(1-$B10)+INPUTS!$C$17+DEAL!$C$9+G$7+INPUTS!$C$18)+INPUTS!$C$27/INPUTS!$C$5)/DEAL!$C$15-DEAL!$C$20-INPUTS!$C$24-INPUTS!$C$25) | H10: =IF(OR(DEAL!$C$9="",H$7=""),"",1-((BOM!$E$22*(1-$B10)+INPUTS!$C$17+DEAL!$C$9+H$7+INPUTS!$C$18)+INPUTS!$C$27/INPUTS!$C$5)/DEAL!$C$15-DEAL!$C$20-INPUTS!$C$24-INPUTS!$C$25)
B11: 0.15 | C11: =IF(OR(DEAL!$C$9="",C$7=""),"",1-((BOM!$E$22*(1-$B11)+INPUTS!$C$17+DEAL!$C$9+C$7+INPUTS!$C$18)+INPUTS!$C$27/INPUTS!$C$5)/DEAL!$C$15-DEAL!$C$20-INPUTS!$C$24-INPUTS!$C$25) | D11: =IF(OR(DEAL!$C$9="",D$7=""),"",1-((BOM!$E$22*(1-$B11)+INPUTS!$C$17+DEAL!$C$9+D$7+INPUTS!$C$18)+INPUTS!$C$27/INPUTS!$C$5)/DEAL!$C$15-DEAL!$C$20-INPUTS!$C$24-INPUTS!$C$25) | E11: =IF(OR(DEAL!$C$9="",E$7=""),"",1-((BOM!$E$22*(1-$B11)+INPUTS!$C$17+DEAL!$C$9+E$7+INPUTS!$C$18)+INPUTS!$C$27/INPUTS!$C$5)/DEAL!$C$15-DEAL!$C$20-INPUTS!$C$24-INPUTS!$C$25) | F11: =IF(OR(DEAL!$C$9="",F$7=""),"",1-((BOM!$E$22*(1-$B11)+INPUTS!$C$17+DEAL!$C$9+F$7+INPUTS!$C$18)+INPUTS!$C$27/INPUTS!$C$5)/DEAL!$C$15-DEAL!$C$20-INPUTS!$C$24-INPUTS!$C$25) | G11: =IF(OR(DEAL!$C$9="",G$7=""),"",1-((BOM!$E$22*(1-$B11)+INPUTS!$C$17+DEAL!$C$9+G$7+INPUTS!$C$18)+INPUTS!$C$27/INPUTS!$C$5)/DEAL!$C$15-DEAL!$C$20-INPUTS!$C$24-INPUTS!$C$25) | H11: =IF(OR(DEAL!$C$9="",H$7=""),"",1-((BOM!$E$22*(1-$B11)+INPUTS!$C$17+DEAL!$C$9+H$7+INPUTS!$C$18)+INPUTS!$C$27/INPUTS!$C$5)/DEAL!$C$15-DEAL!$C$20-INPUTS!$C$24-INPUTS!$C$25)
B12: 0.2 | C12: =IF(OR(DEAL!$C$9="",C$7=""),"",1-((BOM!$E$22*(1-$B12)+INPUTS!$C$17+DEAL!$C$9+C$7+INPUTS!$C$18)+INPUTS!$C$27/INPUTS!$C$5)/DEAL!$C$15-DEAL!$C$20-INPUTS!$C$24-INPUTS!$C$25) | D12: =IF(OR(DEAL!$C$9="",D$7=""),"",1-((BOM!$E$22*(1-$B12)+INPUTS!$C$17+DEAL!$C$9+D$7+INPUTS!$C$18)+INPUTS!$C$27/INPUTS!$C$5)/DEAL!$C$15-DEAL!$C$20-INPUTS!$C$24-INPUTS!$C$25) | E12: =IF(OR(DEAL!$C$9="",E$7=""),"",1-((BOM!$E$22*(1-$B12)+INPUTS!$C$17+DEAL!$C$9+E$7+INPUTS!$C$18)+INPUTS!$C$27/INPUTS!$C$5)/DEAL!$C$15-DEAL!$C$20-INPUTS!$C$24-INPUTS!$C$25) | F12: =IF(OR(DEAL!$C$9="",F$7=""),"",1-((BOM!$E$22*(1-$B12)+INPUTS!$C$17+DEAL!$C$9+F$7+INPUTS!$C$18)+INPUTS!$C$27/INPUTS!$C$5)/DEAL!$C$15-DEAL!$C$20-INPUTS!$C$24-INPUTS!$C$25) | G12: =IF(OR(DEAL!$C$9="",G$7=""),"",1-((BOM!$E$22*(1-$B12)+INPUTS!$C$17+DEAL!$C$9+G$7+INPUTS!$C$18)+INPUTS!$C$27/INPUTS!$C$5)/DEAL!$C$15-DEAL!$C$20-INPUTS!$C$24-INPUTS!$C$25) | H12: =IF(OR(DEAL!$C$9="",H$7=""),"",1-((BOM!$E$22*(1-$B12)+INPUTS!$C$17+DEAL!$C$9+H$7+INPUTS!$C$18)+INPUTS!$C$27/INPUTS!$C$5)/DEAL!$C$15-DEAL!$C$20-INPUTS!$C$24-INPUTS!$C$25)
B13: 0.25 | C13: =IF(OR(DEAL!$C$9="",C$7=""),"",1-((BOM!$E$22*(1-$B13)+INPUTS!$C$17+DEAL!$C$9+C$7+INPUTS!$C$18)+INPUTS!$C$27/INPUTS!$C$5)/DEAL!$C$15-DEAL!$C$20-INPUTS!$C$24-INPUTS!$C$25) | D13: =IF(OR(DEAL!$C$9="",D$7=""),"",1-((BOM!$E$22*(1-$B13)+INPUTS!$C$17+DEAL!$C$9+D$7+INPUTS!$C$18)+INPUTS!$C$27/INPUTS!$C$5)/DEAL!$C$15-DEAL!$C$20-INPUTS!$C$24-INPUTS!$C$25) | E13: =IF(OR(DEAL!$C$9="",E$7=""),"",1-((BOM!$E$22*(1-$B13)+INPUTS!$C$17+DEAL!$C$9+E$7+INPUTS!$C$18)+INPUTS!$C$27/INPUTS!$C$5)/DEAL!$C$15-DEAL!$C$20-INPUTS!$C$24-INPUTS!$C$25) | F13: =IF(OR(DEAL!$C$9="",F$7=""),"",1-((BOM!$E$22*(1-$B13)+INPUTS!$C$17+DEAL!$C$9+F$7+INPUTS!$C$18)+INPUTS!$C$27/INPUTS!$C$5)/DEAL!$C$15-DEAL!$C$20-INPUTS!$C$24-INPUTS!$C$25) | G13: =IF(OR(DEAL!$C$9="",G$7=""),"",1-((BOM!$E$22*(1-$B13)+INPUTS!$C$17+DEAL!$C$9+G$7+INPUTS!$C$18)+INPUTS!$C$27/INPUTS!$C$5)/DEAL!$C$15-DEAL!$C$20-INPUTS!$C$24-INPUTS!$C$25) | H13: =IF(OR(DEAL!$C$9="",H$7=""),"",1-((BOM!$E$22*(1-$B13)+INPUTS!$C$17+DEAL!$C$9+H$7+INPUTS!$C$18)+INPUTS!$C$27/INPUTS!$C$5)/DEAL!$C$15-DEAL!$C$20-INPUTS!$C$24-INPUTS!$C$25)
B14: 0.3 | C14: =IF(OR(DEAL!$C$9="",C$7=""),"",1-((BOM!$E$22*(1-$B14)+INPUTS!$C$17+DEAL!$C$9+C$7+INPUTS!$C$18)+INPUTS!$C$27/INPUTS!$C$5)/DEAL!$C$15-DEAL!$C$20-INPUTS!$C$24-INPUTS!$C$25) | D14: =IF(OR(DEAL!$C$9="",D$7=""),"",1-((BOM!$E$22*(1-$B14)+INPUTS!$C$17+DEAL!$C$9+D$7+INPUTS!$C$18)+INPUTS!$C$27/INPUTS!$C$5)/DEAL!$C$15-DEAL!$C$20-INPUTS!$C$24-INPUTS!$C$25) | E14: =IF(OR(DEAL!$C$9="",E$7=""),"",1-((BOM!$E$22*(1-$B14)+INPUTS!$C$17+DEAL!$C$9+E$7+INPUTS!$C$18)+INPUTS!$C$27/INPUTS!$C$5)/DEAL!$C$15-DEAL!$C$20-INPUTS!$C$24-INPUTS!$C$25) | F14: =IF(OR(DEAL!$C$9="",F$7=""),"",1-((BOM!$E$22*(1-$B14)+INPUTS!$C$17+DEAL!$C$9+F$7+INPUTS!$C$18)+INPUTS!$C$27/INPUTS!$C$5)/DEAL!$C$15-DEAL!$C$20-INPUTS!$C$24-INPUTS!$C$25) | G14: =IF(OR(DEAL!$C$9="",G$7=""),"",1-((BOM!$E$22*(1-$B14)+INPUTS!$C$17+DEAL!$C$9+G$7+INPUTS!$C$18)+INPUTS!$C$27/INPUTS!$C$5)/DEAL!$C$15-DEAL!$C$20-INPUTS!$C$24-INPUTS!$C$25) | H14: =IF(OR(DEAL!$C$9="",H$7=""),"",1-((BOM!$E$22*(1-$B14)+INPUTS!$C$17+DEAL!$C$9+H$7+INPUTS!$C$18)+INPUTS!$C$27/INPUTS!$C$5)/DEAL!$C$15-DEAL!$C$20-INPUTS!$C$24-INPUTS!$C$25)
B15: 0.35 | C15: =IF(OR(DEAL!$C$9="",C$7=""),"",1-((BOM!$E$22*(1-$B15)+INPUTS!$C$17+DEAL!$C$9+C$7+INPUTS!$C$18)+INPUTS!$C$27/INPUTS!$C$5)/DEAL!$C$15-DEAL!$C$20-INPUTS!$C$24-INPUTS!$C$25) | D15: =IF(OR(DEAL!$C$9="",D$7=""),"",1-((BOM!$E$22*(1-$B15)+INPUTS!$C$17+DEAL!$C$9+D$7+INPUTS!$C$18)+INPUTS!$C$27/INPUTS!$C$5)/DEAL!$C$15-DEAL!$C$20-INPUTS!$C$24-INPUTS!$C$25) | E15: =IF(OR(DEAL!$C$9="",E$7=""),"",1-((BOM!$E$22*(1-$B15)+INPUTS!$C$17+DEAL!$C$9+E$7+INPUTS!$C$18)+INPUTS!$C$27/INPUTS!$C$5)/DEAL!$C$15-DEAL!$C$20-INPUTS!$C$24-INPUTS!$C$25) | F15: =IF(OR(DEAL!$C$9="",F$7=""),"",1-((BOM!$E$22*(1-$B15)+INPUTS!$C$17+DEAL!$C$9+F$7+INPUTS!$C$18)+INPUTS!$C$27/INPUTS!$C$5)/DEAL!$C$15-DEAL!$C$20-INPUTS!$C$24-INPUTS!$C$25) | G15: =IF(OR(DEAL!$C$9="",G$7=""),"",1-((BOM!$E$22*(1-$B15)+INPUTS!$C$17+DEAL!$C$9+G$7+INPUTS!$C$18)+INPUTS!$C$27/INPUTS!$C$5)/DEAL!$C$15-DEAL!$C$20-INPUTS!$C$24-INPUTS!$C$25) | H15: =IF(OR(DEAL!$C$9="",H$7=""),"",1-((BOM!$E$22*(1-$B15)+INPUTS!$C$17+DEAL!$C$9+H$7+INPUTS!$C$18)+INPUTS!$C$27/INPUTS!$C$5)/DEAL!$C$15-DEAL!$C$20-INPUTS!$C$24-INPUTS!$C$25)
B16: 0.4 | C16: =IF(OR(DEAL!$C$9="",C$7=""),"",1-((BOM!$E$22*(1-$B16)+INPUTS!$C$17+DEAL!$C$9+C$7+INPUTS!$C$18)+INPUTS!$C$27/INPUTS!$C$5)/DEAL!$C$15-DEAL!$C$20-INPUTS!$C$24-INPUTS!$C$25) | D16: =IF(OR(DEAL!$C$9="",D$7=""),"",1-((BOM!$E$22*(1-$B16)+INPUTS!$C$17+DEAL!$C$9+D$7+INPUTS!$C$18)+INPUTS!$C$27/INPUTS!$C$5)/DEAL!$C$15-DEAL!$C$20-INPUTS!$C$24-INPUTS!$C$25) | E16: =IF(OR(DEAL!$C$9="",E$7=""),"",1-((BOM!$E$22*(1-$B16)+INPUTS!$C$17+DEAL!$C$9+E$7+INPUTS!$C$18)+INPUTS!$C$27/INPUTS!$C$5)/DEAL!$C$15-DEAL!$C$20-INPUTS!$C$24-INPUTS!$C$25) | F16: =IF(OR(DEAL!$C$9="",F$7=""),"",1-((BOM!$E$22*(1-$B16)+INPUTS!$C$17+DEAL!$C$9+F$7+INPUTS!$C$18)+INPUTS!$C$27/INPUTS!$C$5)/DEAL!$C$15-DEAL!$C$20-INPUTS!$C$24-INPUTS!$C$25) | G16: =IF(OR(DEAL!$C$9="",G$7=""),"",1-((BOM!$E$22*(1-$B16)+INPUTS!$C$17+DEAL!$C$9+G$7+INPUTS!$C$18)+INPUTS!$C$27/INPUTS!$C$5)/DEAL!$C$15-DEAL!$C$20-INPUTS!$C$24-INPUTS!$C$25) | H16: =IF(OR(DEAL!$C$9="",H$7=""),"",1-((BOM!$E$22*(1-$B16)+INPUTS!$C$17+DEAL!$C$9+H$7+INPUTS!$C$18)+INPUTS!$C$27/INPUTS!$C$5)/DEAL!$C$15-DEAL!$C$20-INPUTS!$C$24-INPUTS!$C$25)
B17: 0.45 | C17: =IF(OR(DEAL!$C$9="",C$7=""),"",1-((BOM!$E$22*(1-$B17)+INPUTS!$C$17+DEAL!$C$9+C$7+INPUTS!$C$18)+INPUTS!$C$27/INPUTS!$C$5)/DEAL!$C$15-DEAL!$C$20-INPUTS!$C$24-INPUTS!$C$25) | D17: =IF(OR(DEAL!$C$9="",D$7=""),"",1-((BOM!$E$22*(1-$B17)+INPUTS!$C$17+DEAL!$C$9+D$7+INPUTS!$C$18)+INPUTS!$C$27/INPUTS!$C$5)/DEAL!$C$15-DEAL!$C$20-INPUTS!$C$24-INPUTS!$C$25) | E17: =IF(OR(DEAL!$C$9="",E$7=""),"",1-((BOM!$E$22*(1-$B17)+INPUTS!$C$17+DEAL!$C$9+E$7+INPUTS!$C$18)+INPUTS!$C$27/INPUTS!$C$5)/DEAL!$C$15-DEAL!$C$20-INPUTS!$C$24-INPUTS!$C$25) | F17: =IF(OR(DEAL!$C$9="",F$7=""),"",1-((BOM!$E$22*(1-$B17)+INPUTS!$C$17+DEAL!$C$9+F$7+INPUTS!$C$18)+INPUTS!$C$27/INPUTS!$C$5)/DEAL!$C$15-DEAL!$C$20-INPUTS!$C$24-INPUTS!$C$25) | G17: =IF(OR(DEAL!$C$9="",G$7=""),"",1-((BOM!$E$22*(1-$B17)+INPUTS!$C$17+DEAL!$C$9+G$7+INPUTS!$C$18)+INPUTS!$C$27/INPUTS!$C$5)/DEAL!$C$15-DEAL!$C$20-INPUTS!$C$24-INPUTS!$C$25) | H17: =IF(OR(DEAL!$C$9="",H$7=""),"",1-((BOM!$E$22*(1-$B17)+INPUTS!$C$17+DEAL!$C$9+H$7+INPUTS!$C$18)+INPUTS!$C$27/INPUTS!$C$5)/DEAL!$C$15-DEAL!$C$20-INPUTS!$C$24-INPUTS!$C$25)
B18: 0.5 | C18: =IF(OR(DEAL!$C$9="",C$7=""),"",1-((BOM!$E$22*(1-$B18)+INPUTS!$C$17+DEAL!$C$9+C$7+INPUTS!$C$18)+INPUTS!$C$27/INPUTS!$C$5)/DEAL!$C$15-DEAL!$C$20-INPUTS!$C$24-INPUTS!$C$25) | D18: =IF(OR(DEAL!$C$9="",D$7=""),"",1-((BOM!$E$22*(1-$B18)+INPUTS!$C$17+DEAL!$C$9+D$7+INPUTS!$C$18)+INPUTS!$C$27/INPUTS!$C$5)/DEAL!$C$15-DEAL!$C$20-INPUTS!$C$24-INPUTS!$C$25) | E18: =IF(OR(DEAL!$C$9="",E$7=""),"",1-((BOM!$E$22*(1-$B18)+INPUTS!$C$17+DEAL!$C$9+E$7+INPUTS!$C$18)+INPUTS!$C$27/INPUTS!$C$5)/DEAL!$C$15-DEAL!$C$20-INPUTS!$C$24-INPUTS!$C$25) | F18: =IF(OR(DEAL!$C$9="",F$7=""),"",1-((BOM!$E$22*(1-$B18)+INPUTS!$C$17+DEAL!$C$9+F$7+INPUTS!$C$18)+INPUTS!$C$27/INPUTS!$C$5)/DEAL!$C$15-DEAL!$C$20-INPUTS!$C$24-INPUTS!$C$25) | G18: =IF(OR(DEAL!$C$9="",G$7=""),"",1-((BOM!$E$22*(1-$B18)+INPUTS!$C$17+DEAL!$C$9+G$7+INPUTS!$C$18)+INPUTS!$C$27/INPUTS!$C$5)/DEAL!$C$15-DEAL!$C$20-INPUTS!$C$24-INPUTS!$C$25) | H18: =IF(OR(DEAL!$C$9="",H$7=""),"",1-((BOM!$E$22*(1-$B18)+INPUTS!$C$17+DEAL!$C$9+H$7+INPUTS!$C$18)+INPUTS!$C$27/INPUTS!$C$5)/DEAL!$C$15-DEAL!$C$20-INPUTS!$C$24-INPUTS!$C$25)
B20: GRID B — bid as % of estimate × supplier discount (at YOUR freight)
B21: bid % of estimate ↓ discount off list →
C22: 0 | D22: 0.1 | E22: 0.2 | F22: 0.3 | G22: 0.4 | H22: 0.45
B23: 0.6 | C23: =IF(OR(DEAL!$C$9="",DEAL!$C$10=""),"",1-((BOM!$E$22*(1-C$22)+INPUTS!$C$17+DEAL!$C$9+DEAL!$C$10+INPUTS!$C$18)+INPUTS!$C$27/INPUTS!$C$5)/(INPUTS!$C$6*$B23)-DEAL!$C$20-INPUTS!$C$24-INPUTS!$C$25) | D23: =IF(OR(DEAL!$C$9="",DEAL!$C$10=""),"",1-((BOM!$E$22*(1-D$22)+INPUTS!$C$17+DEAL!$C$9+DEAL!$C$10+INPUTS!$C$18)+INPUTS!$C$27/INPUTS!$C$5)/(INPUTS!$C$6*$B23)-DEAL!$C$20-INPUTS!$C$24-INPUTS!$C$25) | E23: =IF(OR(DEAL!$C$9="",DEAL!$C$10=""),"",1-((BOM!$E$22*(1-E$22)+INPUTS!$C$17+DEAL!$C$9+DEAL!$C$10+INPUTS!$C$18)+INPUTS!$C$27/INPUTS!$C$5)/(INPUTS!$C$6*$B23)-DEAL!$C$20-INPUTS!$C$24-INPUTS!$C$25) | F23: =IF(OR(DEAL!$C$9="",DEAL!$C$10=""),"",1-((BOM!$E$22*(1-F$22)+INPUTS!$C$17+DEAL!$C$9+DEAL!$C$10+INPUTS!$C$18)+INPUTS!$C$27/INPUTS!$C$5)/(INPUTS!$C$6*$B23)-DEAL!$C$20-INPUTS!$C$24-INPUTS!$C$25) | G23: =IF(OR(DEAL!$C$9="",DEAL!$C$10=""),"",1-((BOM!$E$22*(1-G$22)+INPUTS!$C$17+DEAL!$C$9+DEAL!$C$10+INPUTS!$C$18)+INPUTS!$C$27/INPUTS!$C$5)/(INPUTS!$C$6*$B23)-DEAL!$C$20-INPUTS!$C$24-INPUTS!$C$25) | H23: =IF(OR(DEAL!$C$9="",DEAL!$C$10=""),"",1-((BOM!$E$22*(1-H$22)+INPUTS!$C$17+DEAL!$C$9+DEAL!$C$10+INPUTS!$C$18)+INPUTS!$C$27/INPUTS!$C$5)/(INPUTS!$C$6*$B23)-DEAL!$C$20-INPUTS!$C$24-INPUTS!$C$25)
B24: 0.65 | C24: =IF(OR(DEAL!$C$9="",DEAL!$C$10=""),"",1-((BOM!$E$22*(1-C$22)+INPUTS!$C$17+DEAL!$C$9+DEAL!$C$10+INPUTS!$C$18)+INPUTS!$C$27/INPUTS!$C$5)/(INPUTS!$C$6*$B24)-DEAL!$C$20-INPUTS!$C$24-INPUTS!$C$25) | D24: =IF(OR(DEAL!$C$9="",DEAL!$C$10=""),"",1-((BOM!$E$22*(1-D$22)+INPUTS!$C$17+DEAL!$C$9+DEAL!$C$10+INPUTS!$C$18)+INPUTS!$C$27/INPUTS!$C$5)/(INPUTS!$C$6*$B24)-DEAL!$C$20-INPUTS!$C$24-INPUTS!$C$25) | E24: =IF(OR(DEAL!$C$9="",DEAL!$C$10=""),"",1-((BOM!$E$22*(1-E$22)+INPUTS!$C$17+DEAL!$C$9+DEAL!$C$10+INPUTS!$C$18)+INPUTS!$C$27/INPUTS!$C$5)/(INPUTS!$C$6*$B24)-DEAL!$C$20-INPUTS!$C$24-INPUTS!$C$25) | F24: =IF(OR(DEAL!$C$9="",DEAL!$C$10=""),"",1-((BOM!$E$22*(1-F$22)+INPUTS!$C$17+DEAL!$C$9+DEAL!$C$10+INPUTS!$C$18)+INPUTS!$C$27/INPUTS!$C$5)/(INPUTS!$C$6*$B24)-DEAL!$C$20-INPUTS!$C$24-INPUTS!$C$25) | G24: =IF(OR(DEAL!$C$9="",DEAL!$C$10=""),"",1-((BOM!$E$22*(1-G$22)+INPUTS!$C$17+DEAL!$C$9+DEAL!$C$10+INPUTS!$C$18)+INPUTS!$C$27/INPUTS!$C$5)/(INPUTS!$C$6*$B24)-DEAL!$C$20-INPUTS!$C$24-INPUTS!$C$25) | H24: =IF(OR(DEAL!$C$9="",DEAL!$C$10=""),"",1-((BOM!$E$22*(1-H$22)+INPUTS!$C$17+DEAL!$C$9+DEAL!$C$10+INPUTS!$C$18)+INPUTS!$C$27/INPUTS!$C$5)/(INPUTS!$C$6*$B24)-DEAL!$C$20-INPUTS!$C$24-INPUTS!$C$25)
B25: 0.7 | C25: =IF(OR(DEAL!$C$9="",DEAL!$C$10=""),"",1-((BOM!$E$22*(1-C$22)+INPUTS!$C$17+DEAL!$C$9+DEAL!$C$10+INPUTS!$C$18)+INPUTS!$C$27/INPUTS!$C$5)/(INPUTS!$C$6*$B25)-DEAL!$C$20-INPUTS!$C$24-INPUTS!$C$25) | D25: =IF(OR(DEAL!$C$9="",DEAL!$C$10=""),"",1-((BOM!$E$22*(1-D$22)+INPUTS!$C$17+DEAL!$C$9+DEAL!$C$10+INPUTS!$C$18)+INPUTS!$C$27/INPUTS!$C$5)/(INPUTS!$C$6*$B25)-DEAL!$C$20-INPUTS!$C$24-INPUTS!$C$25) | E25: =IF(OR(DEAL!$C$9="",DEAL!$C$10=""),"",1-((BOM!$E$22*(1-E$22)+INPUTS!$C$17+DEAL!$C$9+DEAL!$C$10+INPUTS!$C$18)+INPUTS!$C$27/INPUTS!$C$5)/(INPUTS!$C$6*$B25)-DEAL!$C$20-INPUTS!$C$24-INPUTS!$C$25) | F25: =IF(OR(DEAL!$C$9="",DEAL!$C$10=""),"",1-((BOM!$E$22*(1-F$22)+INPUTS!$C$17+DEAL!$C$9+DEAL!$C$10+INPUTS!$C$18)+INPUTS!$C$27/INPUTS!$C$5)/(INPUTS!$C$6*$B25)-DEAL!$C$20-INPUTS!$C$24-INPUTS!$C$25) | G25: =IF(OR(DEAL!$C$9="",DEAL!$C$10=""),"",1-((BOM!$E$22*(1-G$22)+INPUTS!$C$17+DEAL!$C$9+DEAL!$C$10+INPUTS!$C$18)+INPUTS!$C$27/INPUTS!$C$5)/(INPUTS!$C$6*$B25)-DEAL!$C$20-INPUTS!$C$24-INPUTS!$C$25) | H25: =IF(OR(DEAL!$C$9="",DEAL!$C$10=""),"",1-((BOM!$E$22*(1-H$22)+INPUTS!$C$17+DEAL!$C$9+DEAL!$C$10+INPUTS!$C$18)+INPUTS!$C$27/INPUTS!$C$5)/(INPUTS!$C$6*$B25)-DEAL!$C$20-INPUTS!$C$24-INPUTS!$C$25)
B26: 0.75 | C26: =IF(OR(DEAL!$C$9="",DEAL!$C$10=""),"",1-((BOM!$E$22*(1-C$22)+INPUTS!$C$17+DEAL!$C$9+DEAL!$C$10+INPUTS!$C$18)+INPUTS!$C$27/INPUTS!$C$5)/(INPUTS!$C$6*$B26)-DEAL!$C$20-INPUTS!$C$24-INPUTS!$C$25) | D26: =IF(OR(DEAL!$C$9="",DEAL!$C$10=""),"",1-((BOM!$E$22*(1-D$22)+INPUTS!$C$17+DEAL!$C$9+DEAL!$C$10+INPUTS!$C$18)+INPUTS!$C$27/INPUTS!$C$5)/(INPUTS!$C$6*$B26)-DEAL!$C$20-INPUTS!$C$24-INPUTS!$C$25) | E26: =IF(OR(DEAL!$C$9="",DEAL!$C$10=""),"",1-((BOM!$E$22*(1-E$22)+INPUTS!$C$17+DEAL!$C$9+DEAL!$C$10+INPUTS!$C$18)+INPUTS!$C$27/INPUTS!$C$5)/(INPUTS!$C$6*$B26)-DEAL!$C$20-INPUTS!$C$24-INPUTS!$C$25) | F26: =IF(OR(DEAL!$C$9="",DEAL!$C$10=""),"",1-((BOM!$E$22*(1-F$22)+INPUTS!$C$17+DEAL!$C$9+DEAL!$C$10+INPUTS!$C$18)+INPUTS!$C$27/INPUTS!$C$5)/(INPUTS!$C$6*$B26)-DEAL!$C$20-INPUTS!$C$24-INPUTS!$C$25) | G26: =IF(OR(DEAL!$C$9="",DEAL!$C$10=""),"",1-((BOM!$E$22*(1-G$22)+INPUTS!$C$17+DEAL!$C$9+DEAL!$C$10+INPUTS!$C$18)+INPUTS!$C$27/INPUTS!$C$5)/(INPUTS!$C$6*$B26)-DEAL!$C$20-INPUTS!$C$24-INPUTS!$C$25) | H26: =IF(OR(DEAL!$C$9="",DEAL!$C$10=""),"",1-((BOM!$E$22*(1-H$22)+INPUTS!$C$17+DEAL!$C$9+DEAL!$C$10+INPUTS!$C$18)+INPUTS!$C$27/INPUTS!$C$5)/(INPUTS!$C$6*$B26)-DEAL!$C$20-INPUTS!$C$24-INPUTS!$C$25)
B27: 0.8 | C27: =IF(OR(DEAL!$C$9="",DEAL!$C$10=""),"",1-((BOM!$E$22*(1-C$22)+INPUTS!$C$17+DEAL!$C$9+DEAL!$C$10+INPUTS!$C$18)+INPUTS!$C$27/INPUTS!$C$5)/(INPUTS!$C$6*$B27)-DEAL!$C$20-INPUTS!$C$24-INPUTS!$C$25) | D27: =IF(OR(DEAL!$C$9="",DEAL!$C$10=""),"",1-((BOM!$E$22*(1-D$22)+INPUTS!$C$17+DEAL!$C$9+DEAL!$C$10+INPUTS!$C$18)+INPUTS!$C$27/INPUTS!$C$5)/(INPUTS!$C$6*$B27)-DEAL!$C$20-INPUTS!$C$24-INPUTS!$C$25) | E27: =IF(OR(DEAL!$C$9="",DEAL!$C$10=""),"",1-((BOM!$E$22*(1-E$22)+INPUTS!$C$17+DEAL!$C$9+DEAL!$C$10+INPUTS!$C$18)+INPUTS!$C$27/INPUTS!$C$5)/(INPUTS!$C$6*$B27)-DEAL!$C$20-INPUTS!$C$24-INPUTS!$C$25) | F27: =IF(OR(DEAL!$C$9="",DEAL!$C$10=""),"",1-((BOM!$E$22*(1-F$22)+INPUTS!$C$17+DEAL!$C$9+DEAL!$C$10+INPUTS!$C$18)+INPUTS!$C$27/INPUTS!$C$5)/(INPUTS!$C$6*$B27)-DEAL!$C$20-INPUTS!$C$24-INPUTS!$C$25) | G27: =IF(OR(DEAL!$C$9="",DEAL!$C$10=""),"",1-((BOM!$E$22*(1-G$22)+INPUTS!$C$17+DEAL!$C$9+DEAL!$C$10+INPUTS!$C$18)+INPUTS!$C$27/INPUTS!$C$5)/(INPUTS!$C$6*$B27)-DEAL!$C$20-INPUTS!$C$24-INPUTS!$C$25) | H27: =IF(OR(DEAL!$C$9="",DEAL!$C$10=""),"",1-((BOM!$E$22*(1-H$22)+INPUTS!$C$17+DEAL!$C$9+DEAL!$C$10+INPUTS!$C$18)+INPUTS!$C$27/INPUTS!$C$5)/(INPUTS!$C$6*$B27)-DEAL!$C$20-INPUTS!$C$24-INPUTS!$C$25)
B28: 0.85 | C28: =IF(OR(DEAL!$C$9="",DEAL!$C$10=""),"",1-((BOM!$E$22*(1-C$22)+INPUTS!$C$17+DEAL!$C$9+DEAL!$C$10+INPUTS!$C$18)+INPUTS!$C$27/INPUTS!$C$5)/(INPUTS!$C$6*$B28)-DEAL!$C$20-INPUTS!$C$24-INPUTS!$C$25) | D28: =IF(OR(DEAL!$C$9="",DEAL!$C$10=""),"",1-((BOM!$E$22*(1-D$22)+INPUTS!$C$17+DEAL!$C$9+DEAL!$C$10+INPUTS!$C$18)+INPUTS!$C$27/INPUTS!$C$5)/(INPUTS!$C$6*$B28)-DEAL!$C$20-INPUTS!$C$24-INPUTS!$C$25) | E28: =IF(OR(DEAL!$C$9="",DEAL!$C$10=""),"",1-((BOM!$E$22*(1-E$22)+INPUTS!$C$17+DEAL!$C$9+DEAL!$C$10+INPUTS!$C$18)+INPUTS!$C$27/INPUTS!$C$5)/(INPUTS!$C$6*$B28)-DEAL!$C$20-INPUTS!$C$24-INPUTS!$C$25) | F28: =IF(OR(DEAL!$C$9="",DEAL!$C$10=""),"",1-((BOM!$E$22*(1-F$22)+INPUTS!$C$17+DEAL!$C$9+DEAL!$C$10+INPUTS!$C$18)+INPUTS!$C$27/INPUTS!$C$5)/(INPUTS!$C$6*$B28)-DEAL!$C$20-INPUTS!$C$24-INPUTS!$C$25) | G28: =IF(OR(DEAL!$C$9="",DEAL!$C$10=""),"",1-((BOM!$E$22*(1-G$22)+INPUTS!$C$17+DEAL!$C$9+DEAL!$C$10+INPUTS!$C$18)+INPUTS!$C$27/INPUTS!$C$5)/(INPUTS!$C$6*$B28)-DEAL!$C$20-INPUTS!$C$24-INPUTS!$C$25) | H28: =IF(OR(DEAL!$C$9="",DEAL!$C$10=""),"",1-((BOM!$E$22*(1-H$22)+INPUTS!$C$17+DEAL!$C$9+DEAL!$C$10+INPUTS!$C$18)+INPUTS!$C$27/INPUTS!$C$5)/(INPUTS!$C$6*$B28)-DEAL!$C$20-INPUTS!$C$24-INPUTS!$C$25)
B29: 0.9 | C29: =IF(OR(DEAL!$C$9="",DEAL!$C$10=""),"",1-((BOM!$E$22*(1-C$22)+INPUTS!$C$17+DEAL!$C$9+DEAL!$C$10+INPUTS!$C$18)+INPUTS!$C$27/INPUTS!$C$5)/(INPUTS!$C$6*$B29)-DEAL!$C$20-INPUTS!$C$24-INPUTS!$C$25) | D29: =IF(OR(DEAL!$C$9="",DEAL!$C$10=""),"",1-((BOM!$E$22*(1-D$22)+INPUTS!$C$17+DEAL!$C$9+DEAL!$C$10+INPUTS!$C$18)+INPUTS!$C$27/INPUTS!$C$5)/(INPUTS!$C$6*$B29)-DEAL!$C$20-INPUTS!$C$24-INPUTS!$C$25) | E29: =IF(OR(DEAL!$C$9="",DEAL!$C$10=""),"",1-((BOM!$E$22*(1-E$22)+INPUTS!$C$17+DEAL!$C$9+DEAL!$C$10+INPUTS!$C$18)+INPUTS!$C$27/INPUTS!$C$5)/(INPUTS!$C$6*$B29)-DEAL!$C$20-INPUTS!$C$24-INPUTS!$C$25) | F29: =IF(OR(DEAL!$C$9="",DEAL!$C$10=""),"",1-((BOM!$E$22*(1-F$22)+INPUTS!$C$17+DEAL!$C$9+DEAL!$C$10+INPUTS!$C$18)+INPUTS!$C$27/INPUTS!$C$5)/(INPUTS!$C$6*$B29)-DEAL!$C$20-INPUTS!$C$24-INPUTS!$C$25) | G29: =IF(OR(DEAL!$C$9="",DEAL!$C$10=""),"",1-((BOM!$E$22*(1-G$22)+INPUTS!$C$17+DEAL!$C$9+DEAL!$C$10+INPUTS!$C$18)+INPUTS!$C$27/INPUTS!$C$5)/(INPUTS!$C$6*$B29)-DEAL!$C$20-INPUTS!$C$24-INPUTS!$C$25) | H29: =IF(OR(DEAL!$C$9="",DEAL!$C$10=""),"",1-((BOM!$E$22*(1-H$22)+INPUTS!$C$17+DEAL!$C$9+DEAL!$C$10+INPUTS!$C$18)+INPUTS!$C$27/INPUTS!$C$5)/(INPUTS!$C$6*$B29)-DEAL!$C$20-INPUTS!$C$24-INPUTS!$C$25)
B30: 0.95 | C30: =IF(OR(DEAL!$C$9="",DEAL!$C$10=""),"",1-((BOM!$E$22*(1-C$22)+INPUTS!$C$17+DEAL!$C$9+DEAL!$C$10+INPUTS!$C$18)+INPUTS!$C$27/INPUTS!$C$5)/(INPUTS!$C$6*$B30)-DEAL!$C$20-INPUTS!$C$24-INPUTS!$C$25) | D30: =IF(OR(DEAL!$C$9="",DEAL!$C$10=""),"",1-((BOM!$E$22*(1-D$22)+INPUTS!$C$17+DEAL!$C$9+DEAL!$C$10+INPUTS!$C$18)+INPUTS!$C$27/INPUTS!$C$5)/(INPUTS!$C$6*$B30)-DEAL!$C$20-INPUTS!$C$24-INPUTS!$C$25) | E30: =IF(OR(DEAL!$C$9="",DEAL!$C$10=""),"",1-((BOM!$E$22*(1-E$22)+INPUTS!$C$17+DEAL!$C$9+DEAL!$C$10+INPUTS!$C$18)+INPUTS!$C$27/INPUTS!$C$5)/(INPUTS!$C$6*$B30)-DEAL!$C$20-INPUTS!$C$24-INPUTS!$C$25) | F30: =IF(OR(DEAL!$C$9="",DEAL!$C$10=""),"",1-((BOM!$E$22*(1-F$22)+INPUTS!$C$17+DEAL!$C$9+DEAL!$C$10+INPUTS!$C$18)+INPUTS!$C$27/INPUTS!$C$5)/(INPUTS!$C$6*$B30)-DEAL!$C$20-INPUTS!$C$24-INPUTS!$C$25) | G30: =IF(OR(DEAL!$C$9="",DEAL!$C$10=""),"",1-((BOM!$E$22*(1-G$22)+INPUTS!$C$17+DEAL!$C$9+DEAL!$C$10+INPUTS!$C$18)+INPUTS!$C$27/INPUTS!$C$5)/(INPUTS!$C$6*$B30)-DEAL!$C$20-INPUTS!$C$24-INPUTS!$C$25) | H30: =IF(OR(DEAL!$C$9="",DEAL!$C$10=""),"",1-((BOM!$E$22*(1-H$22)+INPUTS!$C$17+DEAL!$C$9+DEAL!$C$10+INPUTS!$C$18)+INPUTS!$C$27/INPUTS!$C$5)/(INPUTS!$C$6*$B30)-DEAL!$C$20-INPUTS!$C$24-INPUTS!$C$25)
B31: 1 | C31: =IF(OR(DEAL!$C$9="",DEAL!$C$10=""),"",1-((BOM!$E$22*(1-C$22)+INPUTS!$C$17+DEAL!$C$9+DEAL!$C$10+INPUTS!$C$18)+INPUTS!$C$27/INPUTS!$C$5)/(INPUTS!$C$6*$B31)-DEAL!$C$20-INPUTS!$C$24-INPUTS!$C$25) | D31: =IF(OR(DEAL!$C$9="",DEAL!$C$10=""),"",1-((BOM!$E$22*(1-D$22)+INPUTS!$C$17+DEAL!$C$9+DEAL!$C$10+INPUTS!$C$18)+INPUTS!$C$27/INPUTS!$C$5)/(INPUTS!$C$6*$B31)-DEAL!$C$20-INPUTS!$C$24-INPUTS!$C$25) | E31: =IF(OR(DEAL!$C$9="",DEAL!$C$10=""),"",1-((BOM!$E$22*(1-E$22)+INPUTS!$C$17+DEAL!$C$9+DEAL!$C$10+INPUTS!$C$18)+INPUTS!$C$27/INPUTS!$C$5)/(INPUTS!$C$6*$B31)-DEAL!$C$20-INPUTS!$C$24-INPUTS!$C$25) | F31: =IF(OR(DEAL!$C$9="",DEAL!$C$10=""),"",1-((BOM!$E$22*(1-F$22)+INPUTS!$C$17+DEAL!$C$9+DEAL!$C$10+INPUTS!$C$18)+INPUTS!$C$27/INPUTS!$C$5)/(INPUTS!$C$6*$B31)-DEAL!$C$20-INPUTS!$C$24-INPUTS!$C$25) | G31: =IF(OR(DEAL!$C$9="",DEAL!$C$10=""),"",1-((BOM!$E$22*(1-G$22)+INPUTS!$C$17+DEAL!$C$9+DEAL!$C$10+INPUTS!$C$18)+INPUTS!$C$27/INPUTS!$C$5)/(INPUTS!$C$6*$B31)-DEAL!$C$20-INPUTS!$C$24-INPUTS!$C$25) | H31: =IF(OR(DEAL!$C$9="",DEAL!$C$10=""),"",1-((BOM!$E$22*(1-H$22)+INPUTS!$C$17+DEAL!$C$9+DEAL!$C$10+INPUTS!$C$18)+INPUTS!$C$27/INPUTS!$C$5)/(INPUTS!$C$6*$B31)-DEAL!$C$20-INPUTS!$C$24-INPUTS!$C$25)
B34: Read it: find the discount you can actually get, then read across to the freight you will actually pay. Grid A holds the bid fixed at your INPUTS level; Grid B holds freight fixed at yours.
B35: Both grids ignore the platform fee cap, so they run slightly conservative on large lots.

Sheet SCENARIOS
B2: SCENARIOS — the same business under six sets of facts
B3: Each column stands alone: the blue cells are its own assumptions, everything below is computed from them. Lots per year is never assumed — it is what R$15.600 of capital can actually turn over at that column's float.
B5: SCENARIO | C5: A · As typed | D5: B · TODAY, done right | E5: C · + 20% supplier discount | F5: D · + 28-day supplier terms | G5: E · Terms, NO discount | H5: F · Lote único at 50% | I5: WHAT IT MEANS
B6: Kits in the lot | C6: 100 | D6: 61 | E6: 73 | F6: 73 | G6: 61 | H6: 61 | I6: Column A is 100 kits because that is the median tender; B–E are the biggest lot R$15.600 can actually fund.
B7: Bid as % of the buyer's estimate | C7: 0.75 | D7: 0.9 | E7: 0.9 | F7: 0.9 | G7: 0.9 | H7: 0.5 | I7: Per-item lots clear at 97–100% of estimate. Bidding 75% was never required — it was inherited.
B8: Supplier discount off list | C8: 0 | D8: 0 | E8: 0.2 | F8: 0.2 | G8: 0 | H8: 0 | I8: UNVERIFIED. ~45% is the rumoured account tier; 20% is deliberately conservative.
B9: Freight per kit (LTL SP→CE, measured) | C9: 53.99 | D9: 53.99 | E9: 53.99 | F9: 53.99 | G9: 53.99 | H9: 53.99 | I9: Swap this for R$188,40 (PAC to MA) and every column below turns negative.
B10: Days the cash is out (float) | C10: 45 | D10: 45 | E10: 45 | F10: 6 | G10: 6 | H10: 45 | I10: 45 = prepay. 6 = a supplier granting 28 days. This one line is the whole business.
B12: Shared by every column: estimate R$359,05 · capital R$15.600 · fixed costs R$6.000/yr · 8 h per order · R$5,20/US$
B14: ONE LOT
B15: Cost per kit | C15: =(BOM!$E$22*(1-C8)+C9) | D15: =(BOM!$E$22*(1-D8)+D9) | E15: =(BOM!$E$22*(1-E8)+E9) | F15: =(BOM!$E$22*(1-F8)+F9) | G15: =(BOM!$E$22*(1-G8)+G9) | H15: =(BOM!$E$22*(1-H8)+H9) | I15: Goods after discount, plus freight. Assembly is R$0 — every lot here is inside the 240-kit self-pack ceiling.
B16: Bid price per kit | C16: =(INPUTS!$C$6*C7) | D16: =(INPUTS!$C$6*D7) | E16: =(INPUTS!$C$6*E7) | F16: =(INPUTS!$C$6*F7) | G16: =(INPUTS!$C$6*G7) | H16: =(INPUTS!$C$6*H7)
B17: Cash you must front | C17: =((BOM!$E$22*(1-C8)+C9)*C6) | D17: =((BOM!$E$22*(1-D8)+D9)*D6) | E17: =((BOM!$E$22*(1-E8)+E9)*E6) | F17: =((BOM!$E$22*(1-F8)+F9)*F6) | G17: =((BOM!$E$22*(1-G8)+G9)*G6) | H17: =((BOM!$E$22*(1-H8)+H9)*H6) | I17: Must not exceed R$15.600. That ceiling is what sets the lot size.
B18: Net margin on the lot | C18: =IF(((INPUTS!$C$6*C7)*C6)=0,0,(((INPUTS!$C$6*C7)*C6)-((BOM!$E$22*(1-C8)+C9)*C6)-((INPUTS!$C$6*C7)*C6)*(IF((((INPUTS!$C$6*C7)*C6)*((INPUTS!$C$28/((BOM!$E$22*(1-C8)+C9)*C6))*365/C10))<=0,0.04,IF((((INPUTS!$C$6*C7)*C6)*((INPUTS!$C$28/((BOM!$E$22*(1-C8)+C9)*C6))*365/C10))<=180000,0.04,IF((((INPUTS!$C$6*C7)*C6)*((INPUTS!$C$28/((BOM!$E$22*(1-C8)+C9)*C6))*365/C10))<=360000,((((INPUTS!$C$6*C7)*C6)*((INPUTS!$C$28/((BOM!$E$22*(1-C8)+C9)*C6))*365/C10))*0.073-5940)/(((INPUTS!$C$6*C7)*C6)*((INPUTS!$C$28/((BOM!$E$22*(1-C8)+C9)*C6))*365/C10)),IF((((INPUTS!$C$6*C7)*C6)*((INPUTS!$C$28/((BOM!$E$22*(1-C8)+C9)*C6))*365/C10))<=720000,((((INPUTS!$C$6*C7)*C6)*((INPUTS!$C$28/((BOM!$E$22*(1-C8)+C9)*C6))*365/C10))*0.095-13860)/(((INPUTS!$C$6*C7)*C6)*((INPUTS!$C$28/((BOM!$E$22*(1-C8)+C9)*C6))*365/C10)),IF((((INPUTS!$C$6*C7)*C6)*((INPUTS!$C$28/((BOM!$E$22*(1-C8)+C9)*C6))*365/C10))<=1800000,((((INPUTS!$C$6*C7)*C6)*((INPUTS!$C$28/((BOM!$E$22*(1-C8)+C9)*C6))*365/C10))*0.107-22500)/(((INPUTS!$C$6*C7)*C6)*((INPUTS!$C$28/((BOM!$E$22*(1-C8)+C9)*C6))*365/C10)),IF((((INPUTS!$C$6*C7)*C6)*((INPUTS!$C$28/((BOM!$E$22*(1-C8)+C9)*C6))*365/C10))<=3600000,((((INPUTS!$C$6*C7)*C6)*((INPUTS!$C$28/((BOM!$E$22*(1-C8)+C9)*C6))*365/C10))*0.143-87300)/(((INPUTS!$C$6*C7)*C6)*((INPUTS!$C$28/((BOM!$E$22*(1-C8)+C9)*C6))*365/C10)),((((INPUTS!$C$6*C7)*C6)*((INPUTS!$C$28/((BOM!$E$22*(1-C8)+C9)*C6))*365/C10))*0.19-378000)/(((INPUTS!$C$6*C7)*C6)*((INPUTS!$C$28/((BOM!$E$22*(1-C8)+C9)*C6))*365/C10)))))))))-MIN(((INPUTS!$C$6*C7)*C6)*INPUTS!$C$25,INPUTS!$C$26))/((INPUTS!$C$6*C7)*C6)) | D18: =IF(((INPUTS!$C$6*D7)*D6)=0,0,(((INPUTS!$C$6*D7)*D6)-((BOM!$E$22*(1-D8)+D9)*D6)-((INPUTS!$C$6*D7)*D6)*(IF((((INPUTS!$C$6*D7)*D6)*((INPUTS!$C$28/((BOM!$E$22*(1-D8)+D9)*D6))*365/D10))<=0,0.04,IF((((INPUTS!$C$6*D7)*D6)*((INPUTS!$C$28/((BOM!$E$22*(1-D8)+D9)*D6))*365/D10))<=180000,0.04,IF((((INPUTS!$C$6*D7)*D6)*((INPUTS!$C$28/((BOM!$E$22*(1-D8)+D9)*D6))*365/D10))<=360000,((((INPUTS!$C$6*D7)*D6)*((INPUTS!$C$28/((BOM!$E$22*(1-D8)+D9)*D6))*365/D10))*0.073-5940)/(((INPUTS!$C$6*D7)*D6)*((INPUTS!$C$28/((BOM!$E$22*(1-D8)+D9)*D6))*365/D10)),IF((((INPUTS!$C$6*D7)*D6)*((INPUTS!$C$28/((BOM!$E$22*(1-D8)+D9)*D6))*365/D10))<=720000,((((INPUTS!$C$6*D7)*D6)*((INPUTS!$C$28/((BOM!$E$22*(1-D8)+D9)*D6))*365/D10))*0.095-13860)/(((INPUTS!$C$6*D7)*D6)*((INPUTS!$C$28/((BOM!$E$22*(1-D8)+D9)*D6))*365/D10)),IF((((INPUTS!$C$6*D7)*D6)*((INPUTS!$C$28/((BOM!$E$22*(1-D8)+D9)*D6))*365/D10))<=1800000,((((INPUTS!$C$6*D7)*D6)*((INPUTS!$C$28/((BOM!$E$22*(1-D8)+D9)*D6))*365/D10))*0.107-22500)/(((INPUTS!$C$6*D7)*D6)*((INPUTS!$C$28/((BOM!$E$22*(1-D8)+D9)*D6))*365/D10)),IF((((INPUTS!$C$6*D7)*D6)*((INPUTS!$C$28/((BOM!$E$22*(1-D8)+D9)*D6))*365/D10))<=3600000,((((INPUTS!$C$6*D7)*D6)*((INPUTS!$C$28/((BOM!$E$22*(1-D8)+D9)*D6))*365/D10))*0.143-87300)/(((INPUTS!$C$6*D7)*D6)*((INPUTS!$C$28/((BOM!$E$22*(1-D8)+D9)*D6))*365/D10)),((((INPUTS!$C$6*D7)*D6)*((INPUTS!$C$28/((BOM!$E$22*(1-D8)+D9)*D6))*365/D10))*0.19-378000)/(((INPUTS!$C$6*D7)*D6)*((INPUTS!$C$28/((BOM!$E$22*(1-D8)+D9)*D6))*365/D10)))))))))-MIN(((INPUTS!$C$6*D7)*D6)*INPUTS!$C$25,INPUTS!$C$26))/((INPUTS!$C$6*D7)*D6)) | E18: =IF(((INPUTS!$C$6*E7)*E6)=0,0,(((INPUTS!$C$6*E7)*E6)-((BOM!$E$22*(1-E8)+E9)*E6)-((INPUTS!$C$6*E7)*E6)*(IF((((INPUTS!$C$6*E7)*E6)*((INPUTS!$C$28/((BOM!$E$22*(1-E8)+E9)*E6))*365/E10))<=0,0.04,IF((((INPUTS!$C$6*E7)*E6)*((INPUTS!$C$28/((BOM!$E$22*(1-E8)+E9)*E6))*365/E10))<=180000,0.04,IF((((INPUTS!$C$6*E7)*E6)*((INPUTS!$C$28/((BOM!$E$22*(1-E8)+E9)*E6))*365/E10))<=360000,((((INPUTS!$C$6*E7)*E6)*((INPUTS!$C$28/((BOM!$E$22*(1-E8)+E9)*E6))*365/E10))*0.073-5940)/(((INPUTS!$C$6*E7)*E6)*((INPUTS!$C$28/((BOM!$E$22*(1-E8)+E9)*E6))*365/E10)),IF((((INPUTS!$C$6*E7)*E6)*((INPUTS!$C$28/((BOM!$E$22*(1-E8)+E9)*E6))*365/E10))<=720000,((((INPUTS!$C$6*E7)*E6)*((INPUTS!$C$28/((BOM!$E$22*(1-E8)+E9)*E6))*365/E10))*0.095-13860)/(((INPUTS!$C$6*E7)*E6)*((INPUTS!$C$28/((BOM!$E$22*(1-E8)+E9)*E6))*365/E10)),IF((((INPUTS!$C$6*E7)*E6)*((INPUTS!$C$28/((BOM!$E$22*(1-E8)+E9)*E6))*365/E10))<=1800000,((((INPUTS!$C$6*E7)*E6)*((INPUTS!$C$28/((BOM!$E$22*(1-E8)+E9)*E6))*365/E10))*0.107-22500)/(((INPUTS!$C$6*E7)*E6)*((INPUTS!$C$28/((BOM!$E$22*(1-E8)+E9)*E6))*365/E10)),IF((((INPUTS!$C$6*E7)*E6)*((INPUTS!$C$28/((BOM!$E$22*(1-E8)+E9)*E6))*365/E10))<=3600000,((((INPUTS!$C$6*E7)*E6)*((INPUTS!$C$28/((BOM!$E$22*(1-E8)+E9)*E6))*365/E10))*0.143-87300)/(((INPUTS!$C$6*E7)*E6)*((INPUTS!$C$28/((BOM!$E$22*(1-E8)+E9)*E6))*365/E10)),((((INPUTS!$C$6*E7)*E6)*((INPUTS!$C$28/((BOM!$E$22*(1-E8)+E9)*E6))*365/E10))*0.19-378000)/(((INPUTS!$C$6*E7)*E6)*((INPUTS!$C$28/((BOM!$E$22*(1-E8)+E9)*E6))*365/E10)))))))))-MIN(((INPUTS!$C$6*E7)*E6)*INPUTS!$C$25,INPUTS!$C$26))/((INPUTS!$C$6*E7)*E6)) | F18: =IF(((INPUTS!$C$6*F7)*F6)=0,0,(((INPUTS!$C$6*F7)*F6)-((BOM!$E$22*(1-F8)+F9)*F6)-((INPUTS!$C$6*F7)*F6)*(IF((((INPUTS!$C$6*F7)*F6)*((INPUTS!$C$28/((BOM!$E$22*(1-F8)+F9)*F6))*365/F10))<=0,0.04,IF((((INPUTS!$C$6*F7)*F6)*((INPUTS!$C$28/((BOM!$E$22*(1-F8)+F9)*F6))*365/F10))<=180000,0.04,IF((((INPUTS!$C$6*F7)*F6)*((INPUTS!$C$28/((BOM!$E$22*(1-F8)+F9)*F6))*365/F10))<=360000,((((INPUTS!$C$6*F7)*F6)*((INPUTS!$C$28/((BOM!$E$22*(1-F8)+F9)*F6))*365/F10))*0.073-5940)/(((INPUTS!$C$6*F7)*F6)*((INPUTS!$C$28/((BOM!$E$22*(1-F8)+F9)*F6))*365/F10)),IF((((INPUTS!$C$6*F7)*F6)*((INPUTS!$C$28/((BOM!$E$22*(1-F8)+F9)*F6))*365/F10))<=720000,((((INPUTS!$C$6*F7)*F6)*((INPUTS!$C$28/((BOM!$E$22*(1-F8)+F9)*F6))*365/F10))*0.095-13860)/(((INPUTS!$C$6*F7)*F6)*((INPUTS!$C$28/((BOM!$E$22*(1-F8)+F9)*F6))*365/F10)),IF((((INPUTS!$C$6*F7)*F6)*((INPUTS!$C$28/((BOM!$E$22*(1-F8)+F9)*F6))*365/F10))<=1800000,((((INPUTS!$C$6*F7)*F6)*((INPUTS!$C$28/((BOM!$E$22*(1-F8)+F9)*F6))*365/F10))*0.107-22500)/(((INPUTS!$C$6*F7)*F6)*((INPUTS!$C$28/((BOM!$E$22*(1-F8)+F9)*F6))*365/F10)),IF((((INPUTS!$C$6*F7)*F6)*((INPUTS!$C$28/((BOM!$E$22*(1-F8)+F9)*F6))*365/F10))<=3600000,((((INPUTS!$C$6*F7)*F6)*((INPUTS!$C$28/((BOM!$E$22*(1-F8)+F9)*F6))*365/F10))*0.143-87300)/(((INPUTS!$C$6*F7)*F6)*((INPUTS!$C$28/((BOM!$E$22*(1-F8)+F9)*F6))*365/F10)),((((INPUTS!$C$6*F7)*F6)*((INPUTS!$C$28/((BOM!$E$22*(1-F8)+F9)*F6))*365/F10))*0.19-378000)/(((INPUTS!$C$6*F7)*F6)*((INPUTS!$C$28/((BOM!$E$22*(1-F8)+F9)*F6))*365/F10)))))))))-MIN(((INPUTS!$C$6*F7)*F6)*INPUTS!$C$25,INPUTS!$C$26))/((INPUTS!$C$6*F7)*F6)) | G18: =IF(((INPUTS!$C$6*G7)*G6)=0,0,(((INPUTS!$C$6*G7)*G6)-((BOM!$E$22*(1-G8)+G9)*G6)-((INPUTS!$C$6*G7)*G6)*(IF((((INPUTS!$C$6*G7)*G6)*((INPUTS!$C$28/((BOM!$E$22*(1-G8)+G9)*G6))*365/G10))<=0,0.04,IF((((INPUTS!$C$6*G7)*G6)*((INPUTS!$C$28/((BOM!$E$22*(1-G8)+G9)*G6))*365/G10))<=180000,0.04,IF((((INPUTS!$C$6*G7)*G6)*((INPUTS!$C$28/((BOM!$E$22*(1-G8)+G9)*G6))*365/G10))<=360000,((((INPUTS!$C$6*G7)*G6)*((INPUTS!$C$28/((BOM!$E$22*(1-G8)+G9)*G6))*365/G10))*0.073-5940)/(((INPUTS!$C$6*G7)*G6)*((INPUTS!$C$28/((BOM!$E$22*(1-G8)+G9)*G6))*365/G10)),IF((((INPUTS!$C$6*G7)*G6)*((INPUTS!$C$28/((BOM!$E$22*(1-G8)+G9)*G6))*365/G10))<=720000,((((INPUTS!$C$6*G7)*G6)*((INPUTS!$C$28/((BOM!$E$22*(1-G8)+G9)*G6))*365/G10))*0.095-13860)/(((INPUTS!$C$6*G7)*G6)*((INPUTS!$C$28/((BOM!$E$22*(1-G8)+G9)*G6))*365/G10)),IF((((INPUTS!$C$6*G7)*G6)*((INPUTS!$C$28/((BOM!$E$22*(1-G8)+G9)*G6))*365/G10))<=1800000,((((INPUTS!$C$6*G7)*G6)*((INPUTS!$C$28/((BOM!$E$22*(1-G8)+G9)*G6))*365/G10))*0.107-22500)/(((INPUTS!$C$6*G7)*G6)*((INPUTS!$C$28/((BOM!$E$22*(1-G8)+G9)*G6))*365/G10)),IF((((INPUTS!$C$6*G7)*G6)*((INPUTS!$C$28/((BOM!$E$22*(1-G8)+G9)*G6))*365/G10))<=3600000,((((INPUTS!$C$6*G7)*G6)*((INPUTS!$C$28/((BOM!$E$22*(1-G8)+G9)*G6))*365/G10))*0.143-87300)/(((INPUTS!$C$6*G7)*G6)*((INPUTS!$C$28/((BOM!$E$22*(1-G8)+G9)*G6))*365/G10)),((((INPUTS!$C$6*G7)*G6)*((INPUTS!$C$28/((BOM!$E$22*(1-G8)+G9)*G6))*365/G10))*0.19-378000)/(((INPUTS!$C$6*G7)*G6)*((INPUTS!$C$28/((BOM!$E$22*(1-G8)+G9)*G6))*365/G10)))))))))-MIN(((INPUTS!$C$6*G7)*G6)*INPUTS!$C$25,INPUTS!$C$26))/((INPUTS!$C$6*G7)*G6)) | H18: =IF(((INPUTS!$C$6*H7)*H6)=0,0,(((INPUTS!$C$6*H7)*H6)-((BOM!$E$22*(1-H8)+H9)*H6)-((INPUTS!$C$6*H7)*H6)*(IF((((INPUTS!$C$6*H7)*H6)*((INPUTS!$C$28/((BOM!$E$22*(1-H8)+H9)*H6))*365/H10))<=0,0.04,IF((((INPUTS!$C$6*H7)*H6)*((INPUTS!$C$28/((BOM!$E$22*(1-H8)+H9)*H6))*365/H10))<=180000,0.04,IF((((INPUTS!$C$6*H7)*H6)*((INPUTS!$C$28/((BOM!$E$22*(1-H8)+H9)*H6))*365/H10))<=360000,((((INPUTS!$C$6*H7)*H6)*((INPUTS!$C$28/((BOM!$E$22*(1-H8)+H9)*H6))*365/H10))*0.073-5940)/(((INPUTS!$C$6*H7)*H6)*((INPUTS!$C$28/((BOM!$E$22*(1-H8)+H9)*H6))*365/H10)),IF((((INPUTS!$C$6*H7)*H6)*((INPUTS!$C$28/((BOM!$E$22*(1-H8)+H9)*H6))*365/H10))<=720000,((((INPUTS!$C$6*H7)*H6)*((INPUTS!$C$28/((BOM!$E$22*(1-H8)+H9)*H6))*365/H10))*0.095-13860)/(((INPUTS!$C$6*H7)*H6)*((INPUTS!$C$28/((BOM!$E$22*(1-H8)+H9)*H6))*365/H10)),IF((((INPUTS!$C$6*H7)*H6)*((INPUTS!$C$28/((BOM!$E$22*(1-H8)+H9)*H6))*365/H10))<=1800000,((((INPUTS!$C$6*H7)*H6)*((INPUTS!$C$28/((BOM!$E$22*(1-H8)+H9)*H6))*365/H10))*0.107-22500)/(((INPUTS!$C$6*H7)*H6)*((INPUTS!$C$28/((BOM!$E$22*(1-H8)+H9)*H6))*365/H10)),IF((((INPUTS!$C$6*H7)*H6)*((INPUTS!$C$28/((BOM!$E$22*(1-H8)+H9)*H6))*365/H10))<=3600000,((((INPUTS!$C$6*H7)*H6)*((INPUTS!$C$28/((BOM!$E$22*(1-H8)+H9)*H6))*365/H10))*0.143-87300)/(((INPUTS!$C$6*H7)*H6)*((INPUTS!$C$28/((BOM!$E$22*(1-H8)+H9)*H6))*365/H10)),((((INPUTS!$C$6*H7)*H6)*((INPUTS!$C$28/((BOM!$E$22*(1-H8)+H9)*H6))*365/H10))*0.19-378000)/(((INPUTS!$C$6*H7)*H6)*((INPUTS!$C$28/((BOM!$E$22*(1-H8)+H9)*H6))*365/H10)))))))))-MIN(((INPUTS!$C$6*H7)*H6)*INPUTS!$C$25,INPUTS!$C$26))/((INPUTS!$C$6*H7)*H6))
B19: Net profit on the lot | C19: =(((INPUTS!$C$6*C7)*C6)-((BOM!$E$22*(1-C8)+C9)*C6)-((INPUTS!$C$6*C7)*C6)*(IF((((INPUTS!$C$6*C7)*C6)*((INPUTS!$C$28/((BOM!$E$22*(1-C8)+C9)*C6))*365/C10))<=0,0.04,IF((((INPUTS!$C$6*C7)*C6)*((INPUTS!$C$28/((BOM!$E$22*(1-C8)+C9)*C6))*365/C10))<=180000,0.04,IF((((INPUTS!$C$6*C7)*C6)*((INPUTS!$C$28/((BOM!$E$22*(1-C8)+C9)*C6))*365/C10))<=360000,((((INPUTS!$C$6*C7)*C6)*((INPUTS!$C$28/((BOM!$E$22*(1-C8)+C9)*C6))*365/C10))*0.073-5940)/(((INPUTS!$C$6*C7)*C6)*((INPUTS!$C$28/((BOM!$E$22*(1-C8)+C9)*C6))*365/C10)),IF((((INPUTS!$C$6*C7)*C6)*((INPUTS!$C$28/((BOM!$E$22*(1-C8)+C9)*C6))*365/C10))<=720000,((((INPUTS!$C$6*C7)*C6)*((INPUTS!$C$28/((BOM!$E$22*(1-C8)+C9)*C6))*365/C10))*0.095-13860)/(((INPUTS!$C$6*C7)*C6)*((INPUTS!$C$28/((BOM!$E$22*(1-C8)+C9)*C6))*365/C10)),IF((((INPUTS!$C$6*C7)*C6)*((INPUTS!$C$28/((BOM!$E$22*(1-C8)+C9)*C6))*365/C10))<=1800000,((((INPUTS!$C$6*C7)*C6)*((INPUTS!$C$28/((BOM!$E$22*(1-C8)+C9)*C6))*365/C10))*0.107-22500)/(((INPUTS!$C$6*C7)*C6)*((INPUTS!$C$28/((BOM!$E$22*(1-C8)+C9)*C6))*365/C10)),IF((((INPUTS!$C$6*C7)*C6)*((INPUTS!$C$28/((BOM!$E$22*(1-C8)+C9)*C6))*365/C10))<=3600000,((((INPUTS!$C$6*C7)*C6)*((INPUTS!$C$28/((BOM!$E$22*(1-C8)+C9)*C6))*365/C10))*0.143-87300)/(((INPUTS!$C$6*C7)*C6)*((INPUTS!$C$28/((BOM!$E$22*(1-C8)+C9)*C6))*365/C10)),((((INPUTS!$C$6*C7)*C6)*((INPUTS!$C$28/((BOM!$E$22*(1-C8)+C9)*C6))*365/C10))*0.19-378000)/(((INPUTS!$C$6*C7)*C6)*((INPUTS!$C$28/((BOM!$E$22*(1-C8)+C9)*C6))*365/C10)))))))))-MIN(((INPUTS!$C$6*C7)*C6)*INPUTS!$C$25,INPUTS!$C$26)) | D19: =(((INPUTS!$C$6*D7)*D6)-((BOM!$E$22*(1-D8)+D9)*D6)-((INPUTS!$C$6*D7)*D6)*(IF((((INPUTS!$C$6*D7)*D6)*((INPUTS!$C$28/((BOM!$E$22*(1-D8)+D9)*D6))*365/D10))<=0,0.04,IF((((INPUTS!$C$6*D7)*D6)*((INPUTS!$C$28/((BOM!$E$22*(1-D8)+D9)*D6))*365/D10))<=180000,0.04,IF((((INPUTS!$C$6*D7)*D6)*((INPUTS!$C$28/((BOM!$E$22*(1-D8)+D9)*D6))*365/D10))<=360000,((((INPUTS!$C$6*D7)*D6)*((INPUTS!$C$28/((BOM!$E$22*(1-D8)+D9)*D6))*365/D10))*0.073-5940)/(((INPUTS!$C$6*D7)*D6)*((INPUTS!$C$28/((BOM!$E$22*(1-D8)+D9)*D6))*365/D10)),IF((((INPUTS!$C$6*D7)*D6)*((INPUTS!$C$28/((BOM!$E$22*(1-D8)+D9)*D6))*365/D10))<=720000,((((INPUTS!$C$6*D7)*D6)*((INPUTS!$C$28/((BOM!$E$22*(1-D8)+D9)*D6))*365/D10))*0.095-13860)/(((INPUTS!$C$6*D7)*D6)*((INPUTS!$C$28/((BOM!$E$22*(1-D8)+D9)*D6))*365/D10)),IF((((INPUTS!$C$6*D7)*D6)*((INPUTS!$C$28/((BOM!$E$22*(1-D8)+D9)*D6))*365/D10))<=1800000,((((INPUTS!$C$6*D7)*D6)*((INPUTS!$C$28/((BOM!$E$22*(1-D8)+D9)*D6))*365/D10))*0.107-22500)/(((INPUTS!$C$6*D7)*D6)*((INPUTS!$C$28/((BOM!$E$22*(1-D8)+D9)*D6))*365/D10)),IF((((INPUTS!$C$6*D7)*D6)*((INPUTS!$C$28/((BOM!$E$22*(1-D8)+D9)*D6))*365/D10))<=3600000,((((INPUTS!$C$6*D7)*D6)*((INPUTS!$C$28/((BOM!$E$22*(1-D8)+D9)*D6))*365/D10))*0.143-87300)/(((INPUTS!$C$6*D7)*D6)*((INPUTS!$C$28/((BOM!$E$22*(1-D8)+D9)*D6))*365/D10)),((((INPUTS!$C$6*D7)*D6)*((INPUTS!$C$28/((BOM!$E$22*(1-D8)+D9)*D6))*365/D10))*0.19-378000)/(((INPUTS!$C$6*D7)*D6)*((INPUTS!$C$28/((BOM!$E$22*(1-D8)+D9)*D6))*365/D10)))))))))-MIN(((INPUTS!$C$6*D7)*D6)*INPUTS!$C$25,INPUTS!$C$26)) | E19: =(((INPUTS!$C$6*E7)*E6)-((BOM!$E$22*(1-E8)+E9)*E6)-((INPUTS!$C$6*E7)*E6)*(IF((((INPUTS!$C$6*E7)*E6)*((INPUTS!$C$28/((BOM!$E$22*(1-E8)+E9)*E6))*365/E10))<=0,0.04,IF((((INPUTS!$C$6*E7)*E6)*((INPUTS!$C$28/((BOM!$E$22*(1-E8)+E9)*E6))*365/E10))<=180000,0.04,IF((((INPUTS!$C$6*E7)*E6)*((INPUTS!$C$28/((BOM!$E$22*(1-E8)+E9)*E6))*365/E10))<=360000,((((INPUTS!$C$6*E7)*E6)*((INPUTS!$C$28/((BOM!$E$22*(1-E8)+E9)*E6))*365/E10))*0.073-5940)/(((INPUTS!$C$6*E7)*E6)*((INPUTS!$C$28/((BOM!$E$22*(1-E8)+E9)*E6))*365/E10)),IF((((INPUTS!$C$6*E7)*E6)*((INPUTS!$C$28/((BOM!$E$22*(1-E8)+E9)*E6))*365/E10))<=720000,((((INPUTS!$C$6*E7)*E6)*((INPUTS!$C$28/((BOM!$E$22*(1-E8)+E9)*E6))*365/E10))*0.095-13860)/(((INPUTS!$C$6*E7)*E6)*((INPUTS!$C$28/((BOM!$E$22*(1-E8)+E9)*E6))*365/E10)),IF((((INPUTS!$C$6*E7)*E6)*((INPUTS!$C$28/((BOM!$E$22*(1-E8)+E9)*E6))*365/E10))<=1800000,((((INPUTS!$C$6*E7)*E6)*((INPUTS!$C$28/((BOM!$E$22*(1-E8)+E9)*E6))*365/E10))*0.107-22500)/(((INPUTS!$C$6*E7)*E6)*((INPUTS!$C$28/((BOM!$E$22*(1-E8)+E9)*E6))*365/E10)),IF((((INPUTS!$C$6*E7)*E6)*((INPUTS!$C$28/((BOM!$E$22*(1-E8)+E9)*E6))*365/E10))<=3600000,((((INPUTS!$C$6*E7)*E6)*((INPUTS!$C$28/((BOM!$E$22*(1-E8)+E9)*E6))*365/E10))*0.143-87300)/(((INPUTS!$C$6*E7)*E6)*((INPUTS!$C$28/((BOM!$E$22*(1-E8)+E9)*E6))*365/E10)),((((INPUTS!$C$6*E7)*E6)*((INPUTS!$C$28/((BOM!$E$22*(1-E8)+E9)*E6))*365/E10))*0.19-378000)/(((INPUTS!$C$6*E7)*E6)*((INPUTS!$C$28/((BOM!$E$22*(1-E8)+E9)*E6))*365/E10)))))))))-MIN(((INPUTS!$C$6*E7)*E6)*INPUTS!$C$25,INPUTS!$C$26)) | F19: =(((INPUTS!$C$6*F7)*F6)-((BOM!$E$22*(1-F8)+F9)*F6)-((INPUTS!$C$6*F7)*F6)*(IF((((INPUTS!$C$6*F7)*F6)*((INPUTS!$C$28/((BOM!$E$22*(1-F8)+F9)*F6))*365/F10))<=0,0.04,IF((((INPUTS!$C$6*F7)*F6)*((INPUTS!$C$28/((BOM!$E$22*(1-F8)+F9)*F6))*365/F10))<=180000,0.04,IF((((INPUTS!$C$6*F7)*F6)*((INPUTS!$C$28/((BOM!$E$22*(1-F8)+F9)*F6))*365/F10))<=360000,((((INPUTS!$C$6*F7)*F6)*((INPUTS!$C$28/((BOM!$E$22*(1-F8)+F9)*F6))*365/F10))*0.073-5940)/(((INPUTS!$C$6*F7)*F6)*((INPUTS!$C$28/((BOM!$E$22*(1-F8)+F9)*F6))*365/F10)),IF((((INPUTS!$C$6*F7)*F6)*((INPUTS!$C$28/((BOM!$E$22*(1-F8)+F9)*F6))*365/F10))<=720000,((((INPUTS!$C$6*F7)*F6)*((INPUTS!$C$28/((BOM!$E$22*(1-F8)+F9)*F6))*365/F10))*0.095-13860)/(((INPUTS!$C$6*F7)*F6)*((INPUTS!$C$28/((BOM!$E$22*(1-F8)+F9)*F6))*365/F10)),IF((((INPUTS!$C$6*F7)*F6)*((INPUTS!$C$28/((BOM!$E$22*(1-F8)+F9)*F6))*365/F10))<=1800000,((((INPUTS!$C$6*F7)*F6)*((INPUTS!$C$28/((BOM!$E$22*(1-F8)+F9)*F6))*365/F10))*0.107-22500)/(((INPUTS!$C$6*F7)*F6)*((INPUTS!$C$28/((BOM!$E$22*(1-F8)+F9)*F6))*365/F10)),IF((((INPUTS!$C$6*F7)*F6)*((INPUTS!$C$28/((BOM!$E$22*(1-F8)+F9)*F6))*365/F10))<=3600000,((((INPUTS!$C$6*F7)*F6)*((INPUTS!$C$28/((BOM!$E$22*(1-F8)+F9)*F6))*365/F10))*0.143-87300)/(((INPUTS!$C$6*F7)*F6)*((INPUTS!$C$28/((BOM!$E$22*(1-F8)+F9)*F6))*365/F10)),((((INPUTS!$C$6*F7)*F6)*((INPUTS!$C$28/((BOM!$E$22*(1-F8)+F9)*F6))*365/F10))*0.19-378000)/(((INPUTS!$C$6*F7)*F6)*((INPUTS!$C$28/((BOM!$E$22*(1-F8)+F9)*F6))*365/F10)))))))))-MIN(((INPUTS!$C$6*F7)*F6)*INPUTS!$C$25,INPUTS!$C$26)) | G19: =(((INPUTS!$C$6*G7)*G6)-((BOM!$E$22*(1-G8)+G9)*G6)-((INPUTS!$C$6*G7)*G6)*(IF((((INPUTS!$C$6*G7)*G6)*((INPUTS!$C$28/((BOM!$E$22*(1-G8)+G9)*G6))*365/G10))<=0,0.04,IF((((INPUTS!$C$6*G7)*G6)*((INPUTS!$C$28/((BOM!$E$22*(1-G8)+G9)*G6))*365/G10))<=180000,0.04,IF((((INPUTS!$C$6*G7)*G6)*((INPUTS!$C$28/((BOM!$E$22*(1-G8)+G9)*G6))*365/G10))<=360000,((((INPUTS!$C$6*G7)*G6)*((INPUTS!$C$28/((BOM!$E$22*(1-G8)+G9)*G6))*365/G10))*0.073-5940)/(((INPUTS!$C$6*G7)*G6)*((INPUTS!$C$28/((BOM!$E$22*(1-G8)+G9)*G6))*365/G10)),IF((((INPUTS!$C$6*G7)*G6)*((INPUTS!$C$28/((BOM!$E$22*(1-G8)+G9)*G6))*365/G10))<=720000,((((INPUTS!$C$6*G7)*G6)*((INPUTS!$C$28/((BOM!$E$22*(1-G8)+G9)*G6))*365/G10))*0.095-13860)/(((INPUTS!$C$6*G7)*G6)*((INPUTS!$C$28/((BOM!$E$22*(1-G8)+G9)*G6))*365/G10)),IF((((INPUTS!$C$6*G7)*G6)*((INPUTS!$C$28/((BOM!$E$22*(1-G8)+G9)*G6))*365/G10))<=1800000,((((INPUTS!$C$6*G7)*G6)*((INPUTS!$C$28/((BOM!$E$22*(1-G8)+G9)*G6))*365/G10))*0.107-22500)/(((INPUTS!$C$6*G7)*G6)*((INPUTS!$C$28/((BOM!$E$22*(1-G8)+G9)*G6))*365/G10)),IF((((INPUTS!$C$6*G7)*G6)*((INPUTS!$C$28/((BOM!$E$22*(1-G8)+G9)*G6))*365/G10))<=3600000,((((INPUTS!$C$6*G7)*G6)*((INPUTS!$C$28/((BOM!$E$22*(1-G8)+G9)*G6))*365/G10))*0.143-87300)/(((INPUTS!$C$6*G7)*G6)*((INPUTS!$C$28/((BOM!$E$22*(1-G8)+G9)*G6))*365/G10)),((((INPUTS!$C$6*G7)*G6)*((INPUTS!$C$28/((BOM!$E$22*(1-G8)+G9)*G6))*365/G10))*0.19-378000)/(((INPUTS!$C$6*G7)*G6)*((INPUTS!$C$28/((BOM!$E$22*(1-G8)+G9)*G6))*365/G10)))))))))-MIN(((INPUTS!$C$6*G7)*G6)*INPUTS!$C$25,INPUTS!$C$26)) | H19: =(((INPUTS!$C$6*H7)*H6)-((BOM!$E$22*(1-H8)+H9)*H6)-((INPUTS!$C$6*H7)*H6)*(IF((((INPUTS!$C$6*H7)*H6)*((INPUTS!$C$28/((BOM!$E$22*(1-H8)+H9)*H6))*365/H10))<=0,0.04,IF((((INPUTS!$C$6*H7)*H6)*((INPUTS!$C$28/((BOM!$E$22*(1-H8)+H9)*H6))*365/H10))<=180000,0.04,IF((((INPUTS!$C$6*H7)*H6)*((INPUTS!$C$28/((BOM!$E$22*(1-H8)+H9)*H6))*365/H10))<=360000,((((INPUTS!$C$6*H7)*H6)*((INPUTS!$C$28/((BOM!$E$22*(1-H8)+H9)*H6))*365/H10))*0.073-5940)/(((INPUTS!$C$6*H7)*H6)*((INPUTS!$C$28/((BOM!$E$22*(1-H8)+H9)*H6))*365/H10)),IF((((INPUTS!$C$6*H7)*H6)*((INPUTS!$C$28/((BOM!$E$22*(1-H8)+H9)*H6))*365/H10))<=720000,((((INPUTS!$C$6*H7)*H6)*((INPUTS!$C$28/((BOM!$E$22*(1-H8)+H9)*H6))*365/H10))*0.095-13860)/(((INPUTS!$C$6*H7)*H6)*((INPUTS!$C$28/((BOM!$E$22*(1-H8)+H9)*H6))*365/H10)),IF((((INPUTS!$C$6*H7)*H6)*((INPUTS!$C$28/((BOM!$E$22*(1-H8)+H9)*H6))*365/H10))<=1800000,((((INPUTS!$C$6*H7)*H6)*((INPUTS!$C$28/((BOM!$E$22*(1-H8)+H9)*H6))*365/H10))*0.107-22500)/(((INPUTS!$C$6*H7)*H6)*((INPUTS!$C$28/((BOM!$E$22*(1-H8)+H9)*H6))*365/H10)),IF((((INPUTS!$C$6*H7)*H6)*((INPUTS!$C$28/((BOM!$E$22*(1-H8)+H9)*H6))*365/H10))<=3600000,((((INPUTS!$C$6*H7)*H6)*((INPUTS!$C$28/((BOM!$E$22*(1-H8)+H9)*H6))*365/H10))*0.143-87300)/(((INPUTS!$C$6*H7)*H6)*((INPUTS!$C$28/((BOM!$E$22*(1-H8)+H9)*H6))*365/H10)),((((INPUTS!$C$6*H7)*H6)*((INPUTS!$C$28/((BOM!$E$22*(1-H8)+H9)*H6))*365/H10))*0.19-378000)/(((INPUTS!$C$6*H7)*H6)*((INPUTS!$C$28/((BOM!$E$22*(1-H8)+H9)*H6))*365/H10)))))))))-MIN(((INPUTS!$C$6*H7)*H6)*INPUTS!$C$25,INPUTS!$C$26))
B21: A YEAR OF LOTS LIKE THIS
B22: Lots the capital can actually carry | C22: =((INPUTS!$C$28/((BOM!$E$22*(1-C8)+C9)*C6))*365/C10) | D22: =((INPUTS!$C$28/((BOM!$E$22*(1-D8)+D9)*D6))*365/D10) | E22: =((INPUTS!$C$28/((BOM!$E$22*(1-E8)+E9)*E6))*365/E10) | F22: =((INPUTS!$C$28/((BOM!$E$22*(1-F8)+F9)*F6))*365/F10) | G22: =((INPUTS!$C$28/((BOM!$E$22*(1-G8)+G9)*G6))*365/G10) | H22: =((INPUTS!$C$28/((BOM!$E$22*(1-H8)+H9)*H6))*365/H10) | I22: Not an assumption: capital ÷ cash per lot × 365 ÷ float days.
B23: Revenue for the year | C23: =(((INPUTS!$C$6*C7)*C6)*((INPUTS!$C$28/((BOM!$E$22*(1-C8)+C9)*C6))*365/C10)) | D23: =(((INPUTS!$C$6*D7)*D6)*((INPUTS!$C$28/((BOM!$E$22*(1-D8)+D9)*D6))*365/D10)) | E23: =(((INPUTS!$C$6*E7)*E6)*((INPUTS!$C$28/((BOM!$E$22*(1-E8)+E9)*E6))*365/E10)) | F23: =(((INPUTS!$C$6*F7)*F6)*((INPUTS!$C$28/((BOM!$E$22*(1-F8)+F9)*F6))*365/F10)) | G23: =(((INPUTS!$C$6*G7)*G6)*((INPUTS!$C$28/((BOM!$E$22*(1-G8)+G9)*G6))*365/G10)) | H23: =(((INPUTS!$C$6*H7)*H6)*((INPUTS!$C$28/((BOM!$E$22*(1-H8)+H9)*H6))*365/H10))
B24: Simples effective rate at that revenue | C24: =IF((((INPUTS!$C$6*C7)*C6)*((INPUTS!$C$28/((BOM!$E$22*(1-C8)+C9)*C6))*365/C10))<=0,0.04,IF((((INPUTS!$C$6*C7)*C6)*((INPUTS!$C$28/((BOM!$E$22*(1-C8)+C9)*C6))*365/C10))<=180000,0.04,IF((((INPUTS!$C$6*C7)*C6)*((INPUTS!$C$28/((BOM!$E$22*(1-C8)+C9)*C6))*365/C10))<=360000,((((INPUTS!$C$6*C7)*C6)*((INPUTS!$C$28/((BOM!$E$22*(1-C8)+C9)*C6))*365/C10))*0.073-5940)/(((INPUTS!$C$6*C7)*C6)*((INPUTS!$C$28/((BOM!$E$22*(1-C8)+C9)*C6))*365/C10)),IF((((INPUTS!$C$6*C7)*C6)*((INPUTS!$C$28/((BOM!$E$22*(1-C8)+C9)*C6))*365/C10))<=720000,((((INPUTS!$C$6*C7)*C6)*((INPUTS!$C$28/((BOM!$E$22*(1-C8)+C9)*C6))*365/C10))*0.095-13860)/(((INPUTS!$C$6*C7)*C6)*((INPUTS!$C$28/((BOM!$E$22*(1-C8)+C9)*C6))*365/C10)),IF((((INPUTS!$C$6*C7)*C6)*((INPUTS!$C$28/((BOM!$E$22*(1-C8)+C9)*C6))*365/C10))<=1800000,((((INPUTS!$C$6*C7)*C6)*((INPUTS!$C$28/((BOM!$E$22*(1-C8)+C9)*C6))*365/C10))*0.107-22500)/(((INPUTS!$C$6*C7)*C6)*((INPUTS!$C$28/((BOM!$E$22*(1-C8)+C9)*C6))*365/C10)),IF((((INPUTS!$C$6*C7)*C6)*((INPUTS!$C$28/((BOM!$E$22*(1-C8)+C9)*C6))*365/C10))<=3600000,((((INPUTS!$C$6*C7)*C6)*((INPUTS!$C$28/((BOM!$E$22*(1-C8)+C9)*C6))*365/C10))*0.143-87300)/(((INPUTS!$C$6*C7)*C6)*((INPUTS!$C$28/((BOM!$E$22*(1-C8)+C9)*C6))*365/C10)),((((INPUTS!$C$6*C7)*C6)*((INPUTS!$C$28/((BOM!$E$22*(1-C8)+C9)*C6))*365/C10))*0.19-378000)/(((INPUTS!$C$6*C7)*C6)*((INPUTS!$C$28/((BOM!$E$22*(1-C8)+C9)*C6))*365/C10)))))))) | D24: =IF((((INPUTS!$C$6*D7)*D6)*((INPUTS!$C$28/((BOM!$E$22*(1-D8)+D9)*D6))*365/D10))<=0,0.04,IF((((INPUTS!$C$6*D7)*D6)*((INPUTS!$C$28/((BOM!$E$22*(1-D8)+D9)*D6))*365/D10))<=180000,0.04,IF((((INPUTS!$C$6*D7)*D6)*((INPUTS!$C$28/((BOM!$E$22*(1-D8)+D9)*D6))*365/D10))<=360000,((((INPUTS!$C$6*D7)*D6)*((INPUTS!$C$28/((BOM!$E$22*(1-D8)+D9)*D6))*365/D10))*0.073-5940)/(((INPUTS!$C$6*D7)*D6)*((INPUTS!$C$28/((BOM!$E$22*(1-D8)+D9)*D6))*365/D10)),IF((((INPUTS!$C$6*D7)*D6)*((INPUTS!$C$28/((BOM!$E$22*(1-D8)+D9)*D6))*365/D10))<=720000,((((INPUTS!$C$6*D7)*D6)*((INPUTS!$C$28/((BOM!$E$22*(1-D8)+D9)*D6))*365/D10))*0.095-13860)/(((INPUTS!$C$6*D7)*D6)*((INPUTS!$C$28/((BOM!$E$22*(1-D8)+D9)*D6))*365/D10)),IF((((INPUTS!$C$6*D7)*D6)*((INPUTS!$C$28/((BOM!$E$22*(1-D8)+D9)*D6))*365/D10))<=1800000,((((INPUTS!$C$6*D7)*D6)*((INPUTS!$C$28/((BOM!$E$22*(1-D8)+D9)*D6))*365/D10))*0.107-22500)/(((INPUTS!$C$6*D7)*D6)*((INPUTS!$C$28/((BOM!$E$22*(1-D8)+D9)*D6))*365/D10)),IF((((INPUTS!$C$6*D7)*D6)*((INPUTS!$C$28/((BOM!$E$22*(1-D8)+D9)*D6))*365/D10))<=3600000,((((INPUTS!$C$6*D7)*D6)*((INPUTS!$C$28/((BOM!$E$22*(1-D8)+D9)*D6))*365/D10))*0.143-87300)/(((INPUTS!$C$6*D7)*D6)*((INPUTS!$C$28/((BOM!$E$22*(1-D8)+D9)*D6))*365/D10)),((((INPUTS!$C$6*D7)*D6)*((INPUTS!$C$28/((BOM!$E$22*(1-D8)+D9)*D6))*365/D10))*0.19-378000)/(((INPUTS!$C$6*D7)*D6)*((INPUTS!$C$28/((BOM!$E$22*(1-D8)+D9)*D6))*365/D10)))))))) | E24: =IF((((INPUTS!$C$6*E7)*E6)*((INPUTS!$C$28/((BOM!$E$22*(1-E8)+E9)*E6))*365/E10))<=0,0.04,IF((((INPUTS!$C$6*E7)*E6)*((INPUTS!$C$28/((BOM!$E$22*(1-E8)+E9)*E6))*365/E10))<=180000,0.04,IF((((INPUTS!$C$6*E7)*E6)*((INPUTS!$C$28/((BOM!$E$22*(1-E8)+E9)*E6))*365/E10))<=360000,((((INPUTS!$C$6*E7)*E6)*((INPUTS!$C$28/((BOM!$E$22*(1-E8)+E9)*E6))*365/E10))*0.073-5940)/(((INPUTS!$C$6*E7)*E6)*((INPUTS!$C$28/((BOM!$E$22*(1-E8)+E9)*E6))*365/E10)),IF((((INPUTS!$C$6*E7)*E6)*((INPUTS!$C$28/((BOM!$E$22*(1-E8)+E9)*E6))*365/E10))<=720000,((((INPUTS!$C$6*E7)*E6)*((INPUTS!$C$28/((BOM!$E$22*(1-E8)+E9)*E6))*365/E10))*0.095-13860)/(((INPUTS!$C$6*E7)*E6)*((INPUTS!$C$28/((BOM!$E$22*(1-E8)+E9)*E6))*365/E10)),IF((((INPUTS!$C$6*E7)*E6)*((INPUTS!$C$28/((BOM!$E$22*(1-E8)+E9)*E6))*365/E10))<=1800000,((((INPUTS!$C$6*E7)*E6)*((INPUTS!$C$28/((BOM!$E$22*(1-E8)+E9)*E6))*365/E10))*0.107-22500)/(((INPUTS!$C$6*E7)*E6)*((INPUTS!$C$28/((BOM!$E$22*(1-E8)+E9)*E6))*365/E10)),IF((((INPUTS!$C$6*E7)*E6)*((INPUTS!$C$28/((BOM!$E$22*(1-E8)+E9)*E6))*365/E10))<=3600000,((((INPUTS!$C$6*E7)*E6)*((INPUTS!$C$28/((BOM!$E$22*(1-E8)+E9)*E6))*365/E10))*0.143-87300)/(((INPUTS!$C$6*E7)*E6)*((INPUTS!$C$28/((BOM!$E$22*(1-E8)+E9)*E6))*365/E10)),((((INPUTS!$C$6*E7)*E6)*((INPUTS!$C$28/((BOM!$E$22*(1-E8)+E9)*E6))*365/E10))*0.19-378000)/(((INPUTS!$C$6*E7)*E6)*((INPUTS!$C$28/((BOM!$E$22*(1-E8)+E9)*E6))*365/E10)))))))) | F24: =IF((((INPUTS!$C$6*F7)*F6)*((INPUTS!$C$28/((BOM!$E$22*(1-F8)+F9)*F6))*365/F10))<=0,0.04,IF((((INPUTS!$C$6*F7)*F6)*((INPUTS!$C$28/((BOM!$E$22*(1-F8)+F9)*F6))*365/F10))<=180000,0.04,IF((((INPUTS!$C$6*F7)*F6)*((INPUTS!$C$28/((BOM!$E$22*(1-F8)+F9)*F6))*365/F10))<=360000,((((INPUTS!$C$6*F7)*F6)*((INPUTS!$C$28/((BOM!$E$22*(1-F8)+F9)*F6))*365/F10))*0.073-5940)/(((INPUTS!$C$6*F7)*F6)*((INPUTS!$C$28/((BOM!$E$22*(1-F8)+F9)*F6))*365/F10)),IF((((INPUTS!$C$6*F7)*F6)*((INPUTS!$C$28/((BOM!$E$22*(1-F8)+F9)*F6))*365/F10))<=720000,((((INPUTS!$C$6*F7)*F6)*((INPUTS!$C$28/((BOM!$E$22*(1-F8)+F9)*F6))*365/F10))*0.095-13860)/(((INPUTS!$C$6*F7)*F6)*((INPUTS!$C$28/((BOM!$E$22*(1-F8)+F9)*F6))*365/F10)),IF((((INPUTS!$C$6*F7)*F6)*((INPUTS!$C$28/((BOM!$E$22*(1-F8)+F9)*F6))*365/F10))<=1800000,((((INPUTS!$C$6*F7)*F6)*((INPUTS!$C$28/((BOM!$E$22*(1-F8)+F9)*F6))*365/F10))*0.107-22500)/(((INPUTS!$C$6*F7)*F6)*((INPUTS!$C$28/((BOM!$E$22*(1-F8)+F9)*F6))*365/F10)),IF((((INPUTS!$C$6*F7)*F6)*((INPUTS!$C$28/((BOM!$E$22*(1-F8)+F9)*F6))*365/F10))<=3600000,((((INPUTS!$C$6*F7)*F6)*((INPUTS!$C$28/((BOM!$E$22*(1-F8)+F9)*F6))*365/F10))*0.143-87300)/(((INPUTS!$C$6*F7)*F6)*((INPUTS!$C$28/((BOM!$E$22*(1-F8)+F9)*F6))*365/F10)),((((INPUTS!$C$6*F7)*F6)*((INPUTS!$C$28/((BOM!$E$22*(1-F8)+F9)*F6))*365/F10))*0.19-378000)/(((INPUTS!$C$6*F7)*F6)*((INPUTS!$C$28/((BOM!$E$22*(1-F8)+F9)*F6))*365/F10)))))))) | G24: =IF((((INPUTS!$C$6*G7)*G6)*((INPUTS!$C$28/((BOM!$E$22*(1-G8)+G9)*G6))*365/G10))<=0,0.04,IF((((INPUTS!$C$6*G7)*G6)*((INPUTS!$C$28/((BOM!$E$22*(1-G8)+G9)*G6))*365/G10))<=180000,0.04,IF((((INPUTS!$C$6*G7)*G6)*((INPUTS!$C$28/((BOM!$E$22*(1-G8)+G9)*G6))*365/G10))<=360000,((((INPUTS!$C$6*G7)*G6)*((INPUTS!$C$28/((BOM!$E$22*(1-G8)+G9)*G6))*365/G10))*0.073-5940)/(((INPUTS!$C$6*G7)*G6)*((INPUTS!$C$28/((BOM!$E$22*(1-G8)+G9)*G6))*365/G10)),IF((((INPUTS!$C$6*G7)*G6)*((INPUTS!$C$28/((BOM!$E$22*(1-G8)+G9)*G6))*365/G10))<=720000,((((INPUTS!$C$6*G7)*G6)*((INPUTS!$C$28/((BOM!$E$22*(1-G8)+G9)*G6))*365/G10))*0.095-13860)/(((INPUTS!$C$6*G7)*G6)*((INPUTS!$C$28/((BOM!$E$22*(1-G8)+G9)*G6))*365/G10)),IF((((INPUTS!$C$6*G7)*G6)*((INPUTS!$C$28/((BOM!$E$22*(1-G8)+G9)*G6))*365/G10))<=1800000,((((INPUTS!$C$6*G7)*G6)*((INPUTS!$C$28/((BOM!$E$22*(1-G8)+G9)*G6))*365/G10))*0.107-22500)/(((INPUTS!$C$6*G7)*G6)*((INPUTS!$C$28/((BOM!$E$22*(1-G8)+G9)*G6))*365/G10)),IF((((INPUTS!$C$6*G7)*G6)*((INPUTS!$C$28/((BOM!$E$22*(1-G8)+G9)*G6))*365/G10))<=3600000,((((INPUTS!$C$6*G7)*G6)*((INPUTS!$C$28/((BOM!$E$22*(1-G8)+G9)*G6))*365/G10))*0.143-87300)/(((INPUTS!$C$6*G7)*G6)*((INPUTS!$C$28/((BOM!$E$22*(1-G8)+G9)*G6))*365/G10)),((((INPUTS!$C$6*G7)*G6)*((INPUTS!$C$28/((BOM!$E$22*(1-G8)+G9)*G6))*365/G10))*0.19-378000)/(((INPUTS!$C$6*G7)*G6)*((INPUTS!$C$28/((BOM!$E$22*(1-G8)+G9)*G6))*365/G10)))))))) | H24: =IF((((INPUTS!$C$6*H7)*H6)*((INPUTS!$C$28/((BOM!$E$22*(1-H8)+H9)*H6))*365/H10))<=0,0.04,IF((((INPUTS!$C$6*H7)*H6)*((INPUTS!$C$28/((BOM!$E$22*(1-H8)+H9)*H6))*365/H10))<=180000,0.04,IF((((INPUTS!$C$6*H7)*H6)*((INPUTS!$C$28/((BOM!$E$22*(1-H8)+H9)*H6))*365/H10))<=360000,((((INPUTS!$C$6*H7)*H6)*((INPUTS!$C$28/((BOM!$E$22*(1-H8)+H9)*H6))*365/H10))*0.073-5940)/(((INPUTS!$C$6*H7)*H6)*((INPUTS!$C$28/((BOM!$E$22*(1-H8)+H9)*H6))*365/H10)),IF((((INPUTS!$C$6*H7)*H6)*((INPUTS!$C$28/((BOM!$E$22*(1-H8)+H9)*H6))*365/H10))<=720000,((((INPUTS!$C$6*H7)*H6)*((INPUTS!$C$28/((BOM!$E$22*(1-H8)+H9)*H6))*365/H10))*0.095-13860)/(((INPUTS!$C$6*H7)*H6)*((INPUTS!$C$28/((BOM!$E$22*(1-H8)+H9)*H6))*365/H10)),IF((((INPUTS!$C$6*H7)*H6)*((INPUTS!$C$28/((BOM!$E$22*(1-H8)+H9)*H6))*365/H10))<=1800000,((((INPUTS!$C$6*H7)*H6)*((INPUTS!$C$28/((BOM!$E$22*(1-H8)+H9)*H6))*365/H10))*0.107-22500)/(((INPUTS!$C$6*H7)*H6)*((INPUTS!$C$28/((BOM!$E$22*(1-H8)+H9)*H6))*365/H10)),IF((((INPUTS!$C$6*H7)*H6)*((INPUTS!$C$28/((BOM!$E$22*(1-H8)+H9)*H6))*365/H10))<=3600000,((((INPUTS!$C$6*H7)*H6)*((INPUTS!$C$28/((BOM!$E$22*(1-H8)+H9)*H6))*365/H10))*0.143-87300)/(((INPUTS!$C$6*H7)*H6)*((INPUTS!$C$28/((BOM!$E$22*(1-H8)+H9)*H6))*365/H10)),((((INPUTS!$C$6*H7)*H6)*((INPUTS!$C$28/((BOM!$E$22*(1-H8)+H9)*H6))*365/H10))*0.19-378000)/(((INPUTS!$C$6*H7)*H6)*((INPUTS!$C$28/((BOM!$E$22*(1-H8)+H9)*H6))*365/H10)))))))) | I24: Rises with revenue — the columns that scale pay a higher rate, and that is already deducted below.
B25: TAKE-HOME for the year, after fixed costs | C25: =((((INPUTS!$C$6*C7)*C6)-((BOM!$E$22*(1-C8)+C9)*C6)-((INPUTS!$C$6*C7)*C6)*(IF((((INPUTS!$C$6*C7)*C6)*((INPUTS!$C$28/((BOM!$E$22*(1-C8)+C9)*C6))*365/C10))<=0,0.04,IF((((INPUTS!$C$6*C7)*C6)*((INPUTS!$C$28/((BOM!$E$22*(1-C8)+C9)*C6))*365/C10))<=180000,0.04,IF((((INPUTS!$C$6*C7)*C6)*((INPUTS!$C$28/((BOM!$E$22*(1-C8)+C9)*C6))*365/C10))<=360000,((((INPUTS!$C$6*C7)*C6)*((INPUTS!$C$28/((BOM!$E$22*(1-C8)+C9)*C6))*365/C10))*0.073-5940)/(((INPUTS!$C$6*C7)*C6)*((INPUTS!$C$28/((BOM!$E$22*(1-C8)+C9)*C6))*365/C10)),IF((((INPUTS!$C$6*C7)*C6)*((INPUTS!$C$28/((BOM!$E$22*(1-C8)+C9)*C6))*365/C10))<=720000,((((INPUTS!$C$6*C7)*C6)*((INPUTS!$C$28/((BOM!$E$22*(1-C8)+C9)*C6))*365/C10))*0.095-13860)/(((INPUTS!$C$6*C7)*C6)*((INPUTS!$C$28/((BOM!$E$22*(1-C8)+C9)*C6))*365/C10)),IF((((INPUTS!$C$6*C7)*C6)*((INPUTS!$C$28/((BOM!$E$22*(1-C8)+C9)*C6))*365/C10))<=1800000,((((INPUTS!$C$6*C7)*C6)*((INPUTS!$C$28/((BOM!$E$22*(1-C8)+C9)*C6))*365/C10))*0.107-22500)/(((INPUTS!$C$6*C7)*C6)*((INPUTS!$C$28/((BOM!$E$22*(1-C8)+C9)*C6))*365/C10)),IF((((INPUTS!$C$6*C7)*C6)*((INPUTS!$C$28/((BOM!$E$22*(1-C8)+C9)*C6))*365/C10))<=3600000,((((INPUTS!$C$6*C7)*C6)*((INPUTS!$C$28/((BOM!$E$22*(1-C8)+C9)*C6))*365/C10))*0.143-87300)/(((INPUTS!$C$6*C7)*C6)*((INPUTS!$C$28/((BOM!$E$22*(1-C8)+C9)*C6))*365/C10)),((((INPUTS!$C$6*C7)*C6)*((INPUTS!$C$28/((BOM!$E$22*(1-C8)+C9)*C6))*365/C10))*0.19-378000)/(((INPUTS!$C$6*C7)*C6)*((INPUTS!$C$28/((BOM!$E$22*(1-C8)+C9)*C6))*365/C10)))))))))-MIN(((INPUTS!$C$6*C7)*C6)*INPUTS!$C$25,INPUTS!$C$26))*((INPUTS!$C$28/((BOM!$E$22*(1-C8)+C9)*C6))*365/C10)-INPUTS!$C$33) | D25: =((((INPUTS!$C$6*D7)*D6)-((BOM!$E$22*(1-D8)+D9)*D6)-((INPUTS!$C$6*D7)*D6)*(IF((((INPUTS!$C$6*D7)*D6)*((INPUTS!$C$28/((BOM!$E$22*(1-D8)+D9)*D6))*365/D10))<=0,0.04,IF((((INPUTS!$C$6*D7)*D6)*((INPUTS!$C$28/((BOM!$E$22*(1-D8)+D9)*D6))*365/D10))<=180000,0.04,IF((((INPUTS!$C$6*D7)*D6)*((INPUTS!$C$28/((BOM!$E$22*(1-D8)+D9)*D6))*365/D10))<=360000,((((INPUTS!$C$6*D7)*D6)*((INPUTS!$C$28/((BOM!$E$22*(1-D8)+D9)*D6))*365/D10))*0.073-5940)/(((INPUTS!$C$6*D7)*D6)*((INPUTS!$C$28/((BOM!$E$22*(1-D8)+D9)*D6))*365/D10)),IF((((INPUTS!$C$6*D7)*D6)*((INPUTS!$C$28/((BOM!$E$22*(1-D8)+D9)*D6))*365/D10))<=720000,((((INPUTS!$C$6*D7)*D6)*((INPUTS!$C$28/((BOM!$E$22*(1-D8)+D9)*D6))*365/D10))*0.095-13860)/(((INPUTS!$C$6*D7)*D6)*((INPUTS!$C$28/((BOM!$E$22*(1-D8)+D9)*D6))*365/D10)),IF((((INPUTS!$C$6*D7)*D6)*((INPUTS!$C$28/((BOM!$E$22*(1-D8)+D9)*D6))*365/D10))<=1800000,((((INPUTS!$C$6*D7)*D6)*((INPUTS!$C$28/((BOM!$E$22*(1-D8)+D9)*D6))*365/D10))*0.107-22500)/(((INPUTS!$C$6*D7)*D6)*((INPUTS!$C$28/((BOM!$E$22*(1-D8)+D9)*D6))*365/D10)),IF((((INPUTS!$C$6*D7)*D6)*((INPUTS!$C$28/((BOM!$E$22*(1-D8)+D9)*D6))*365/D10))<=3600000,((((INPUTS!$C$6*D7)*D6)*((INPUTS!$C$28/((BOM!$E$22*(1-D8)+D9)*D6))*365/D10))*0.143-87300)/(((INPUTS!$C$6*D7)*D6)*((INPUTS!$C$28/((BOM!$E$22*(1-D8)+D9)*D6))*365/D10)),((((INPUTS!$C$6*D7)*D6)*((INPUTS!$C$28/((BOM!$E$22*(1-D8)+D9)*D6))*365/D10))*0.19-378000)/(((INPUTS!$C$6*D7)*D6)*((INPUTS!$C$28/((BOM!$E$22*(1-D8)+D9)*D6))*365/D10)))))))))-MIN(((INPUTS!$C$6*D7)*D6)*INPUTS!$C$25,INPUTS!$C$26))*((INPUTS!$C$28/((BOM!$E$22*(1-D8)+D9)*D6))*365/D10)-INPUTS!$C$33) | E25: =((((INPUTS!$C$6*E7)*E6)-((BOM!$E$22*(1-E8)+E9)*E6)-((INPUTS!$C$6*E7)*E6)*(IF((((INPUTS!$C$6*E7)*E6)*((INPUTS!$C$28/((BOM!$E$22*(1-E8)+E9)*E6))*365/E10))<=0,0.04,IF((((INPUTS!$C$6*E7)*E6)*((INPUTS!$C$28/((BOM!$E$22*(1-E8)+E9)*E6))*365/E10))<=180000,0.04,IF((((INPUTS!$C$6*E7)*E6)*((INPUTS!$C$28/((BOM!$E$22*(1-E8)+E9)*E6))*365/E10))<=360000,((((INPUTS!$C$6*E7)*E6)*((INPUTS!$C$28/((BOM!$E$22*(1-E8)+E9)*E6))*365/E10))*0.073-5940)/(((INPUTS!$C$6*E7)*E6)*((INPUTS!$C$28/((BOM!$E$22*(1-E8)+E9)*E6))*365/E10)),IF((((INPUTS!$C$6*E7)*E6)*((INPUTS!$C$28/((BOM!$E$22*(1-E8)+E9)*E6))*365/E10))<=720000,((((INPUTS!$C$6*E7)*E6)*((INPUTS!$C$28/((BOM!$E$22*(1-E8)+E9)*E6))*365/E10))*0.095-13860)/(((INPUTS!$C$6*E7)*E6)*((INPUTS!$C$28/((BOM!$E$22*(1-E8)+E9)*E6))*365/E10)),IF((((INPUTS!$C$6*E7)*E6)*((INPUTS!$C$28/((BOM!$E$22*(1-E8)+E9)*E6))*365/E10))<=1800000,((((INPUTS!$C$6*E7)*E6)*((INPUTS!$C$28/((BOM!$E$22*(1-E8)+E9)*E6))*365/E10))*0.107-22500)/(((INPUTS!$C$6*E7)*E6)*((INPUTS!$C$28/((BOM!$E$22*(1-E8)+E9)*E6))*365/E10)),IF((((INPUTS!$C$6*E7)*E6)*((INPUTS!$C$28/((BOM!$E$22*(1-E8)+E9)*E6))*365/E10))<=3600000,((((INPUTS!$C$6*E7)*E6)*((INPUTS!$C$28/((BOM!$E$22*(1-E8)+E9)*E6))*365/E10))*0.143-87300)/(((INPUTS!$C$6*E7)*E6)*((INPUTS!$C$28/((BOM!$E$22*(1-E8)+E9)*E6))*365/E10)),((((INPUTS!$C$6*E7)*E6)*((INPUTS!$C$28/((BOM!$E$22*(1-E8)+E9)*E6))*365/E10))*0.19-378000)/(((INPUTS!$C$6*E7)*E6)*((INPUTS!$C$28/((BOM!$E$22*(1-E8)+E9)*E6))*365/E10)))))))))-MIN(((INPUTS!$C$6*E7)*E6)*INPUTS!$C$25,INPUTS!$C$26))*((INPUTS!$C$28/((BOM!$E$22*(1-E8)+E9)*E6))*365/E10)-INPUTS!$C$33) | F25: =((((INPUTS!$C$6*F7)*F6)-((BOM!$E$22*(1-F8)+F9)*F6)-((INPUTS!$C$6*F7)*F6)*(IF((((INPUTS!$C$6*F7)*F6)*((INPUTS!$C$28/((BOM!$E$22*(1-F8)+F9)*F6))*365/F10))<=0,0.04,IF((((INPUTS!$C$6*F7)*F6)*((INPUTS!$C$28/((BOM!$E$22*(1-F8)+F9)*F6))*365/F10))<=180000,0.04,IF((((INPUTS!$C$6*F7)*F6)*((INPUTS!$C$28/((BOM!$E$22*(1-F8)+F9)*F6))*365/F10))<=360000,((((INPUTS!$C$6*F7)*F6)*((INPUTS!$C$28/((BOM!$E$22*(1-F8)+F9)*F6))*365/F10))*0.073-5940)/(((INPUTS!$C$6*F7)*F6)*((INPUTS!$C$28/((BOM!$E$22*(1-F8)+F9)*F6))*365/F10)),IF((((INPUTS!$C$6*F7)*F6)*((INPUTS!$C$28/((BOM!$E$22*(1-F8)+F9)*F6))*365/F10))<=720000,((((INPUTS!$C$6*F7)*F6)*((INPUTS!$C$28/((BOM!$E$22*(1-F8)+F9)*F6))*365/F10))*0.095-13860)/(((INPUTS!$C$6*F7)*F6)*((INPUTS!$C$28/((BOM!$E$22*(1-F8)+F9)*F6))*365/F10)),IF((((INPUTS!$C$6*F7)*F6)*((INPUTS!$C$28/((BOM!$E$22*(1-F8)+F9)*F6))*365/F10))<=1800000,((((INPUTS!$C$6*F7)*F6)*((INPUTS!$C$28/((BOM!$E$22*(1-F8)+F9)*F6))*365/F10))*0.107-22500)/(((INPUTS!$C$6*F7)*F6)*((INPUTS!$C$28/((BOM!$E$22*(1-F8)+F9)*F6))*365/F10)),IF((((INPUTS!$C$6*F7)*F6)*((INPUTS!$C$28/((BOM!$E$22*(1-F8)+F9)*F6))*365/F10))<=3600000,((((INPUTS!$C$6*F7)*F6)*((INPUTS!$C$28/((BOM!$E$22*(1-F8)+F9)*F6))*365/F10))*0.143-87300)/(((INPUTS!$C$6*F7)*F6)*((INPUTS!$C$28/((BOM!$E$22*(1-F8)+F9)*F6))*365/F10)),((((INPUTS!$C$6*F7)*F6)*((INPUTS!$C$28/((BOM!$E$22*(1-F8)+F9)*F6))*365/F10))*0.19-378000)/(((INPUTS!$C$6*F7)*F6)*((INPUTS!$C$28/((BOM!$E$22*(1-F8)+F9)*F6))*365/F10)))))))))-MIN(((INPUTS!$C$6*F7)*F6)*INPUTS!$C$25,INPUTS!$C$26))*((INPUTS!$C$28/((BOM!$E$22*(1-F8)+F9)*F6))*365/F10)-INPUTS!$C$33) | G25: =((((INPUTS!$C$6*G7)*G6)-((BOM!$E$22*(1-G8)+G9)*G6)-((INPUTS!$C$6*G7)*G6)*(IF((((INPUTS!$C$6*G7)*G6)*((INPUTS!$C$28/((BOM!$E$22*(1-G8)+G9)*G6))*365/G10))<=0,0.04,IF((((INPUTS!$C$6*G7)*G6)*((INPUTS!$C$28/((BOM!$E$22*(1-G8)+G9)*G6))*365/G10))<=180000,0.04,IF((((INPUTS!$C$6*G7)*G6)*((INPUTS!$C$28/((BOM!$E$22*(1-G8)+G9)*G6))*365/G10))<=360000,((((INPUTS!$C$6*G7)*G6)*((INPUTS!$C$28/((BOM!$E$22*(1-G8)+G9)*G6))*365/G10))*0.073-5940)/(((INPUTS!$C$6*G7)*G6)*((INPUTS!$C$28/((BOM!$E$22*(1-G8)+G9)*G6))*365/G10)),IF((((INPUTS!$C$6*G7)*G6)*((INPUTS!$C$28/((BOM!$E$22*(1-G8)+G9)*G6))*365/G10))<=720000,((((INPUTS!$C$6*G7)*G6)*((INPUTS!$C$28/((BOM!$E$22*(1-G8)+G9)*G6))*365/G10))*0.095-13860)/(((INPUTS!$C$6*G7)*G6)*((INPUTS!$C$28/((BOM!$E$22*(1-G8)+G9)*G6))*365/G10)),IF((((INPUTS!$C$6*G7)*G6)*((INPUTS!$C$28/((BOM!$E$22*(1-G8)+G9)*G6))*365/G10))<=1800000,((((INPUTS!$C$6*G7)*G6)*((INPUTS!$C$28/((BOM!$E$22*(1-G8)+G9)*G6))*365/G10))*0.107-22500)/(((INPUTS!$C$6*G7)*G6)*((INPUTS!$C$28/((BOM!$E$22*(1-G8)+G9)*G6))*365/G10)),IF((((INPUTS!$C$6*G7)*G6)*((INPUTS!$C$28/((BOM!$E$22*(1-G8)+G9)*G6))*365/G10))<=3600000,((((INPUTS!$C$6*G7)*G6)*((INPUTS!$C$28/((BOM!$E$22*(1-G8)+G9)*G6))*365/G10))*0.143-87300)/(((INPUTS!$C$6*G7)*G6)*((INPUTS!$C$28/((BOM!$E$22*(1-G8)+G9)*G6))*365/G10)),((((INPUTS!$C$6*G7)*G6)*((INPUTS!$C$28/((BOM!$E$22*(1-G8)+G9)*G6))*365/G10))*0.19-378000)/(((INPUTS!$C$6*G7)*G6)*((INPUTS!$C$28/((BOM!$E$22*(1-G8)+G9)*G6))*365/G10)))))))))-MIN(((INPUTS!$C$6*G7)*G6)*INPUTS!$C$25,INPUTS!$C$26))*((INPUTS!$C$28/((BOM!$E$22*(1-G8)+G9)*G6))*365/G10)-INPUTS!$C$33) | H25: =((((INPUTS!$C$6*H7)*H6)-((BOM!$E$22*(1-H8)+H9)*H6)-((INPUTS!$C$6*H7)*H6)*(IF((((INPUTS!$C$6*H7)*H6)*((INPUTS!$C$28/((BOM!$E$22*(1-H8)+H9)*H6))*365/H10))<=0,0.04,IF((((INPUTS!$C$6*H7)*H6)*((INPUTS!$C$28/((BOM!$E$22*(1-H8)+H9)*H6))*365/H10))<=180000,0.04,IF((((INPUTS!$C$6*H7)*H6)*((INPUTS!$C$28/((BOM!$E$22*(1-H8)+H9)*H6))*365/H10))<=360000,((((INPUTS!$C$6*H7)*H6)*((INPUTS!$C$28/((BOM!$E$22*(1-H8)+H9)*H6))*365/H10))*0.073-5940)/(((INPUTS!$C$6*H7)*H6)*((INPUTS!$C$28/((BOM!$E$22*(1-H8)+H9)*H6))*365/H10)),IF((((INPUTS!$C$6*H7)*H6)*((INPUTS!$C$28/((BOM!$E$22*(1-H8)+H9)*H6))*365/H10))<=720000,((((INPUTS!$C$6*H7)*H6)*((INPUTS!$C$28/((BOM!$E$22*(1-H8)+H9)*H6))*365/H10))*0.095-13860)/(((INPUTS!$C$6*H7)*H6)*((INPUTS!$C$28/((BOM!$E$22*(1-H8)+H9)*H6))*365/H10)),IF((((INPUTS!$C$6*H7)*H6)*((INPUTS!$C$28/((BOM!$E$22*(1-H8)+H9)*H6))*365/H10))<=1800000,((((INPUTS!$C$6*H7)*H6)*((INPUTS!$C$28/((BOM!$E$22*(1-H8)+H9)*H6))*365/H10))*0.107-22500)/(((INPUTS!$C$6*H7)*H6)*((INPUTS!$C$28/((BOM!$E$22*(1-H8)+H9)*H6))*365/H10)),IF((((INPUTS!$C$6*H7)*H6)*((INPUTS!$C$28/((BOM!$E$22*(1-H8)+H9)*H6))*365/H10))<=3600000,((((INPUTS!$C$6*H7)*H6)*((INPUTS!$C$28/((BOM!$E$22*(1-H8)+H9)*H6))*365/H10))*0.143-87300)/(((INPUTS!$C$6*H7)*H6)*((INPUTS!$C$28/((BOM!$E$22*(1-H8)+H9)*H6))*365/H10)),((((INPUTS!$C$6*H7)*H6)*((INPUTS!$C$28/((BOM!$E$22*(1-H8)+H9)*H6))*365/H10))*0.19-378000)/(((INPUTS!$C$6*H7)*H6)*((INPUTS!$C$28/((BOM!$E$22*(1-H8)+H9)*H6))*365/H10)))))))))-MIN(((INPUTS!$C$6*H7)*H6)*INPUTS!$C$25,INPUTS!$C$26))*((INPUTS!$C$28/((BOM!$E$22*(1-H8)+H9)*H6))*365/H10)-INPUTS!$C$33)
B26: …per month | C26: =(((((INPUTS!$C$6*C7)*C6)-((BOM!$E$22*(1-C8)+C9)*C6)-((INPUTS!$C$6*C7)*C6)*(IF((((INPUTS!$C$6*C7)*C6)*((INPUTS!$C$28/((BOM!$E$22*(1-C8)+C9)*C6))*365/C10))<=0,0.04,IF((((INPUTS!$C$6*C7)*C6)*((INPUTS!$C$28/((BOM!$E$22*(1-C8)+C9)*C6))*365/C10))<=180000,0.04,IF((((INPUTS!$C$6*C7)*C6)*((INPUTS!$C$28/((BOM!$E$22*(1-C8)+C9)*C6))*365/C10))<=360000,((((INPUTS!$C$6*C7)*C6)*((INPUTS!$C$28/((BOM!$E$22*(1-C8)+C9)*C6))*365/C10))*0.073-5940)/(((INPUTS!$C$6*C7)*C6)*((INPUTS!$C$28/((BOM!$E$22*(1-C8)+C9)*C6))*365/C10)),IF((((INPUTS!$C$6*C7)*C6)*((INPUTS!$C$28/((BOM!$E$22*(1-C8)+C9)*C6))*365/C10))<=720000,((((INPUTS!$C$6*C7)*C6)*((INPUTS!$C$28/((BOM!$E$22*(1-C8)+C9)*C6))*365/C10))*0.095-13860)/(((INPUTS!$C$6*C7)*C6)*((INPUTS!$C$28/((BOM!$E$22*(1-C8)+C9)*C6))*365/C10)),IF((((INPUTS!$C$6*C7)*C6)*((INPUTS!$C$28/((BOM!$E$22*(1-C8)+C9)*C6))*365/C10))<=1800000,((((INPUTS!$C$6*C7)*C6)*((INPUTS!$C$28/((BOM!$E$22*(1-C8)+C9)*C6))*365/C10))*0.107-22500)/(((INPUTS!$C$6*C7)*C6)*((INPUTS!$C$28/((BOM!$E$22*(1-C8)+C9)*C6))*365/C10)),IF((((INPUTS!$C$6*C7)*C6)*((INPUTS!$C$28/((BOM!$E$22*(1-C8)+C9)*C6))*365/C10))<=3600000,((((INPUTS!$C$6*C7)*C6)*((INPUTS!$C$28/((BOM!$E$22*(1-C8)+C9)*C6))*365/C10))*0.143-87300)/(((INPUTS!$C$6*C7)*C6)*((INPUTS!$C$28/((BOM!$E$22*(1-C8)+C9)*C6))*365/C10)),((((INPUTS!$C$6*C7)*C6)*((INPUTS!$C$28/((BOM!$E$22*(1-C8)+C9)*C6))*365/C10))*0.19-378000)/(((INPUTS!$C$6*C7)*C6)*((INPUTS!$C$28/((BOM!$E$22*(1-C8)+C9)*C6))*365/C10)))))))))-MIN(((INPUTS!$C$6*C7)*C6)*INPUTS!$C$25,INPUTS!$C$26))*((INPUTS!$C$28/((BOM!$E$22*(1-C8)+C9)*C6))*365/C10)-INPUTS!$C$33)/12) | D26: =(((((INPUTS!$C$6*D7)*D6)-((BOM!$E$22*(1-D8)+D9)*D6)-((INPUTS!$C$6*D7)*D6)*(IF((((INPUTS!$C$6*D7)*D6)*((INPUTS!$C$28/((BOM!$E$22*(1-D8)+D9)*D6))*365/D10))<=0,0.04,IF((((INPUTS!$C$6*D7)*D6)*((INPUTS!$C$28/((BOM!$E$22*(1-D8)+D9)*D6))*365/D10))<=180000,0.04,IF((((INPUTS!$C$6*D7)*D6)*((INPUTS!$C$28/((BOM!$E$22*(1-D8)+D9)*D6))*365/D10))<=360000,((((INPUTS!$C$6*D7)*D6)*((INPUTS!$C$28/((BOM!$E$22*(1-D8)+D9)*D6))*365/D10))*0.073-5940)/(((INPUTS!$C$6*D7)*D6)*((INPUTS!$C$28/((BOM!$E$22*(1-D8)+D9)*D6))*365/D10)),IF((((INPUTS!$C$6*D7)*D6)*((INPUTS!$C$28/((BOM!$E$22*(1-D8)+D9)*D6))*365/D10))<=720000,((((INPUTS!$C$6*D7)*D6)*((INPUTS!$C$28/((BOM!$E$22*(1-D8)+D9)*D6))*365/D10))*0.095-13860)/(((INPUTS!$C$6*D7)*D6)*((INPUTS!$C$28/((BOM!$E$22*(1-D8)+D9)*D6))*365/D10)),IF((((INPUTS!$C$6*D7)*D6)*((INPUTS!$C$28/((BOM!$E$22*(1-D8)+D9)*D6))*365/D10))<=1800000,((((INPUTS!$C$6*D7)*D6)*((INPUTS!$C$28/((BOM!$E$22*(1-D8)+D9)*D6))*365/D10))*0.107-22500)/(((INPUTS!$C$6*D7)*D6)*((INPUTS!$C$28/((BOM!$E$22*(1-D8)+D9)*D6))*365/D10)),IF((((INPUTS!$C$6*D7)*D6)*((INPUTS!$C$28/((BOM!$E$22*(1-D8)+D9)*D6))*365/D10))<=3600000,((((INPUTS!$C$6*D7)*D6)*((INPUTS!$C$28/((BOM!$E$22*(1-D8)+D9)*D6))*365/D10))*0.143-87300)/(((INPUTS!$C$6*D7)*D6)*((INPUTS!$C$28/((BOM!$E$22*(1-D8)+D9)*D6))*365/D10)),((((INPUTS!$C$6*D7)*D6)*((INPUTS!$C$28/((BOM!$E$22*(1-D8)+D9)*D6))*365/D10))*0.19-378000)/(((INPUTS!$C$6*D7)*D6)*((INPUTS!$C$28/((BOM!$E$22*(1-D8)+D9)*D6))*365/D10)))))))))-MIN(((INPUTS!$C$6*D7)*D6)*INPUTS!$C$25,INPUTS!$C$26))*((INPUTS!$C$28/((BOM!$E$22*(1-D8)+D9)*D6))*365/D10)-INPUTS!$C$33)/12) | E26: =(((((INPUTS!$C$6*E7)*E6)-((BOM!$E$22*(1-E8)+E9)*E6)-((INPUTS!$C$6*E7)*E6)*(IF((((INPUTS!$C$6*E7)*E6)*((INPUTS!$C$28/((BOM!$E$22*(1-E8)+E9)*E6))*365/E10))<=0,0.04,IF((((INPUTS!$C$6*E7)*E6)*((INPUTS!$C$28/((BOM!$E$22*(1-E8)+E9)*E6))*365/E10))<=180000,0.04,IF((((INPUTS!$C$6*E7)*E6)*((INPUTS!$C$28/((BOM!$E$22*(1-E8)+E9)*E6))*365/E10))<=360000,((((INPUTS!$C$6*E7)*E6)*((INPUTS!$C$28/((BOM!$E$22*(1-E8)+E9)*E6))*365/E10))*0.073-5940)/(((INPUTS!$C$6*E7)*E6)*((INPUTS!$C$28/((BOM!$E$22*(1-E8)+E9)*E6))*365/E10)),IF((((INPUTS!$C$6*E7)*E6)*((INPUTS!$C$28/((BOM!$E$22*(1-E8)+E9)*E6))*365/E10))<=720000,((((INPUTS!$C$6*E7)*E6)*((INPUTS!$C$28/((BOM!$E$22*(1-E8)+E9)*E6))*365/E10))*0.095-13860)/(((INPUTS!$C$6*E7)*E6)*((INPUTS!$C$28/((BOM!$E$22*(1-E8)+E9)*E6))*365/E10)),IF((((INPUTS!$C$6*E7)*E6)*((INPUTS!$C$28/((BOM!$E$22*(1-E8)+E9)*E6))*365/E10))<=1800000,((((INPUTS!$C$6*E7)*E6)*((INPUTS!$C$28/((BOM!$E$22*(1-E8)+E9)*E6))*365/E10))*0.107-22500)/(((INPUTS!$C$6*E7)*E6)*((INPUTS!$C$28/((BOM!$E$22*(1-E8)+E9)*E6))*365/E10)),IF((((INPUTS!$C$6*E7)*E6)*((INPUTS!$C$28/((BOM!$E$22*(1-E8)+E9)*E6))*365/E10))<=3600000,((((INPUTS!$C$6*E7)*E6)*((INPUTS!$C$28/((BOM!$E$22*(1-E8)+E9)*E6))*365/E10))*0.143-87300)/(((INPUTS!$C$6*E7)*E6)*((INPUTS!$C$28/((BOM!$E$22*(1-E8)+E9)*E6))*365/E10)),((((INPUTS!$C$6*E7)*E6)*((INPUTS!$C$28/((BOM!$E$22*(1-E8)+E9)*E6))*365/E10))*0.19-378000)/(((INPUTS!$C$6*E7)*E6)*((INPUTS!$C$28/((BOM!$E$22*(1-E8)+E9)*E6))*365/E10)))))))))-MIN(((INPUTS!$C$6*E7)*E6)*INPUTS!$C$25,INPUTS!$C$26))*((INPUTS!$C$28/((BOM!$E$22*(1-E8)+E9)*E6))*365/E10)-INPUTS!$C$33)/12) | F26: =(((((INPUTS!$C$6*F7)*F6)-((BOM!$E$22*(1-F8)+F9)*F6)-((INPUTS!$C$6*F7)*F6)*(IF((((INPUTS!$C$6*F7)*F6)*((INPUTS!$C$28/((BOM!$E$22*(1-F8)+F9)*F6))*365/F10))<=0,0.04,IF((((INPUTS!$C$6*F7)*F6)*((INPUTS!$C$28/((BOM!$E$22*(1-F8)+F9)*F6))*365/F10))<=180000,0.04,IF((((INPUTS!$C$6*F7)*F6)*((INPUTS!$C$28/((BOM!$E$22*(1-F8)+F9)*F6))*365/F10))<=360000,((((INPUTS!$C$6*F7)*F6)*((INPUTS!$C$28/((BOM!$E$22*(1-F8)+F9)*F6))*365/F10))*0.073-5940)/(((INPUTS!$C$6*F7)*F6)*((INPUTS!$C$28/((BOM!$E$22*(1-F8)+F9)*F6))*365/F10)),IF((((INPUTS!$C$6*F7)*F6)*((INPUTS!$C$28/((BOM!$E$22*(1-F8)+F9)*F6))*365/F10))<=720000,((((INPUTS!$C$6*F7)*F6)*((INPUTS!$C$28/((BOM!$E$22*(1-F8)+F9)*F6))*365/F10))*0.095-13860)/(((INPUTS!$C$6*F7)*F6)*((INPUTS!$C$28/((BOM!$E$22*(1-F8)+F9)*F6))*365/F10)),IF((((INPUTS!$C$6*F7)*F6)*((INPUTS!$C$28/((BOM!$E$22*(1-F8)+F9)*F6))*365/F10))<=1800000,((((INPUTS!$C$6*F7)*F6)*((INPUTS!$C$28/((BOM!$E$22*(1-F8)+F9)*F6))*365/F10))*0.107-22500)/(((INPUTS!$C$6*F7)*F6)*((INPUTS!$C$28/((BOM!$E$22*(1-F8)+F9)*F6))*365/F10)),IF((((INPUTS!$C$6*F7)*F6)*((INPUTS!$C$28/((BOM!$E$22*(1-F8)+F9)*F6))*365/F10))<=3600000,((((INPUTS!$C$6*F7)*F6)*((INPUTS!$C$28/((BOM!$E$22*(1-F8)+F9)*F6))*365/F10))*0.143-87300)/(((INPUTS!$C$6*F7)*F6)*((INPUTS!$C$28/((BOM!$E$22*(1-F8)+F9)*F6))*365/F10)),((((INPUTS!$C$6*F7)*F6)*((INPUTS!$C$28/((BOM!$E$22*(1-F8)+F9)*F6))*365/F10))*0.19-378000)/(((INPUTS!$C$6*F7)*F6)*((INPUTS!$C$28/((BOM!$E$22*(1-F8)+F9)*F6))*365/F10)))))))))-MIN(((INPUTS!$C$6*F7)*F6)*INPUTS!$C$25,INPUTS!$C$26))*((INPUTS!$C$28/((BOM!$E$22*(1-F8)+F9)*F6))*365/F10)-INPUTS!$C$33)/12) | G26: =(((((INPUTS!$C$6*G7)*G6)-((BOM!$E$22*(1-G8)+G9)*G6)-((INPUTS!$C$6*G7)*G6)*(IF((((INPUTS!$C$6*G7)*G6)*((INPUTS!$C$28/((BOM!$E$22*(1-G8)+G9)*G6))*365/G10))<=0,0.04,IF((((INPUTS!$C$6*G7)*G6)*((INPUTS!$C$28/((BOM!$E$22*(1-G8)+G9)*G6))*365/G10))<=180000,0.04,IF((((INPUTS!$C$6*G7)*G6)*((INPUTS!$C$28/((BOM!$E$22*(1-G8)+G9)*G6))*365/G10))<=360000,((((INPUTS!$C$6*G7)*G6)*((INPUTS!$C$28/((BOM!$E$22*(1-G8)+G9)*G6))*365/G10))*0.073-5940)/(((INPUTS!$C$6*G7)*G6)*((INPUTS!$C$28/((BOM!$E$22*(1-G8)+G9)*G6))*365/G10)),IF((((INPUTS!$C$6*G7)*G6)*((INPUTS!$C$28/((BOM!$E$22*(1-G8)+G9)*G6))*365/G10))<=720000,((((INPUTS!$C$6*G7)*G6)*((INPUTS!$C$28/((BOM!$E$22*(1-G8)+G9)*G6))*365/G10))*0.095-13860)/(((INPUTS!$C$6*G7)*G6)*((INPUTS!$C$28/((BOM!$E$22*(1-G8)+G9)*G6))*365/G10)),IF((((INPUTS!$C$6*G7)*G6)*((INPUTS!$C$28/((BOM!$E$22*(1-G8)+G9)*G6))*365/G10))<=1800000,((((INPUTS!$C$6*G7)*G6)*((INPUTS!$C$28/((BOM!$E$22*(1-G8)+G9)*G6))*365/G10))*0.107-22500)/(((INPUTS!$C$6*G7)*G6)*((INPUTS!$C$28/((BOM!$E$22*(1-G8)+G9)*G6))*365/G10)),IF((((INPUTS!$C$6*G7)*G6)*((INPUTS!$C$28/((BOM!$E$22*(1-G8)+G9)*G6))*365/G10))<=3600000,((((INPUTS!$C$6*G7)*G6)*((INPUTS!$C$28/((BOM!$E$22*(1-G8)+G9)*G6))*365/G10))*0.143-87300)/(((INPUTS!$C$6*G7)*G6)*((INPUTS!$C$28/((BOM!$E$22*(1-G8)+G9)*G6))*365/G10)),((((INPUTS!$C$6*G7)*G6)*((INPUTS!$C$28/((BOM!$E$22*(1-G8)+G9)*G6))*365/G10))*0.19-378000)/(((INPUTS!$C$6*G7)*G6)*((INPUTS!$C$28/((BOM!$E$22*(1-G8)+G9)*G6))*365/G10)))))))))-MIN(((INPUTS!$C$6*G7)*G6)*INPUTS!$C$25,INPUTS!$C$26))*((INPUTS!$C$28/((BOM!$E$22*(1-G8)+G9)*G6))*365/G10)-INPUTS!$C$33)/12) | H26: =(((((INPUTS!$C$6*H7)*H6)-((BOM!$E$22*(1-H8)+H9)*H6)-((INPUTS!$C$6*H7)*H6)*(IF((((INPUTS!$C$6*H7)*H6)*((INPUTS!$C$28/((BOM!$E$22*(1-H8)+H9)*H6))*365/H10))<=0,0.04,IF((((INPUTS!$C$6*H7)*H6)*((INPUTS!$C$28/((BOM!$E$22*(1-H8)+H9)*H6))*365/H10))<=180000,0.04,IF((((INPUTS!$C$6*H7)*H6)*((INPUTS!$C$28/((BOM!$E$22*(1-H8)+H9)*H6))*365/H10))<=360000,((((INPUTS!$C$6*H7)*H6)*((INPUTS!$C$28/((BOM!$E$22*(1-H8)+H9)*H6))*365/H10))*0.073-5940)/(((INPUTS!$C$6*H7)*H6)*((INPUTS!$C$28/((BOM!$E$22*(1-H8)+H9)*H6))*365/H10)),IF((((INPUTS!$C$6*H7)*H6)*((INPUTS!$C$28/((BOM!$E$22*(1-H8)+H9)*H6))*365/H10))<=720000,((((INPUTS!$C$6*H7)*H6)*((INPUTS!$C$28/((BOM!$E$22*(1-H8)+H9)*H6))*365/H10))*0.095-13860)/(((INPUTS!$C$6*H7)*H6)*((INPUTS!$C$28/((BOM!$E$22*(1-H8)+H9)*H6))*365/H10)),IF((((INPUTS!$C$6*H7)*H6)*((INPUTS!$C$28/((BOM!$E$22*(1-H8)+H9)*H6))*365/H10))<=1800000,((((INPUTS!$C$6*H7)*H6)*((INPUTS!$C$28/((BOM!$E$22*(1-H8)+H9)*H6))*365/H10))*0.107-22500)/(((INPUTS!$C$6*H7)*H6)*((INPUTS!$C$28/((BOM!$E$22*(1-H8)+H9)*H6))*365/H10)),IF((((INPUTS!$C$6*H7)*H6)*((INPUTS!$C$28/((BOM!$E$22*(1-H8)+H9)*H6))*365/H10))<=3600000,((((INPUTS!$C$6*H7)*H6)*((INPUTS!$C$28/((BOM!$E$22*(1-H8)+H9)*H6))*365/H10))*0.143-87300)/(((INPUTS!$C$6*H7)*H6)*((INPUTS!$C$28/((BOM!$E$22*(1-H8)+H9)*H6))*365/H10)),((((INPUTS!$C$6*H7)*H6)*((INPUTS!$C$28/((BOM!$E$22*(1-H8)+H9)*H6))*365/H10))*0.19-378000)/(((INPUTS!$C$6*H7)*H6)*((INPUTS!$C$28/((BOM!$E$22*(1-H8)+H9)*H6))*365/H10)))))))))-MIN(((INPUTS!$C$6*H7)*H6)*INPUTS!$C$25,INPUTS!$C$26))*((INPUTS!$C$28/((BOM!$E$22*(1-H8)+H9)*H6))*365/H10)-INPUTS!$C$33)/12)
B27: …per month in US$ | C27: =IF(INPUTS!$C$35=0,0,((((INPUTS!$C$6*C7)*C6)-((BOM!$E$22*(1-C8)+C9)*C6)-((INPUTS!$C$6*C7)*C6)*(IF((((INPUTS!$C$6*C7)*C6)*((INPUTS!$C$28/((BOM!$E$22*(1-C8)+C9)*C6))*365/C10))<=0,0.04,IF((((INPUTS!$C$6*C7)*C6)*((INPUTS!$C$28/((BOM!$E$22*(1-C8)+C9)*C6))*365/C10))<=180000,0.04,IF((((INPUTS!$C$6*C7)*C6)*((INPUTS!$C$28/((BOM!$E$22*(1-C8)+C9)*C6))*365/C10))<=360000,((((INPUTS!$C$6*C7)*C6)*((INPUTS!$C$28/((BOM!$E$22*(1-C8)+C9)*C6))*365/C10))*0.073-5940)/(((INPUTS!$C$6*C7)*C6)*((INPUTS!$C$28/((BOM!$E$22*(1-C8)+C9)*C6))*365/C10)),IF((((INPUTS!$C$6*C7)*C6)*((INPUTS!$C$28/((BOM!$E$22*(1-C8)+C9)*C6))*365/C10))<=720000,((((INPUTS!$C$6*C7)*C6)*((INPUTS!$C$28/((BOM!$E$22*(1-C8)+C9)*C6))*365/C10))*0.095-13860)/(((INPUTS!$C$6*C7)*C6)*((INPUTS!$C$28/((BOM!$E$22*(1-C8)+C9)*C6))*365/C10)),IF((((INPUTS!$C$6*C7)*C6)*((INPUTS!$C$28/((BOM!$E$22*(1-C8)+C9)*C6))*365/C10))<=1800000,((((INPUTS!$C$6*C7)*C6)*((INPUTS!$C$28/((BOM!$E$22*(1-C8)+C9)*C6))*365/C10))*0.107-22500)/(((INPUTS!$C$6*C7)*C6)*((INPUTS!$C$28/((BOM!$E$22*(1-C8)+C9)*C6))*365/C10)),IF((((INPUTS!$C$6*C7)*C6)*((INPUTS!$C$28/((BOM!$E$22*(1-C8)+C9)*C6))*365/C10))<=3600000,((((INPUTS!$C$6*C7)*C6)*((INPUTS!$C$28/((BOM!$E$22*(1-C8)+C9)*C6))*365/C10))*0.143-87300)/(((INPUTS!$C$6*C7)*C6)*((INPUTS!$C$28/((BOM!$E$22*(1-C8)+C9)*C6))*365/C10)),((((INPUTS!$C$6*C7)*C6)*((INPUTS!$C$28/((BOM!$E$22*(1-C8)+C9)*C6))*365/C10))*0.19-378000)/(((INPUTS!$C$6*C7)*C6)*((INPUTS!$C$28/((BOM!$E$22*(1-C8)+C9)*C6))*365/C10)))))))))-MIN(((INPUTS!$C$6*C7)*C6)*INPUTS!$C$25,INPUTS!$C$26))*((INPUTS!$C$28/((BOM!$E$22*(1-C8)+C9)*C6))*365/C10)-INPUTS!$C$33)/12/INPUTS!$C$35) | D27: =IF(INPUTS!$C$35=0,0,((((INPUTS!$C$6*D7)*D6)-((BOM!$E$22*(1-D8)+D9)*D6)-((INPUTS!$C$6*D7)*D6)*(IF((((INPUTS!$C$6*D7)*D6)*((INPUTS!$C$28/((BOM!$E$22*(1-D8)+D9)*D6))*365/D10))<=0,0.04,IF((((INPUTS!$C$6*D7)*D6)*((INPUTS!$C$28/((BOM!$E$22*(1-D8)+D9)*D6))*365/D10))<=180000,0.04,IF((((INPUTS!$C$6*D7)*D6)*((INPUTS!$C$28/((BOM!$E$22*(1-D8)+D9)*D6))*365/D10))<=360000,((((INPUTS!$C$6*D7)*D6)*((INPUTS!$C$28/((BOM!$E$22*(1-D8)+D9)*D6))*365/D10))*0.073-5940)/(((INPUTS!$C$6*D7)*D6)*((INPUTS!$C$28/((BOM!$E$22*(1-D8)+D9)*D6))*365/D10)),IF((((INPUTS!$C$6*D7)*D6)*((INPUTS!$C$28/((BOM!$E$22*(1-D8)+D9)*D6))*365/D10))<=720000,((((INPUTS!$C$6*D7)*D6)*((INPUTS!$C$28/((BOM!$E$22*(1-D8)+D9)*D6))*365/D10))*0.095-13860)/(((INPUTS!$C$6*D7)*D6)*((INPUTS!$C$28/((BOM!$E$22*(1-D8)+D9)*D6))*365/D10)),IF((((INPUTS!$C$6*D7)*D6)*((INPUTS!$C$28/((BOM!$E$22*(1-D8)+D9)*D6))*365/D10))<=1800000,((((INPUTS!$C$6*D7)*D6)*((INPUTS!$C$28/((BOM!$E$22*(1-D8)+D9)*D6))*365/D10))*0.107-22500)/(((INPUTS!$C$6*D7)*D6)*((INPUTS!$C$28/((BOM!$E$22*(1-D8)+D9)*D6))*365/D10)),IF((((INPUTS!$C$6*D7)*D6)*((INPUTS!$C$28/((BOM!$E$22*(1-D8)+D9)*D6))*365/D10))<=3600000,((((INPUTS!$C$6*D7)*D6)*((INPUTS!$C$28/((BOM!$E$22*(1-D8)+D9)*D6))*365/D10))*0.143-87300)/(((INPUTS!$C$6*D7)*D6)*((INPUTS!$C$28/((BOM!$E$22*(1-D8)+D9)*D6))*365/D10)),((((INPUTS!$C$6*D7)*D6)*((INPUTS!$C$28/((BOM!$E$22*(1-D8)+D9)*D6))*365/D10))*0.19-378000)/(((INPUTS!$C$6*D7)*D6)*((INPUTS!$C$28/((BOM!$E$22*(1-D8)+D9)*D6))*365/D10)))))))))-MIN(((INPUTS!$C$6*D7)*D6)*INPUTS!$C$25,INPUTS!$C$26))*((INPUTS!$C$28/((BOM!$E$22*(1-D8)+D9)*D6))*365/D10)-INPUTS!$C$33)/12/INPUTS!$C$35) | E27: =IF(INPUTS!$C$35=0,0,((((INPUTS!$C$6*E7)*E6)-((BOM!$E$22*(1-E8)+E9)*E6)-((INPUTS!$C$6*E7)*E6)*(IF((((INPUTS!$C$6*E7)*E6)*((INPUTS!$C$28/((BOM!$E$22*(1-E8)+E9)*E6))*365/E10))<=0,0.04,IF((((INPUTS!$C$6*E7)*E6)*((INPUTS!$C$28/((BOM!$E$22*(1-E8)+E9)*E6))*365/E10))<=180000,0.04,IF((((INPUTS!$C$6*E7)*E6)*((INPUTS!$C$28/((BOM!$E$22*(1-E8)+E9)*E6))*365/E10))<=360000,((((INPUTS!$C$6*E7)*E6)*((INPUTS!$C$28/((BOM!$E$22*(1-E8)+E9)*E6))*365/E10))*0.073-5940)/(((INPUTS!$C$6*E7)*E6)*((INPUTS!$C$28/((BOM!$E$22*(1-E8)+E9)*E6))*365/E10)),IF((((INPUTS!$C$6*E7)*E6)*((INPUTS!$C$28/((BOM!$E$22*(1-E8)+E9)*E6))*365/E10))<=720000,((((INPUTS!$C$6*E7)*E6)*((INPUTS!$C$28/((BOM!$E$22*(1-E8)+E9)*E6))*365/E10))*0.095-13860)/(((INPUTS!$C$6*E7)*E6)*((INPUTS!$C$28/((BOM!$E$22*(1-E8)+E9)*E6))*365/E10)),IF((((INPUTS!$C$6*E7)*E6)*((INPUTS!$C$28/((BOM!$E$22*(1-E8)+E9)*E6))*365/E10))<=1800000,((((INPUTS!$C$6*E7)*E6)*((INPUTS!$C$28/((BOM!$E$22*(1-E8)+E9)*E6))*365/E10))*0.107-22500)/(((INPUTS!$C$6*E7)*E6)*((INPUTS!$C$28/((BOM!$E$22*(1-E8)+E9)*E6))*365/E10)),IF((((INPUTS!$C$6*E7)*E6)*((INPUTS!$C$28/((BOM!$E$22*(1-E8)+E9)*E6))*365/E10))<=3600000,((((INPUTS!$C$6*E7)*E6)*((INPUTS!$C$28/((BOM!$E$22*(1-E8)+E9)*E6))*365/E10))*0.143-87300)/(((INPUTS!$C$6*E7)*E6)*((INPUTS!$C$28/((BOM!$E$22*(1-E8)+E9)*E6))*365/E10)),((((INPUTS!$C$6*E7)*E6)*((INPUTS!$C$28/((BOM!$E$22*(1-E8)+E9)*E6))*365/E10))*0.19-378000)/(((INPUTS!$C$6*E7)*E6)*((INPUTS!$C$28/((BOM!$E$22*(1-E8)+E9)*E6))*365/E10)))))))))-MIN(((INPUTS!$C$6*E7)*E6)*INPUTS!$C$25,INPUTS!$C$26))*((INPUTS!$C$28/((BOM!$E$22*(1-E8)+E9)*E6))*365/E10)-INPUTS!$C$33)/12/INPUTS!$C$35) | F27: =IF(INPUTS!$C$35=0,0,((((INPUTS!$C$6*F7)*F6)-((BOM!$E$22*(1-F8)+F9)*F6)-((INPUTS!$C$6*F7)*F6)*(IF((((INPUTS!$C$6*F7)*F6)*((INPUTS!$C$28/((BOM!$E$22*(1-F8)+F9)*F6))*365/F10))<=0,0.04,IF((((INPUTS!$C$6*F7)*F6)*((INPUTS!$C$28/((BOM!$E$22*(1-F8)+F9)*F6))*365/F10))<=180000,0.04,IF((((INPUTS!$C$6*F7)*F6)*((INPUTS!$C$28/((BOM!$E$22*(1-F8)+F9)*F6))*365/F10))<=360000,((((INPUTS!$C$6*F7)*F6)*((INPUTS!$C$28/((BOM!$E$22*(1-F8)+F9)*F6))*365/F10))*0.073-5940)/(((INPUTS!$C$6*F7)*F6)*((INPUTS!$C$28/((BOM!$E$22*(1-F8)+F9)*F6))*365/F10)),IF((((INPUTS!$C$6*F7)*F6)*((INPUTS!$C$28/((BOM!$E$22*(1-F8)+F9)*F6))*365/F10))<=720000,((((INPUTS!$C$6*F7)*F6)*((INPUTS!$C$28/((BOM!$E$22*(1-F8)+F9)*F6))*365/F10))*0.095-13860)/(((INPUTS!$C$6*F7)*F6)*((INPUTS!$C$28/((BOM!$E$22*(1-F8)+F9)*F6))*365/F10)),IF((((INPUTS!$C$6*F7)*F6)*((INPUTS!$C$28/((BOM!$E$22*(1-F8)+F9)*F6))*365/F10))<=1800000,((((INPUTS!$C$6*F7)*F6)*((INPUTS!$C$28/((BOM!$E$22*(1-F8)+F9)*F6))*365/F10))*0.107-22500)/(((INPUTS!$C$6*F7)*F6)*((INPUTS!$C$28/((BOM!$E$22*(1-F8)+F9)*F6))*365/F10)),IF((((INPUTS!$C$6*F7)*F6)*((INPUTS!$C$28/((BOM!$E$22*(1-F8)+F9)*F6))*365/F10))<=3600000,((((INPUTS!$C$6*F7)*F6)*((INPUTS!$C$28/((BOM!$E$22*(1-F8)+F9)*F6))*365/F10))*0.143-87300)/(((INPUTS!$C$6*F7)*F6)*((INPUTS!$C$28/((BOM!$E$22*(1-F8)+F9)*F6))*365/F10)),((((INPUTS!$C$6*F7)*F6)*((INPUTS!$C$28/((BOM!$E$22*(1-F8)+F9)*F6))*365/F10))*0.19-378000)/(((INPUTS!$C$6*F7)*F6)*((INPUTS!$C$28/((BOM!$E$22*(1-F8)+F9)*F6))*365/F10)))))))))-MIN(((INPUTS!$C$6*F7)*F6)*INPUTS!$C$25,INPUTS!$C$26))*((INPUTS!$C$28/((BOM!$E$22*(1-F8)+F9)*F6))*365/F10)-INPUTS!$C$33)/12/INPUTS!$C$35) | G27: =IF(INPUTS!$C$35=0,0,((((INPUTS!$C$6*G7)*G6)-((BOM!$E$22*(1-G8)+G9)*G6)-((INPUTS!$C$6*G7)*G6)*(IF((((INPUTS!$C$6*G7)*G6)*((INPUTS!$C$28/((BOM!$E$22*(1-G8)+G9)*G6))*365/G10))<=0,0.04,IF((((INPUTS!$C$6*G7)*G6)*((INPUTS!$C$28/((BOM!$E$22*(1-G8)+G9)*G6))*365/G10))<=180000,0.04,IF((((INPUTS!$C$6*G7)*G6)*((INPUTS!$C$28/((BOM!$E$22*(1-G8)+G9)*G6))*365/G10))<=360000,((((INPUTS!$C$6*G7)*G6)*((INPUTS!$C$28/((BOM!$E$22*(1-G8)+G9)*G6))*365/G10))*0.073-5940)/(((INPUTS!$C$6*G7)*G6)*((INPUTS!$C$28/((BOM!$E$22*(1-G8)+G9)*G6))*365/G10)),IF((((INPUTS!$C$6*G7)*G6)*((INPUTS!$C$28/((BOM!$E$22*(1-G8)+G9)*G6))*365/G10))<=720000,((((INPUTS!$C$6*G7)*G6)*((INPUTS!$C$28/((BOM!$E$22*(1-G8)+G9)*G6))*365/G10))*0.095-13860)/(((INPUTS!$C$6*G7)*G6)*((INPUTS!$C$28/((BOM!$E$22*(1-G8)+G9)*G6))*365/G10)),IF((((INPUTS!$C$6*G7)*G6)*((INPUTS!$C$28/((BOM!$E$22*(1-G8)+G9)*G6))*365/G10))<=1800000,((((INPUTS!$C$6*G7)*G6)*((INPUTS!$C$28/((BOM!$E$22*(1-G8)+G9)*G6))*365/G10))*0.107-22500)/(((INPUTS!$C$6*G7)*G6)*((INPUTS!$C$28/((BOM!$E$22*(1-G8)+G9)*G6))*365/G10)),IF((((INPUTS!$C$6*G7)*G6)*((INPUTS!$C$28/((BOM!$E$22*(1-G8)+G9)*G6))*365/G10))<=3600000,((((INPUTS!$C$6*G7)*G6)*((INPUTS!$C$28/((BOM!$E$22*(1-G8)+G9)*G6))*365/G10))*0.143-87300)/(((INPUTS!$C$6*G7)*G6)*((INPUTS!$C$28/((BOM!$E$22*(1-G8)+G9)*G6))*365/G10)),((((INPUTS!$C$6*G7)*G6)*((INPUTS!$C$28/((BOM!$E$22*(1-G8)+G9)*G6))*365/G10))*0.19-378000)/(((INPUTS!$C$6*G7)*G6)*((INPUTS!$C$28/((BOM!$E$22*(1-G8)+G9)*G6))*365/G10)))))))))-MIN(((INPUTS!$C$6*G7)*G6)*INPUTS!$C$25,INPUTS!$C$26))*((INPUTS!$C$28/((BOM!$E$22*(1-G8)+G9)*G6))*365/G10)-INPUTS!$C$33)/12/INPUTS!$C$35) | H27: =IF(INPUTS!$C$35=0,0,((((INPUTS!$C$6*H7)*H6)-((BOM!$E$22*(1-H8)+H9)*H6)-((INPUTS!$C$6*H7)*H6)*(IF((((INPUTS!$C$6*H7)*H6)*((INPUTS!$C$28/((BOM!$E$22*(1-H8)+H9)*H6))*365/H10))<=0,0.04,IF((((INPUTS!$C$6*H7)*H6)*((INPUTS!$C$28/((BOM!$E$22*(1-H8)+H9)*H6))*365/H10))<=180000,0.04,IF((((INPUTS!$C$6*H7)*H6)*((INPUTS!$C$28/((BOM!$E$22*(1-H8)+H9)*H6))*365/H10))<=360000,((((INPUTS!$C$6*H7)*H6)*((INPUTS!$C$28/((BOM!$E$22*(1-H8)+H9)*H6))*365/H10))*0.073-5940)/(((INPUTS!$C$6*H7)*H6)*((INPUTS!$C$28/((BOM!$E$22*(1-H8)+H9)*H6))*365/H10)),IF((((INPUTS!$C$6*H7)*H6)*((INPUTS!$C$28/((BOM!$E$22*(1-H8)+H9)*H6))*365/H10))<=720000,((((INPUTS!$C$6*H7)*H6)*((INPUTS!$C$28/((BOM!$E$22*(1-H8)+H9)*H6))*365/H10))*0.095-13860)/(((INPUTS!$C$6*H7)*H6)*((INPUTS!$C$28/((BOM!$E$22*(1-H8)+H9)*H6))*365/H10)),IF((((INPUTS!$C$6*H7)*H6)*((INPUTS!$C$28/((BOM!$E$22*(1-H8)+H9)*H6))*365/H10))<=1800000,((((INPUTS!$C$6*H7)*H6)*((INPUTS!$C$28/((BOM!$E$22*(1-H8)+H9)*H6))*365/H10))*0.107-22500)/(((INPUTS!$C$6*H7)*H6)*((INPUTS!$C$28/((BOM!$E$22*(1-H8)+H9)*H6))*365/H10)),IF((((INPUTS!$C$6*H7)*H6)*((INPUTS!$C$28/((BOM!$E$22*(1-H8)+H9)*H6))*365/H10))<=3600000,((((INPUTS!$C$6*H7)*H6)*((INPUTS!$C$28/((BOM!$E$22*(1-H8)+H9)*H6))*365/H10))*0.143-87300)/(((INPUTS!$C$6*H7)*H6)*((INPUTS!$C$28/((BOM!$E$22*(1-H8)+H9)*H6))*365/H10)),((((INPUTS!$C$6*H7)*H6)*((INPUTS!$C$28/((BOM!$E$22*(1-H8)+H9)*H6))*365/H10))*0.19-378000)/(((INPUTS!$C$6*H7)*H6)*((INPUTS!$C$28/((BOM!$E$22*(1-H8)+H9)*H6))*365/H10)))))))))-MIN(((INPUTS!$C$6*H7)*H6)*INPUTS!$C$25,INPUTS!$C$26))*((INPUTS!$C$28/((BOM!$E$22*(1-H8)+H9)*H6))*365/H10)-INPUTS!$C$33)/12/INPUTS!$C$35)
B28: Hours a month that takes | C28: =(INPUTS!$C$34*((INPUTS!$C$28/((BOM!$E$22*(1-C8)+C9)*C6))*365/C10)/12) | D28: =(INPUTS!$C$34*((INPUTS!$C$28/((BOM!$E$22*(1-D8)+D9)*D6))*365/D10)/12) | E28: =(INPUTS!$C$34*((INPUTS!$C$28/((BOM!$E$22*(1-E8)+E9)*E6))*365/E10)/12) | F28: =(INPUTS!$C$34*((INPUTS!$C$28/((BOM!$E$22*(1-F8)+F9)*F6))*365/F10)/12) | G28: =(INPUTS!$C$34*((INPUTS!$C$28/((BOM!$E$22*(1-G8)+G9)*G6))*365/G10)/12) | H28: =(INPUTS!$C$34*((INPUTS!$C$28/((BOM!$E$22*(1-H8)+H9)*H6))*365/H10)/12) | I28: Against the 87 h/month the plan allows. Column D is the only one that starts to fill them.
B30: WHAT THE COLUMN SAYS | C30: =IF(C25<0,"LOSES MONEY",IF(C25<12000,"TOO SMALL TO LIVE ON","WORKS")) | D30: =IF(D25<0,"LOSES MONEY",IF(D25<12000,"TOO SMALL TO LIVE ON","WORKS")) | E30: =IF(E25<0,"LOSES MONEY",IF(E25<12000,"TOO SMALL TO LIVE ON","WORKS")) | F30: =IF(F25<0,"LOSES MONEY",IF(F25<12000,"TOO SMALL TO LIVE ON","WORKS")) | G30: =IF(G25<0,"LOSES MONEY",IF(G25<12000,"TOO SMALL TO LIVE ON","WORKS")) | H30: =IF(H25<0,"LOSES MONEY",IF(H25<12000,"TOO SMALL TO LIVE ON","WORKS")) | I30: R$12.000/yr is a placeholder for "worth doing at all" — change it if your bar is different.
B33: THE THREE THINGS THIS TABLE SAYS
B34: 1. The 75% anchor was the whole problem, and it costs nothing to fix.
B35: Goods plus freight are 70,4% of the buyer's estimate before a centavo of tax. Bidding 75% leaves 4,6 points to cover Simples, the platform fee and profit — it cannot be done. Per-item lots clear at 97–100% of estimate, so 90% both wins and pays. Column A to column B is one number typed differently: −R$429/month becomes +R$1.694.
B37: 2. Supplier TERMS are worth about six times a supplier DISCOUNT.
B38: A 20% discount (column C) takes the month to ~R$4.000. Terms alone, at list price (column E), take it past R$11.000 — because the same R$15.600 turns over eight times as often. When you write to a wholesaler, 'do you have boleto a prazo' is a bigger question than 'what is your revenda price'.
B40: 3. Two kinds of tender can never work, at any price.
B41: Lote único (column F) clears at 36–63% of estimate against a 70,4% cost floor — arithmetically unwinnable, which is what rule 1 already refuses. And any tender delivering kit-by-kit to households: parcel freight to MA is R$188,40 a kit and turns every column above negative. That is what the local-de-entrega reader is for.
B43: Still true in every column: the 17th BOM line (the kit bag) is carried at R$0 because nobody has priced it, and no co-packer has quoted, so nothing here may exceed 240 kits. Both are on your list.

Sheet BOM
A1: Goods cost per kit — data/cost_table.csv, observed SP wholesale, 2026-09-19
A2: Sorted by line cost, largest first. Blue cells are editable: change a unit cost or a quantity and every other sheet follows.
A4: BOM line | B4: SKU | C4: Qty per kit | D4: Unit cost (R$) | E4: Line cost (R$) | F4: % of goods | G4: Basis | H4: Supplier UF | I4: Notes
A5: mochila | B5: MOCHILA | C5: 1 | D5: 52.27 | E5: =IF(D5="","",C5*D5) | F5: =IF(OR(E5="",$E$22=0),"",E5/$E$22) | G5: unit | H5: SP
A6: oleo_infantil | B6: 51050-UN | C6: 1 | D6: 23.89 | E6: =IF(D6="","",C6*D6) | F6: =IF(OR(E6="",$E$22=0),"",E6/$E$22) | G6: unit | H6: SP
A7: fralda_descartavel_rn | B7: 55832-PC | C7: 1 | D7: 23.78 | E7: =IF(D7="","",C7*D7) | F7: =IF(OR(E7="",$E$22=0),"",E7/$E$22) | G7: per_pack | H7: SP | I7: pack of 18 at pack price
A8: banheira_lisa | B8: BANHEIRA | C8: 1 | D8: 18.9 | E8: =IF(D8="","",C8*D8) | F8: =IF(OR(E8="",$E$22=0),"",E8/$E$22) | G8: unit | H8: SP
A9: pagao | B9: PAGAO | C9: 1 | D9: 15.34 | E9: =IF(D9="","",C9*D9) | F9: =IF(OR(E9="",$E$22=0),"",E9/$E$22) | G9: unit_set | H9: SP
A10: cobertor_infantil | B10: COBERTOR | C10: 1 | D10: 12.15 | E10: =IF(D10="","",C10*D10) | F10: =IF(OR(E10="",$E$22=0),"",E10/$E$22) | G10: unit | H10: SP
A11: shampoo_infantil | B11: 26669-UN | C11: 1 | D11: 10.45 | E11: =IF(D11="","",C11*D11) | F11: =IF(OR(E11="",$E$22=0),"",E11/$E$22) | G11: unit | H11: SP
A12: sabonete_liquido | B12: 000000000000941594-UN | C12: 1 | D12: 8.99 | E12: =IF(D12="","",C12*D12) | F12: =IF(OR(E12="",$E$22=0),"",E12/$E$22) | G12: unit | H12: SP
A13: body_manga_longa | B13: BODY | C13: 1 | D13: 7.56 | E13: =IF(D13="","",C13*D13) | F13: =IF(OR(E13="",$E$22=0),"",E13/$E$22) | G13: per_piece | H13: SP
A14: toalhas_umedecidas | B14: 50102-UN | C14: 1 | D14: 6.02 | E14: =IF(D14="","",C14*D14) | F14: =IF(OR(E14="",$E$22=0),"",E14/$E$22) | G14: per_pack | H14: SP
A15: kit_higiene_bebe | B15: KIT_HIGIENE | C15: 1 | D15: 5.2 | E15: =IF(D15="","",C15*D15) | F15: =IF(OR(E15="",$E$22=0),"",E15/$E$22) | G15: unit_kit | H15: SP
A16: cueiro | B16: CUEIRO | C16: 1 | D16: 3.94 | E16: =IF(D16="","",C16*D16) | F16: =IF(OR(E16="",$E$22=0),"",E16/$E$22) | G16: per_piece | H16: SP
A17: toalha_banho_infantil | B17: TOALHA_BANHO | C17: 1 | D17: 3.42 | E17: =IF(D17="","",C17*D17) | F17: =IF(OR(E17="",$E$22=0),"",E17/$E$22) | G17: per_piece | H17: SP
A18: saboneteira | B18: SABONETEIRA | C18: 1 | D18: 3.01 | E18: =IF(D18="","",C18*D18) | F18: =IF(OR(E18="",$E$22=0),"",E18/$E$22) | G18: unit | H18: SP
A19: par_de_meias | B19: MEIAS | C19: 1 | D19: 2.01 | E19: =IF(D19="","",C19*D19) | F19: =IF(OR(E19="",$E$22=0),"",E19/$E$22) | G19: per_pair | H19: SP
A20: pano_de_boca | B20: PANO_BOCA | C20: 1 | D20: 1.85 | E20: =IF(D20="","",C20*D20) | F20: =IF(OR(E20="",$E$22=0),"",E20/$E$22) | G20: per_piece | H20: SP
A21: kit_enxoval | B21: KIT_ENXOVAL | C21: 1 | E21: =IF(D21="","",C21*D21) | F21: =IF(OR(E21="",$E$22=0),"",E21/$E$22) | G21: unit | I21: UNPRICED — the kit bag. Needs the real edital spec (PNCP Family B). Price it here, or carry an allowance in INPUTS!C17.
D22: TOTAL priced lines | E22: =SUM(E5:E21)
D23: Unpriced lines | E23: =SUMPRODUCT(--(D5:D21=""))
A25: Where the goods cost actually sits
A26: Top 4 lines as % of goods cost | C26: =IF($E$22=0,"",SUM(E5:E8)/$E$22) | D26: A discount negotiation that does not move the top four does not move the kit.
A27: Mochila as % of goods cost | C27: =IF($E$22=0,"",E5/$E$22) | D27: The written plan budgeted R$25,00 for the backpack. List is R$52,27 — that one gap is most of the missing margin.

Sheet FREIGHT
A1: Freight per kit — MEASURED 2026-09-19 (data/freight.md, data/cost_freight.csv)
A2: PARCEL = Correios PAC balcao, one 60×40×40 cm box per kit, SP 03005-000 to the CAPITAL CEP. LTL = consolidated road freight to ONE consignee; only SP→CE has a published table (STC).
A3: Blank = never measured. DEAL reports that rather than substituting zero. Interior CEPs differ from capitals. Transit days are PARCEL only — LTL transit is not published.
A5: YOUR SELECTION
A6: Buyer UF | B6: =INPUTS!$C$8
A7: Delivery mode | B7: =INPUTS!$C$9
A8: Freight per kit from the table | B8: =IFERROR(INDEX($F$13:$F$31,MATCH($B$6,$A$13:$A$31,0)),"") | C8: Blank here = no measured rate for this UF and mode. Quote it, or switch mode.
A9: Transit days (parcel) | B9: =IFERROR(INDEX($G$13:$G$31,MATCH($B$6,$A$13:$A$31,0)),"")
A10: Freight as % of your bid price | B10: =IF(OR($B$8="",DEAL!$C$15=0),"",IF(INPUTS!$C$14<>"",INPUTS!$C$14,$B$8)/DEAL!$C$15) | C10: Above ~20% of the bid price, freight alone eats the entire margin.
A12: UF | B12: Parcel per kit (R$) | C12: LTL per kit (R$) | D12: Transit days (PAC, business) | E12: Source | F12: Used for your mode | G12: Transit used
A13: MG | B13: 116.6 | D13: 5 | E13: Correios public calculator, measured | F13: =IF(INPUTS!$C$9="LTL",IF(C13="","",C13),IF(B13="","",B13)) | G13: =IF(D13="","",D13)
A14: MA | B14: 188.4 | D14: 8 | E14: Correios public calculator, measured | F14: =IF(INPUTS!$C$9="LTL",IF(C14="","",C14),IF(B14="","",B14)) | G14: =IF(D14="","",D14)
A15: BA | B15: 132.9 | D15: 6 | E15: Correios public calculator, measured | F15: =IF(INPUTS!$C$9="LTL",IF(C15="","",C15),IF(B15="","",B15)) | G15: =IF(D15="","",D15)
A16: CE | B16: 152.6 | C16: 53.99 | D16: 7 | E16: Correios measured; LTL: STC Transportes published table SP→Fortaleza, 100 kits (R$52,57 at 5.000) | F16: =IF(INPUTS!$C$9="LTL",IF(C16="","",C16),IF(B16="","",B16)) | G16: =IF(D16="","",D16)
A17: PE | B17: 152.6 | D17: 6 | E17: Correios public calculator, measured | F17: =IF(INPUTS!$C$9="LTL",IF(C17="","",C17),IF(B17="","",B17)) | G17: =IF(D17="","",D17)
A18: SE | B18: 188.4 | D18: 8 | E18: Correios public calculator, measured | F18: =IF(INPUTS!$C$9="LTL",IF(C18="","",C18),IF(B18="","",B18)) | G18: =IF(D18="","",D18)
A19: PA | B19: 152.6 | D19: 8 | E19: Correios public calculator, measured | F19: =IF(INPUTS!$C$9="LTL",IF(C19="","",C19),IF(B19="","",B19)) | G19: =IF(D19="","",D19)
A20: RN | B20: 188.4 | D20: 7 | E20: Correios public calculator, measured | F20: =IF(INPUTS!$C$9="LTL",IF(C20="","",C20),IF(B20="","",B20)) | G20: =IF(D20="","",D20)
A21: PB | E21: NOT MEASURED | F21: =IF(INPUTS!$C$9="LTL",IF(C21="","",C21),IF(B21="","",B21)) | G21: =IF(D21="","",D21)
A22: AL | E22: NOT MEASURED | F22: =IF(INPUTS!$C$9="LTL",IF(C22="","",C22),IF(B22="","",B22)) | G22: =IF(D22="","",D22)
A23: PI | E23: NOT MEASURED | F23: =IF(INPUTS!$C$9="LTL",IF(C23="","",C23),IF(B23="","",B23)) | G23: =IF(D23="","",D23)
A24: GO | E24: NOT MEASURED | F24: =IF(INPUTS!$C$9="LTL",IF(C24="","",C24),IF(B24="","",B24)) | G24: =IF(D24="","",D24)
A25: TO | E25: NOT MEASURED | F25: =IF(INPUTS!$C$9="LTL",IF(C25="","",C25),IF(B25="","",B25)) | G25: =IF(D25="","",D25)
A26: RJ | E26: NOT MEASURED | F26: =IF(INPUTS!$C$9="LTL",IF(C26="","",C26),IF(B26="","",B26)) | G26: =IF(D26="","",D26)
A27: PR | E27: NOT MEASURED | F27: =IF(INPUTS!$C$9="LTL",IF(C27="","",C27),IF(B27="","",B27)) | G27: =IF(D27="","",D27)
A28: SC | E28: NOT MEASURED | F28: =IF(INPUTS!$C$9="LTL",IF(C28="","",C28),IF(B28="","",B28)) | G28: =IF(D28="","",D28)
A29: RS | E29: NOT MEASURED | F29: =IF(INPUTS!$C$9="LTL",IF(C29="","",C29),IF(B29="","",B29)) | G29: =IF(D29="","",D29)
A30: AM | E30: NOT MEASURED | F30: =IF(INPUTS!$C$9="LTL",IF(C30="","",C30),IF(B30="","",B30)) | G30: =IF(D30="","",D30)
A31: SP | E31: NOT MEASURED | F31: =IF(INPUTS!$C$9="LTL",IF(C31="","",C31),IF(B31="","",B31)) | G31: =IF(D31="","",D31)

Sheet SOURCES
B2: SOURCES, CAVEATS, AND WHAT CHANGED
B4: WHERE THE NUMBERS COME FROM
B5: Goods | C5: data/cost_table.csv — observed SP wholesale catalogue prices on 2026-09-19, supplier CNPJ and UF on every row. 16 of 17 lines priced; the kit bag is not.
B6: Freight | C6: Correios PAC balcao public calculator and the STC Transportes published table, measured 2026-09-19 to CAPITAL CEPs only. Interior CEPs will differ. Only SP→CE has an LTL rate.
B7: Assembly | C7: No co-packer publishes a per-kit price (data/copacking.md, 24 SP providers surveyed). Self-pack ceiling from config/capital.yaml: 8 h per won order at 2 min/kit.
B8: Taxes | C8: Simples Anexo I effective rates (LC 123). IRRF 1,2% per IN RFB 1.234 unless the Anexo IV declaration is filed with every contract — there is no refund path if it is not.
B9: Platform fees | C9: Regulamento BLL 2026 art. 17 (1,5%, cap R$600 above R$40k lots); BNC 2026 art. 24 (R$118,80/process); PCP adhesion page (R$129/process); Compras.gov.br free.
B10: Days to cash | C10: docs/ORDER_TO_CASH.md — seven real editais. 34 best, 40–55 typical, 69 worst.
B11: Capital, win count, fixed costs, FX | C11: From the written plan, not measured: R$15.600 capital, 21 lots a year, ~R$6.000 of annual fixed costs, 5,20 BRL/USD. All four sit on INPUTS and all four move the take-home figure. Treat them as arguments, not data.
B13: WHAT THIS MODEL STILL IGNORES
B14: Not modelled | C14: Late-delivery fines (multa), sample costs, the SRP obligation to serve every call-off at the registered price, and the cost of LOSING bids — the per-process fees on BNC and PCP are charged whether you win or not.
B15: Cash timing | C15: The annualised return assumes cash leaves on day 0. In reality the supplier is paid nearer day 11, so the real return on capital is better than shown. Deliberately conservative.
B16: Freight basis | C16: A baby bath ships on volume, not weight. LTL carriers refuse to quote without a contract, so exactly one published table exists. Treat any non-CE LTL number as unknown.
B17: Supplier terms | C17: The model assumes you pay cash. 28-day supplier terms would roughly triple the lots your capital can carry — the single highest-value thing on this page and it costs nothing but asking.
B19: WHAT CHANGED IN THIS REBUILD
B20: Decision moved to the front | C20: The verdict used to sit at row 58, below six numbered sections. It is now the first thing on the first sheet.
B21: Income made visible | C21: The old model stopped at profit per lot. It never said what you earn. VERDICT now carries pay per hour, take-home per year and per month, and the hours it costs you — and DEAL shows the arithmetic.
B22: Capital ceiling computed | C22: New: cash per lot → lots you can carry at once → lots a year your capital allows. Check 5 compares that against the year you planned. Income is capped by cash, not by the number of tenders.
B23: Typed cells all in one place | C23: Inputs and formulas used to be interleaved down one column, so 'type in the blue cells only' meant scanning thirty rows. Every typed cell now lives on INPUTS and nowhere else.
B24: Verdict no longer hides failures | C24: The old nested IF returned the FIRST problem only — it reported 'THIN' while silently swallowing an unpriced BOM line and an unset capital figure. Nine checks now report independently, with the count in the headline.
B25: Sensitivity grid follows your UF | C25: The old grid's four freight columns were hardcoded to CE/BA/PE/MA values. Pick MG and no column showed your real freight. Grid A's first column is now your own UF and mode.
B26: Second grid added | C26: Grid B trades bid level against supplier discount at your real freight — the two things you can actually negotiate.
B27: Tax bracket cross-checked | C27: Check 9 compares the RBT12 you typed against the revenue your win-count implies. The old default sat in the 4,00% band while the plan implied a 7,58% one.
B28: BOM sorted by cost | C28: Largest line first, each as a % of goods cost, unpriced line highlighted and counted rather than passing through as a silent zero.
B30: THINGS WORTH ARGUING WITH
B31: The 45% discount | C31: Nothing in this workbook works at 0% off list. Almost everything works at 45%. That single unverified number IS the business. Get it in writing before anything else happens.
B32: Parcel freight | C32: At R$116–188 per kit, PAC exceeds the entire gross margin on a R$269 bid. In Grid A the parcel columns are red at every discount level including 50%. Parcel delivery is not a worse version of this business — it is a different business that does not work.
B33: The written plan's 52% gross margin | C33: The plan assumes ~52% gross and R$360k of sales at 21 wins. With this BOM and this freight the same lot models at about 6% gross. One of the two documents is wrong, and the one with supplier CNPJs on every line is not it.
B34: Coari concentration | C34: The plan notes one Amazon town is 34,8% of the winnable margin. Nothing in this model reflects that, and freight to AM is unmeasured. Model it before counting on it.
